Workbook

Sheet Welcome Page
B3: Welcome!
B4: to the Amazing Race (US) data spreadsheet
B5: Created by wavesei (Sam)
B7: Backstory:
B8: When I was in college, I somehow found myself addicted to the Amazing Race (TAR). I was facinated with the traveling, storylines, and amazing moments throughout, and I knew that it was new dream of my to be on the show. To be able to take part in the most compelling reality show of all time, to take part of my own storyline, to hear Phil say that I'm team number 1. Anyways, I was watching old seasons, when I noticed that there are many similarities between seasons, and I became obsessed with tracking how each season/race was ran. I was never much of a stats guy, but I wanted to be in the mind of the show's creators, in case I ever get the oppotunity to take part in this race that so many love. I began "logging" each season of the race in composition notebooks. I have some scans of a few pages below, including my first and last page. In these entries with my God-awful handwriting, I would log what season it was at the top and separate each leg, normally fitting two on a page. I also dated each entry, to track my progress. Each leg would note where racers traveled to (normally incorrectly), if the leg was elimination or not, what type of clue was read for each challenge, a brief description of each challenge, twists that happened, who got eliminated/saved from elimination and briefly why, and what keywords were seen in this leg. I invented these keywords as I noticed similarities between seasons, to see how the building blocks of the race changed over time. I started this journey of watching and logging each season of TAR in June 2021 with Season 32, and finished this month, July 2024 with Season 35. Yes, it took me three years. Sometimes life got busy with work and school, but I watched and logged when I could. In this process I would mostly work backwards, but sometimes jumped all over the place. Truthfully I do not specifically remember when 20-year-old me decided to start this, but I'm glad I saw this project through to completion, and I imagine some cool stuff can be done with this data. I should note that to properly understand this spreadsheet, you have seen at least one episode of TAR, hopefully an entire season. I tried to explain everything for the casual viewer, but I'm sure there is necessary detail this spreadsheet is lacking for someone who has never watched TAR before to understand. I would first start with reading "Sheets Information", to see what each tab is meant for, or just click whatever it's your life. I'm sure that over this three-year-process I made plenty of mistakes, and if you notice any while viewing this document, please reach out and let me know! Obviously, I want this spreadsheet to be as accurate as possible. Huge thank you to Wikipedia and TAR Wiki on making data on the race so easily accessible. Happy viewing!
B46: Sheets Information:
B47: Logs | D47: This is where the physical logging (on paper) was translated to. Each season's challenges, eliminations, twists, keywords, locations, and winners are logged.
B48: Keywords | D48: Each keyword is explained when and why they are used, and tracked for use in each season.
B49: Race Locations | D49: The countries and geographical areas ran to in each leg of every season are listed here, and each country and area is tracked per leg and in totality. Maps for each season of the race are also included.
B50: Challenges | D50: This sheet tracks the total amount of challenges in each season, and explains the niche challenges in certain seasons, such as the Hazard.
B51: Route Info | D51: Dedicated to tracking the amount of Route Info challenges per season.
B52: Road Block | D52: Dedicated to tracking the amount of Road Block challenges per season.
B53: Detour | D53: Dedicated to tracking the amount of Detour challenges per season.
B54: Fast Forward | D54: Dedicated to tracking the amount of Fast Forward challenges per season.
B55: Speed Bump | D55: Dedicated to tracking the amount of Speed Bump challenges per season.
B56: Leg-by-Leg | D56: This sheet is for tracking the amount of each challenge type for every leg of every season, then examining them in totality.
B57: Challenge-by-Challenge | D57: This sheet is for tracking the amount of each challenge for every challenge on every leg of every season, then examining them in totality.
B58: Leg-by-Challenge | D58: This sheet is for tracking the amount of challenge per leg.
... B67: Season 37 | D67: The actual most-recently filmed season of the race, this sheet also examines how it is different from past seasons.
B69: Notes for the Future:
B70: There are some things that I wish to add to this spreadsheet in the future, in the goal of tracking every piece of data in TAR:
B72: - Money given at the start of each leg
B73: - Adding in common triggers for each episode
B74: - More statistics and tracking of changes over the course of TAR (again, I've never been much for stats).
B75: - Start Times
B76: - Track the amount of miles traveled per Season
B77: - Detour twists (blind Detours, e.g.)

Sheet Logs
B4: Season Logs
K5: Template way over there -->
B6: Season 1 | BT6: Season Template
B7: Winners = Rob and Brennan | E7: Filmed: 3/8/01 - 4/8/01 | Q7: Keywords | BT7: Winners = | BW7: Filmed: | CI7: Keywords
B8: Challenges | C8: Leg 1 | D8: Leg 2 | E8: Leg 3 | F8: Leg 4 | G8: Leg 5 | H8: Leg 6 | I8: Leg 7 | J8: Leg 8 | K8: Leg 9 | L8: Leg 10 | M8: Leg 11 | N8: Leg 12 | O8: Leg 13 | Q8: Leg 1 | R8: Leg 2 | S8: Leg 3 | T8: Leg 4 | U8: Leg 5 | V8: Leg 6 | W8: Leg 7 | X8: Leg 8 | Y8: Leg 9 | Z8: Leg 10 | AA8: Leg 11 | AB8: Leg 12 | AC8: Leg 13 | BT8: Challenges | BU8: Leg 1 | BV8: Leg 2 | BW8: Leg 3 | BX8: Leg 4 | BY8: Leg 5 | BZ8: Leg 6 | CA8: Leg 7 | CB8: Leg 8 | CC8: Leg 9 | CD8: Leg 10 | CE8: Leg 11 | CF8: Leg 12 | CG8: Leg 13 | CI8: Leg 1 | CJ8: Leg 2 | CK8: Leg 3 | CL8: Leg 4 | CM8: Leg 5 | CN8: Leg 6 | CO8: Leg 7 | CP8: Leg 8 | CQ8: Leg 9 | CR8: Leg 10 | CS8: Leg 11 | CT8: Leg 12 | CU8: Leg 13
B9: 1 | C9: Route Info | D9: Fast Forward | E9: Fast Forward | F9: Fast Forward | G9: Fast Forward | H9: Route Info | I9: Fast Forward | J9: Route Info | K9: Fast Forward | L9: Fast Forward | M9: Fast Forward | N9: Route Info | O9: Route Info | Q9: Driving | R9: Travel Issues | S9: Language | T9: Flags | U9: Driving | V9: Searching | W9: Searching | X9: Searching | Y9: Counting | Z9: Physical Strength | AA9: Hand Eye Coordination | AB9: Physical Strength | AC9: Physical Strength | BT9: 1
B10: 2 | C10: Route Info | D10: Route Info | E10: Route Info | F10: Route Info | G10: Route Info | H10: Fast Forward | I10: Detour | J10: Fast Forward | K10: Route Info | L10: Route Info | M10: Route Info | N10: Route Info | O10: Detour | Q10: Travel Issues | R10: Physical Strength | S10: Physical Strength | T10: Travel Issues | U10: Puzzle | V10: Travel Issues | W10: Biking | X10: Animals | Y10: Searching | Z10: Travel Issues | AA10: Language | AB10: Searching | AC10: Animals | BT10: 2
B11: 3 | C11: Fast Forward | D11: Detour | E11: Detour | F11: Detour | G11: Detour | H11: Route Info | I11: Route Info | J11: Route Info | K11: Detour | L11: Detour | M11: Detour | N11: Detour | O11: Road Block | Q11: Physical Strength | R11: Puzzle | T11: Searching | U11: Searching | V11: Driving | W11: Heights | X11: Travel Issues | Y11: Animals | Z11: Heights | AA11: Searching | AB11: Driving | AC11: Pain | BT11: 3
B12: 4 | C12: Route Info | D12: Route Info | E12: Route Info | F12: Route Info | G12: Route Info | H12: Detour | I12: Road Block | J12: Detour | K12: Road Block | L12: Route Info | M12: Route Info | N12: Route Info | O12: Route Info | Q12: Heights | R12: Driving | T12: Pain | U12: Animals | V12: Navigation | W12: Navigation | Z12: Searching | AA12: Food | AB12: Travel Issues | BT12: 4
B13: 5 | C13: Detour | D13: Road Block | E13: Road Block | F13: Road Block | G13: Road Block | H13: Route Info | I13: Route Info | J13: Route Info | K13: Route Info | L13: Road Block | M13: Route Info | N13: Route Info | O13: Route Info | R13: Searching | T13: Animals | U13: Physical Strength | W13: Travel Issues | Z13: Swimming | AA13: Travel Issues | BT13: 5
B14: 6 | C14: Route Info | E14: Route Info | G14: Route Info | H14: Road Block | J14: Road Block | L14: Route Info | M14: Road Block | N14: Route Info | U14: Navigation | BT14: 6
B15: 7 | J15: Route Info | L15: Route Info | N15: Road Block | BT15: 7
B16: 8 | N16: Route Info | BT16: 8
B17: 9 | Q17: Destinations | BT17: 9 | CI17: Destinations
B18: 10 | Q18: Leg 1 | R18: Leg 2 | S18: Leg 3 | T18: Leg 4 | U18: Leg 5 | V18: Leg 6 | W18: Leg 7 | X18: Leg 8 | Y18: Leg 9 | Z18: Leg 10 | AA18: Leg 11 | AB18: Leg 12 | AC18: Leg 13 | BT18: 10 | CI18: Leg 1 | CJ18: Leg 2 | CK18: Leg 3 | CL18: Leg 4 | CM18: Leg 5 | CN18: Leg 6 | CO18: Leg 7 | CP18: Leg 8 | CQ18: Leg 9 | CR18: Leg 10 | CS18: Leg 11 | CT18: Leg 12 | CU18: Leg 13
B19: Elimination? | C19: Yes | D19: Yes | E19: Yes | F19: Yes | G19: Yes | H19: No | I19: Yes | J19: No | K19: Yes | L19: No | M19: Yes | N19: No | O19: Final Leg | Q19: NYC, USA | R19: Livingston District, Zambia | S19: Paris, France | T19: Les Baux-de-Provence, France | U19: El Djem, Tunisia | V19: Gabes, Tunisia | W19: Sant'Agata Bolognese, Italy | X19: Agra, India | Y19: Bikaner, India | Z19: Krabi, Thailand | AA19: Ao Nang, Thailand | AB19: Beijing, China | AC19: Trapper Creek, USA | BT19: Elimination?
Q20: Livingston, Zambia | R20: Mosi-oa-Tunya Nat'l Park, Zambia | S20: Les Baux-de-Provence, France | T20: Tunis, Tunisia | U20: Tatouine, Tunisia | V20: La Marsa, Tunisia | W20: Ferrara, Italy | X20: Jaipur, India | Y20: Bangkok, Thailand | Z20: Ao Phang Nga Nat'l Park, Thailand | AA20: Beijing, China | AB20: Scotty Lake, USA | AC20: Talkeetna, USA | BT20: U-Turn/Yield?
Q21: Mosi-oa-Tunya Nat'l Park, Zambia | R21: Paris, France | T21: El Djem, Tunisia | U21: Jebil Nat'l Park, Tunisia | V21: Rome, Italy | W21: Delhi, India | X21: Amber, India | Y21: Kanchanaburi, Thailand | Z21: Ao Nang, Thailand | AB21: Glacier View, USA | AC21: NYC, USA | BT21: Express Pass/Safe?
Q22: Livingston District, Zambia | V22: San Cesario sul Panaro, Italy | W22: Agra, India | X22: Deshnoke, India | Y22: Krabi, Thailand | AB22: Trapper Creek, USA
V23: Sant'Agata Bolognese, Italy | X23: Bikaner, India
B24: Season 2
B25: Winners = Chris and Alex | E25: Filmed: 1/7/02 - 3/3/02 | Q25: Keywords
B26: Challenges | C26: Leg 1 | D26: Leg 2 | E26: Leg 3 | F26: Leg 4 | G26: Leg 5 | H26: Leg 6 | I26: Leg 7 | J26: Leg 8 | K26: Leg 9 | L26: Leg 10 | M26: Leg 11 | N26: Leg 12 | O26: Leg 13 | Q26: Leg 1 | R26: Leg 2 | S26: Leg 3 | T26: Leg 4 | U26: Leg 5 | V26: Leg 6 | W26: Leg 7 | X26: Leg 8 | Y26: Leg 9 | Z26: Leg 10 | AA26: Leg 11 | AB26: Leg 12 | AC26: Leg 13
B27: 1 | C27: Route Info | D27: Route Info | E27: Route Info | F27: Route Info | G27: Fast Forward | H27: Fast Forward | I27: Route Info | J27: Fast Forward | K27: Fast Forward | L27: Fast Forward | M27: Route Info | N27: Route Info | O27: Route Info | Q27: Driving | R27: Hand Eye Coordination | S27: Dancing | T27: Driving | U27: Travel Issues | V27: Searching | W27: Searching | X27: Physical Strength | Y27: Heights | Z27: Driving | AA27: Driving | AB27: Driving | AC27: Driving
B28: 2 | C28: Route Info | D28: Fast Forward | E28: Fast Forward | F28: Route Info | G28: Route Info | H28: Route Info | I28: Route Info | J28: Route Info | K28: Route Info | L28: Route Info | M28: Fast Forward | N28: Route Info | O28: Route Info | Q28: Heights | R28: Heights | S28: Selling | T28: Searching | U28: Searching | V28: Travel Issues | W28: Driving | X28: Language | Y28: Driving | Z28: Heights | AA28: Travel Issues | AB28: Searching | AC28: Physical Strength
B29: 3 | C29: Fast Forward | D29: Route Info | E29: Route Info | F29: Fast Forward | G29: Detour | H29: Detour | I29: Fast Forward | J29: Route Info | K29: Route Info | L29: Route Info | M29: Route Info | N29: Route Info | O29: Route Info | Q29: Searching | R29: Searching | S29: Travel Issues | T29: Physical Strength | V29: Driving | W29: Food | Y29: Food | Z29: Physical Strength | AA29: Heights | AB29: Biking
B30: 4 | C30: Route Info | D30: Detour | E30: Detour | F30: Route Info | G30: Route Info | H30: Route Info | I30: Route Info | J30: Detour | K30: Detour | L30: Detour | M30: Detour | N30: Detour | O30: Route Info | Q30: Travel Issues | R30: Driving | S30: Food | T30: Swimming | V30: Balance | W30: Travel Issues | Y30: Searching | Z30: Travel Issues | AA30: Physical Strength | AB30: Swimming
B31: 5 | C31: Detour | D31: Route Info | E31: Route Info | F31: Route Info | G31: Road Block | H31: Road Block | I31: Detour | J31: Route Info | K31: Route Info | L31: Route Info | M31: Route Info | N31: Route Info | O31: Route Info | R31: Travel Issues | T31: Travel Issues | V31: Physical Strength | W31: Hand Eye Coordination | Y31: Physical Strength | Z31: Animals | AB31: Physical Strength
B32: 6 | C32: Route Info | D32: Route Info | E32: Road Block | F32: Detour | G32: Route Info | H32: Route Info | I32: Route Info | J32: Road Block | K32: Road Block | L32: Road Block | M32: Road Block | N32: Road Block | O32: Route Info | R32: Physical Strength | V32: Animals | Y32: Hand Eye Coordination | AB32: Travel Issues
B33: 7 | D33: Road Block | F33: Route Info | I33: Road Block | J33: Route Info | K33: Route Info | M33: Route Info | N33: Route Info | O33: Road Block
B34: 8 | D34: Route Info | F34: Route Info | I34: Route Info | O34: Route Info
B35: 9 | F35: Road Block | O35: Route Info | Q35: Destinations
B36: 10 | F36: Route Info | Q36: Leg 1 | R36: Leg 2 | S36: Leg 3 | T36: Leg 4 | U36: Leg 5 | V36: Leg 6 | W36: Leg 7 | X36: Leg 8 | Y36: Leg 9 | Z36: Leg 10 | AA36: Leg 11 | AB36: Leg 12 | AC36: Leg 13
B37: Elimination? | C37: Yes | D37: Yes | E37: Yes | F37: Yes | G37: Yes | H37: No | I37: Yes | J37: No | K37: Yes | L37: No | M37: Yes | N37: No | O37: Final Leg | Q37: Pahrump, USA | R37: Rio de Janero, Brazil | S37: Foz do Iguacu, Brazil | T37: Stellenbosch, South Africa | U37: Windhock, Namibia | V37: Amphawa, Thailand | W37: Karen Village, Thailand | X37: Hong Kong, China | Y37: Sydney, Australia | Z37: Coober Pedy, Australia | AA37: Cantaburry Plains, New Zealand | AB37: Auckland, New Zealand | AC37: Maui, USA
Q38: Rio de Janero, Brazil | R38: Foz do Iguacu, Brazil | S38: Capetown, South Africa | T38: Walvis Bay, Namibia | U38: Bankok, Thailand | V38: Bankok, Thailand | W38: Chiang Mai, Thailand | X38: Sydney, Australia | Y38: Coober Pedy, Australia | Z38: Queenstown, New Zealand | AA38: Rotorua, New Zealand | AB38: Maui, USA | AC38: Hana Bay, USA
S39: Stellenbosch, South Africa | T39: Swakopmund, Namibia | U39: Ratchaburi, Thaliand | V39: Mongou, Thailand | W39: Hong Kong, China | Z39: Gibbston, New Zealand | AA39: Waitomo Caves, New Zealand | AC39: Anchorage, USA
T40: Spitzkopf, Namibia | U40: Amphawa, Thailand | V40: Mae Ping Village, Thailand | Z40: Cantaburry Plains, New Zealand | AA40: Auckland, New Zealand | AC40: Big Lake, USA
T41: Windhock, Namibia | V41: Karen Village, Thailand | AC41: San Fran, USA
B42: Season 3
B43: Winners = Flo and Zach | E43: Filmed: 8/9/02 - 9/8/02 | Q43: Keywords
B44: Challenges | C44: Leg 1 | D44: Leg 2 | E44: Leg 3 | F44: Leg 4 | G44: Leg 5 | H44: Leg 6 | I44: Leg 7 | J44: Leg 8 | K44: Leg 9 | L44: Leg 10 | M44: Leg 11 | N44: Leg 12 | O44: Leg 13 | Q44: Leg 1 | R44: Leg 2 | S44: Leg 3 | T44: Leg 4 | U44: Leg 5 | V44: Leg 6 | W44: Leg 7 | X44: Leg 8 | Y44: Leg 9 | Z44: Leg 10 | AA44: Leg 11 | AB44: Leg 12 | AC44: Leg 13
B45: 1 | C45: Route Info | D45: Fast Forward | E45: Fast Forward | F45: Fast Forward | G45: Fast Forward | H45: Route Info | I45: Route Info | J45: Route Info | K45: Route Info | L45: Route Info | M45: Route Info | N45: Route Info | O45: Route Info | Q45: Driving | R45: Driving | S45: Driving | T45: Driving | U45: Heights | V45: Searching | W45: Balance | X45: Driving | Y45: Driving | Z45: Flags | AA45: Searching | AB45: Searching | AC45: Driving
B46: 2 | C46: Route Info | D46: Route Info | E46: Route Info | F46: Route Info | G46: Route Info | H46: Fast Forward | I46: Fast Forward | J46: Fast Forward | K46: Fast Forward | L46: Route Info | M46: Fast Forward | N46: Route Info | O46: Route Info | Q46: Heights | R46: Physical Strength | S46: Biking | T46: Travel Issues | U46: Physical Strength | V46: Driving | W46: Travel Issues | X46: Searching | Y46: Food | Z46: Searching | AA46: Selling | AB46: Travel Issues | AC46: Heights
B47: 3 | C47: Fast Forward | D47: Route Info | E47: Detour | F47: Route Info | G47: Detour | H47: Route Info | I47: Route Info | J47: Route Info | K47: Route Info | L47: Route Info | M47: Route Info | N47: Detour | O47: Route Info | Q47: Searching | R47: Travel Issues | S47: Physical Strength | T47: Hand Eye Coordination | U47: Driving | V47: Travel Issues | W47: Heights | X47: Counting | Y47: Heights | Z47: Swimming | AA47: Biking | AB47: Balance | AC47: Physical Strength
B48: 4 | C48: Route Info | D48: Detour | E48: Route Info | F48: Detour | G48: Route Info | H48: Detour | I48: Detour | J48: Route Info | K48: Detour | L48: Route Info | M48: Detour | N48: Route Info | O48: Detour | Q48: Navigation | R48: Searching | S48: Travel Issues | T48: Physical Strength | U48: Travel Issues | V48: Language | W48: Driving | X48: Hand Eye Coordination | Y48: Animals | Z48: Driving | AA48: Physical Strength | AB48: Physical Strength | AC48: Travel Issues
B49: 5 | C49: Detour | D49: Route Info | E49: Road Block | F49: Route Info | G49: Route Info | H49: Route Info | I49: Route Info | J49: Detour | K49: Route Info | L49: Detour | M49: Route Info | N49: Road Block | O49: Route Info | Q49: Animals | R49: Swimming | S49: Hand Eye Coordination | U49: Searching | V49: Selling | X49: Physical Strength | Y49: Building | Z49: Travel Issues | AB49: Biking | AC49: Memorization
B50: 6 | C50: Route Info | D50: Road Block | E50: Route Info | F50: Road Block | G50: Road Block | H50: Road Block | I50: Road Block | J50: Route Info | K50: Road Block | L50: Fast Forward | M50: Road Block | N50: Route Info | O50: Route Info | Q50: Travel Issues | R50: Heights | V50: Animals | Y50: Attention to Detail
B51: 7 | D51: Route Info | F51: Route Info | G51: Route Info | H51: Route Info | I51: Route Info | J51: Road Block | K51: Route Info | L51: Route Info | O51: Route Info | Y51: Biking
B52: 8 | J52: Route Info | L52: Road Block | O52: Road Block
B53: 9 | L53: Route Info | O53: Route Info | Q53: Destinations
B54: 10 | Q54: Leg 1 | R54: Leg 2 | S54: Leg 3 | T54: Leg 4 | U54: Leg 5 | V54: Leg 6 | W54: Leg 7 | X54: Leg 8 | Y54: Leg 9 | Z54: Leg 10 | AA54: Leg 11 | AB54: Leg 12 | AC54: Leg 13
B55: Elimination? | C55: Yes | D55: Yes | E55: Yes | F55: Yes | G55: Yes | H55: Yes | I55: Yes | J55: No | K55: No | L55: Yes | M55: Yes | N55: No | O55: Final Leg | Q55: Everglades, USA | R55: Puente de Ixtla, Mexico | S55: Talum, Mexico | T55: Stonehaven, Scotland | U55: Lisbon, Portugal | V55: Fez, Morocco | W55: Marrakesh, Morocco | X55: Schwangau, Germany | Y55: Grindelwald, Switzerland | Z55: Lausanne, Switzerland | AA55: Mount Faber, Singapore | AB55: Ho Chi Minh City, Vientnam | AC55: Da nang, Vietnam
Q56: Mexico City, Mexico | R56: Teotihuacan, Mexico | S56: Duxford, England | T56: Porta, Portugal | U56: Cabo de Roca, Portugal | V56: Casablanca, Morocco | W56: Munich, Germany | X56: Schaffhausen, Switzerland | Y56: Saxeten, Switzerland | Z56: Geneva, Switzerland | AA56: Ho Chi Minh City, Vientnam | AB56: Hue, Vietnam | AC56: Honolulu, USA
Q57: Puente de Ixtla, Mexico | R57: Mexico City, Mexico | S57: Cambridge, England | T57: Lisbon, Portugal | U57: Tangier, Morocco | V57: Marrakesh, Morocco | W57: Innsbruck, Austria | X57: Zurich, Switzerland | Y57: Kandersteg, Switzerland | Z57: Kuala Limpur, Malaysia | AA57: Cai Bei, Vietnam | AB57: Da Nang, Vietnam | AC57: Kauai, USA
R58: Cancun, Mexico | S58: Stonehaven, Scotland | U58: Fez, Morocco | W58: Schwangau, Germany | X58: Grindelwald, Switzerland | Y58: Niouc, Switzerland | Z58: Singapore | AA58: Ho Chi Minh City, Vientnam | AB58: Hoi An, Vietnam | AC58: Seattle, USA
R59: Tulum, Mexico | Y59: Veytaux, Switzerland | Z59: Mount Faber, Singapore | AB59: Da Nang, Vietnam
B60: Season 4
B61: Winners = Reichen and Chip | E61: Filmed: 1/18/03 - 2/14/03 | Q61: Keywords
B62: Challenges | C62: Leg 1 | D62: Leg 2 | E62: Leg 3 | F62: Leg 4 | G62: Leg 5 | H62: Leg 6 | I62: Leg 7 | J62: Leg 8 | K62: Leg 9 | L62: Leg 10 | M62: Leg 11 | N62: Leg 12 | O62: Leg 13 | Q62: Leg 1 | R62: Leg 2 | S62: Leg 3 | T62: Leg 4 | U62: Leg 5 | V62: Leg 6 | W62: Leg 7 | X62: Leg 8 | Y62: Leg 9 | Z62: Leg 10 | AA62: Leg 11 | AB62: Leg 12 | AC62: Leg 13
B63: 1 | C63: Route Info | D63: Route Info | E63: Route Info | F63: Route Info | G63: Route Info | H63: Route Info | I63: Route Info | J63: Route Info | K63: Route Info | L63: Route Info | M63: Route Info | N63: Route Info | O63: Route Info | Q63: Searching | R63: Searching | S63: Balance | T63: Driving | U63: Driving | V63: Biking | W63: Searching | X63: Physical Strength | Y63: Driving | Z63: Searching | AA63: Heights | AB63: Driving | AC63: Heights
B64: 2 | C64: Route Info | D64: Fast Forward | E64: Fast Forward | F64: Road Block | G64: Fast Forward | H64: Fast Forward | I64: Fast Forward | J64: Fast Forward | K64: Fast Forward | L64: Route Info | M64: Fast Forward | N64: Route Info | O64: Route Info | Q64: Driving | R64: Navigation | S64: Travel Issues | T64: Heights | U64: Searching | V64: Searching | W64: Travel Issues | X64: Travel Issues | Y64: Animals | Z64: Travel Issues | AA64: Physical Strength | AB64: Searching | AC64: Navigation
B65: 3 | C65: Fast Forward | D65: Route Info | E65: Route Info | F65: Route Info | G65: Route Info | H65: Route Info | I65: Route Info | J65: Route Info | K65: Route Info | L65: Fast Forward | M65: Route Info | N65: Route Info | O65: Detour | Q65: Heights | S65: Heights | T65: Travel Issues | U65: Physical Strength | V65: Travel Issues | W65: Animals | X65: Animals | Y65: Physical Strength | Z65: Physical Strength | AA65: Driving | AB65: Animals | AC65: Swimming
B66: 4 | C66: Route Info | D66: Detour | E66: Detour | F66: Fast Forward | G66: Detour | H66: Detour | I66: Road Block | J66: Detour | K66: Detour | L66: Route Info | M66: Detour | N66: Route Info | O66: Route Info | Q66: Travel Issues | S66: Physical Strength | T66: Puzzle | U66: Animals | V66: Physical Strength | W66: Biking | X66: Hand Eye Coordination | Y66: Pain | Z66: Pain | AA66: Swimming | AB66: Physical Strength | AC66: Puzzle
B67: 5 | C67: Detour | D67: Route Info | E67: Route Info | F67: Route Info | G67: Route Info | H67: Route Info | I67: Route Info | J67: Route Info | K67: Route Info | L67: Road Block | M67: Route Info | N67: Detour | O67: Road Block | Q67: Physical Strength | W67: Navigation | Y67: Heights | Z67: Swimming | AA67: Animals | AB67: Travel Issues | AC67: Travel Issues
B68: 6 | C68: Route Info | D68: Road Block | E68: Road Block | F68: Detour | G68: Road Block | H68: Road Block | I68: Detour | J68: Road Block | K68: Road Block | L68: Route Info | M68: Road Block | N68: Route Info | O68: Route Info | Z68: Food
B69: 7 | D69: Route Info | E69: Route Info | F69: Route Info | G69: Route Info | H69: Route Info | I69: Route Info | K69: Route Info | L69: Detour | M69: Route Info | N69: Road Block | O69: Route Info
B70: 8 | L70: Route Info | N70: Route Info | O70: Route Info
B71: 9 | O71: Route Info | Q71: Destinations
B72: 10 | O72: Route Info | Q72: Leg 1 | R72: Leg 2 | S72: Leg 3 | T72: Leg 4 | U72: Leg 5 | V72: Leg 6 | W72: Leg 7 | X72: Leg 8 | Y72: Leg 9 | Z72: Leg 10 | AA72: Leg 11 | AB72: Leg 12 | AC72: Leg 13
B73: Elimination? | C73: Yes | D73: Yes | E73: Yes | F73: Yes | G73: Yes | H73: Yes | I73: Yes | J73: No | K73: Yes | L73: No | M73: Yes | N73: No | O73: Final Leg | Q73: LA, USA | R73: Cortina d'Ampezzo, Italy | S73: Venice, Italy | T73: Gmunden, Austria | U73: Saint Remy-de-Provence, France | V73: Muiden, Netherlands | W73: Mumbai, India | X73: Alleppey, India | Y73: Manukan Island, Malaysia | Z73: Sepilok, Malaysia | AA73: Seoul, South Korea | AB73: Mooloolaba, Australia | AC73: Ellis Beach, Australia
Q74: Milan, Italy | R74: Venice, Italy | S74: Vienna, Austria | T74: Le Mans, France | U74: Amsterdam, Netherlands | V74: Mumbai, India | W74: Ernakulam, India | X74: Kota Kinabala, Malaysia | Y74: Ranau, Malaysia | Z74: Sandakan, Malaysia | AA74: Sunshine Coast, Australia | AB74: Ferny Hills, Australia | AC74: Smithfield, Australia
Q75: Cortina d'Ampezzo, Italy | S75: Gmunden, Austria | T75: Gorges du Blavet, France | U75: Alkmaar, Netherlands | W75: Alleppey, India | X75: Manukan Island, Malaysia | Y75: Sepilok, Malaysia | Z75: Seoul, South Korea | AA75: Brisbane, Australia | AB75: Cairns, Australia | AC75: Kaulana Bay, USA
T76: Marseilles, France | U76: Monnickendam, Netherlands | Y76: Sandakan, Malaysia | Z76: Cheorwon, South Korea | AA76: Mooloolaba, Australia | AB76: Wangetti, Australia | AC76: Hawaii Volcanos National Park, USA
T77: Aix-en-Provence, France | U77: Muiden, Netherlands | Y77: Kinbatangan, Malaysia | Z77: Seoul, South Korea | AB77: Julatten, Australia | AC77: Phoenix, USA
B78: Season 5 | T78: Bagnols-en-Foret, France | Y78: Sepilok, Malaysia | AB78: Ellis Beach, Australia
B79: Winners = Chip and Kim | E79: Filmed: 1/30/04 - 2/27/04 | Q79: Keywords | T79: Saint Remy-de-Provence, France
B80: Challenges | C80: Leg 1 | D80: Leg 2 | E80: Leg 3 | F80: Leg 4 | G80: Leg 5 | H80: Leg 6 | I80: Leg 7 | J80: Leg 8 | K80: Leg 9 | L80: Leg 10 | M80: Leg 11 | N80: Leg 12 | O80: Leg 13 | Q80: Leg 1 | R80: Leg 2 | S80: Leg 3 | T80: Leg 4 | U80: Leg 5 | V80: Leg 6 | W80: Leg 7 | X80: Leg 8 | Y80: Leg 9 | Z80: Leg 10 | AA80: Leg 11 | AB80: Leg 12 | AC80: Leg 13
B81: 1 | C81: Route Info | D81: Route Info | E81: Route Info | F81: Route Info | G81: Route Info | H81: Route Info | I81: Route Info | J81: Route Info | K81: Route Info | L81: Route Info | M81: Route Info | N81: Route Info | O81: Route Info | Q81: Driving | R81: Driving | S81: Driving | T81: Driving | U81: Searching | V81: Animals | W81: Biking | X81: Driving | Y81: Driving | Z81: Driving | AA81: Driving | AB81: Searching | AC81: Physical Strength
B82: 2 | C82: Route Info | D82: Route Info | E82: Route Info | F82: Detour | G82: Route Info | H82: Route Info | I82: Route Info | J82: Route Info | K82: Route Info | L82: Detour | M82: Road Block | N82: Route Info | O82: Route Info | Q82: Physical Strength | R82: Searching | S82: Food | T82: Hand Eye Coordination | U82: Physical Strength | V82: Searching | W82: Animals | X82: Travel Issues | Y82: Heights | Z82: Swimming | AA82: Physical Strength | AB82: Flags | AC82: Travel Issues
B83: 3 | C83: Route Info | D83: Detour | E83: Road Block | F83: Route Info | G83: Fast Forward | H83: Detour | I83: Detour | J83: Road Block | K83: Route Info | L83: Route Info | M83: Route Info | N83: Route Info | O83: Road Block | Q83: Heights | R83: Navigation | S83: Heights | T83: Travel Issues | U83: Travel Issues | V83: Travel Issues | W83: Physical Strength | X83: Heights | Y83: Travel Issues | Z83: Searching | AA83: Heights | AB83: Swimming | AC83: Biking
B84: 4 | C84: Route Info | D84: Route Info | E84: Route Info | F84: Route Info | G84: Route Info | H84: Route Info | I84: Route Info | J84: Route Info | K84: Fast Forward | L84: Road Block | M84: Route Info | N84: Route Info | O84: Route Info | Q84: Travel Issues | R84: Animals | S84: Biking | T84: Food | U84: Puzzle | V84: Physical Strength | W84: Cooking | X84: Navigation | Y84: Physical Strength | Z84: Travel Issues | AA84: Attention to Detail | AB84: Heights | AC84: Searching
B85: 5 | C85: Route Info | D85: Road Block | E85: Detour | F85: Road Block | G85: Road Block | H85: Road Block | I85: Road Block | J85: Detour | K85: Route Info | M85: Route Info | N85: Route Info | O85: Route Info | R85: Physical Strength | S85: Travel Issues | U85: Animals | W85: Food | X85: Animals | Y85: Pain | Z85: Physical Strength | AA85: Animals | AB85: Physical Strength
B86: 6 | C86: Route Info | D86: Route Info | E86: Route Info | F86: Route Info | G86: Route Info | H86: Route Info | I86: Route Info | J86: Route Info | K86: Road Block | M86: Detour | N86: Road Block | O86: Detour | R86: Travel Issues | W86: Travel Issues
B87: 7 | C87: Detour | G87: Detour | K87: Route Info | M87: Route Info | N87: Route Info | O87: Route Info
B88: 8 | C88: Route Info | G88: Route Info | K88: Detour | O88: Route Info | Q88: Destinations
B89: 9 | K89: Route Info | O89: Route Info | Q89: Leg 1 | R89: Leg 2 | S89: Leg 3 | T89: Leg 4 | U89: Leg 5 | V89: Leg 6 | W89: Leg 7 | X89: Leg 8 | Y89: Leg 9 | Z89: Leg 10 | AA89: Leg 11 | AB89: Leg 12 | AC89: Leg 13
B90: 10 | Q90: Santa Monica, USA | R90: Punta Ballena, Uruguay | S90: San Antonio de Areco, Argentina | T90: Rio Negro, Argentina | U90: Pushkin, Russia | V90: Giza, Egypt | W90: Luxor, Egypt | X90: Lake Manyara, Tanzania | Y90: Margham, UAE | Z90: Kolkata, India | AA90: Paengaroa, New Zealand | AB90: Pasay, Philippines | AC90: El Nido, Philippines
B91: Elimination? | C91: Yes | D91: Yes | E91: Yes | F91: Yes | G91: No | H91: Yes | I91: Yes | J91: No | K91: No | L91: Yes | M91: No | N91: Yes | O91: Final Leg | Q91: Punta del Este, Uruguay | R91: Montavideo, Uruguay | S91: San Carlos de Bariloche, Argentina | T91: St. Petersburg, Russia | U91: St. Petersburg, Russia | V91: Luxor, Egypt | W91: Kilimanjaro, Tanzania | X91: Dubai, UAE | Y91: Kolkata, India | Z91: Rotorua, New Zealand | AA91: Aukland, New Zealand | AB91: Manilla, Philippines | AC91: Calgary, Canada
B92: Twist | C92: Yield | D92: Yield | E92: Yield | F92: Yield | G92: Yield | H92: Yield | I92: Yield | J92: Yield | K92: Yield | L92: Yield | M92: Yield | N92: Yield | Q92: Gorriti Island, Uruguay | R92: Buenos Aires, Argentina | S92: Villa Cerro Catedral, Argentina | T92: Pushkin, Russia | U92: Cairo, Egypt | W92: Mto wa Mbu, Tanzania | X92: Margham, UAE | Y92: Garia, India | Z92: Paengaroa, New Zealand | AA92: Manilla, Philippines | AB92: El Nido, Philippines | AC92: Dallas, USA
B93: *NOTE: Yields on every leg, but not all were shown | Q93: Punta del Este, Uruguay | R93: San Antonio de Areco, Argentina | S93: Rio Negro, Argentina | U93: Giza, Egypt | W93: Kibaoni, Tanzania | Y93: Kolkata, India | AA93: Imus, Philippines
Q94: Maldonado, Uruguay | W94: Lake Manyara, Tanzania | AA94: Victoria, Philippines
Q95: Punta del Este, Uruguay | AA95: Pasay, Philippines
Q96: Punta Ballena, Uruguay
B97: Season 6
B98: Winners = Freddy and Kendra | E98: Filmed: 8/13/04 - 9/12/04
B99: Challenges | C99: Leg 1 | D99: Leg 2 | E99: Leg 3 | F99: Leg 4 | G99: Leg 5 | H99: Leg 6 | I99: Leg 7 | J99: Leg 8 | K99: Leg 9 | L99: Leg 10 | M99: Leg 11 | N99: Leg 12 | Q99: Keywords
B100: 1 | C100: Route Info | D100: Route Info | E100: Route Info | F100: Route Info | G100: Route Info | H100: Route Info | I100: Route Info | J100: Route Info | K100: Route Info | L100: Route Info | M100: Route Info | N100: Route Info | Q100: Leg 1 | R100: Leg 2 | S100: Leg 3 | T100: Leg 4 | U100: Leg 5 | V100: Leg 6 | W100: Leg 7 | X100: Leg 8 | Y100: Leg 9 | Z100: Leg 10 | AA100: Leg 11 | AB100: Leg 12
B101: 2 | C101: Route Info | D101: Road Block | E101: Route Info | F101: Route Info | G101: Route Info | H101: Route Info | I101: Route Info | J101: Route Info | K101: Route Info | L101: Route Info | M101: Detour | N101: Detour | Q101: Driving | R101: Heights | S101: Driving | T101: Travel Issues | U101: Searching | V101: Heights | W101: Driving | X101: Navigation | Y101: Physical Strength | Z101: Travel Issues | AA101: Searching | AB101: Driving
B102: 3 | C102: Route Info | D102: Route Info | E102: Route Info | F102: Route Info | G102: Route Info | H102: Road Block | I102: Fast Forward | J102: Route Info | K102: Route Info | L102: Road Block | M102: Route Info | N102: Route Info | Q102: Travel Issues | R102: Driving | S102: Biking | T102: Animals | U102: Cooking | V102: Driving | W102: Physical Strength | X102: Physical Strength | Y102: Heights | Z102: Heights | AA102: Physical Strength | AB102: Searching
B103: 4 | C103: Route Info | D103: Route Info | E103: Detour | F103: Route Info | G103: Detour | H103: Route Info | I103: Route Info | J103: Detour | K103: Detour | L103: Route Info | M103: Route Info | N103: Road Block | Q103: Physical Strength | R103: Travel Issues | S103: Hand Eye Coordination | T103: Physical Strength | U103: Travel Issues | V103: Physical Strength | W103: Searching | X103: Animals | Y103: Animals | Z103: Physical Strength | AA103: Travel Issues | AB103: Physical Strength
...

Sheet SQL_Data
A1: Season_Num | B1: Leg_Num | C1: Challenge_1 | D1: Challenge_2 | E1: Challenge_3 | F1: Challenge_4 | G1: Challenge_5 | H1: Challenge_6 | I1: Challenge_7 | J1: Challenge_8 | K1: Challenge_9 | L1: Challenge_10 | M1: Challenge_11 | N1: Challenge_12 | O1: Challenge_13
A2: 1 | B2: 1 | C2: Route Info | D2: Route Info | E2: Fast Forward | F2: Route Info | G2: Detour | H2: Route Info
A3: 1 | B3: 2 | C3: Fast Forward | D3: Route Info | E3: Detour | F3: Route Info | G3: Road Block | Q3: SQL Query Maker
A4: 1 | B4: 3 | C4: Fast Forward | D4: Route Info | E4: Detour | F4: Route Info | G4: Road Block | H4: Route Info | Q4: In each of the dropdowns, either select an option, or leave it blank! SQL will show a list below that meets the requirements you specified. This Query tracks challenges, locations, eliminations, and twists for each season and leg. If your selections have not happened before, the query will return blank. If all the dropdowns are left blank, then information from every leg will return.
A5: 1 | B5: 4 | C5: Fast Forward | D5: Route Info | E5: Detour | F5: Route Info | G5: Road Block | Q5: Season # | R5: Leg # | S5: Challenge 1 | T5: Challenge 2 | U5: Challenge 3 | V5: Challenge 4 | W5: Challenge 5 | X5: Challenge 6 | Y5: Challenge 7 | Z5: Challenge 8 | AA5: Challenge 9 | AB5: Challenge 10 | AC5: Challenge 11 | AD5: Challenge 12 | AE5: Challenge 13 | AF5: Country | AG5: Area of World | AH5: Elimination | AI5: Twist
A6: 1 | B6: 5 | C6: Fast Forward | D6: Route Info | E6: Detour | F6: Route Info | G6: Road Block | H6: Route Info
A7: 1 | B7: 6 | C7: Route Info | D7: Fast Forward | E7: Route Info | F7: Detour | G7: Route Info | H7: Road Block | P7: {=_xldudf_SQLOOKUP(_xlfn._LONGTEXT(" SELECT challenges.Season_Num as 'Season #', challenges.Leg_Num as 'Leg #', challenges.Challenge_1 as 'Challenge 1', challenges.Challenge_2 as 'Challenge 2', challenges.Challenge_3 as 'Challenge 3', challenges.Challenge_4 as 'Challenge 4', challenges.Cha","llenge_5 as 'Challenge 5', challenges.Challenge_6 as 'Challenge 6', challenges.Challenge_7 as 'Challenge 7', challenges.Challenge_8 as 'Challenge 8', challenges.Challenge_9 as 'Challenge 9', challenges.Challenge_10 as 'Challenge 10', challenges.Challenge_","11 as 'Challenge 11', challenges.Challenge_12 as 'Challenge 12', challenges.Challenge_13 as 'Challenge 13', locations.Country, locations.Geographic_Area as 'Area of World', elimination.Elimination, twists.Twist, twists.Challenge_Num as 'Twist Challenge #'",", winners.Winning_Team as 'Leg Winner' FROM challenges INNER JOIN locations ON challenges.Season_Num=locations.Season_Num AND challenges.Leg_Num=locations.Leg_Num INNER JOIN elimination ON challenges.Season_Num=elimination.Season_Num AND challenges.Leg_Nu","m=elimination.Leg_Num INNER JOIN twists ON challenges.Season_Num=twists.Season_Num AND challenges.Leg_Num=twists.Leg_Num INNER JOIN winners ON challenges.Season_Num=winners.Season_Num AND challenges.Leg_Num=winners.Leg_Num WHERE ('")&R6&"' = '' OR challenges.Leg_Num = '"&R6&"') AND ('"&Q6&"' = '' OR challenges.Season_Num = '"&Q6&"') AND ('"&S6&"' = '' OR challenges.Challenge_1 = '"&S6&"') AND ('"&T6&"' = '' OR challenges.Challenge_2 = '"&T6&"') AND ('"&U6&"' = '' OR challenges.Challenge_3 = '"&U6&"') AND ('"&V6&"' = '' OR challenges.Challenge_4 = '"&V6&"') AND ('"&W6&"' = '' OR challenges.Challenge_5 = '"&W6&"') AND ('"&X6&"' = '' OR challenges.Challenge_6 = '"&X6&"') AND ('"&Y6&"' = '' OR challenges.Challenge_7 = '"&Y6&"') AND ('"&Z6&"' = '' OR challenges.Challenge_8 = '"&Z6&"') AND ('"&AA6&"' = '' OR challenges.Challenge_9 = '"&AA6&"') AND ('"&AB6&"' = '' OR challenges.Challenge_10 = '"&AB6&"') AND ('"&AC6&"' = '' OR challenges.Challenge_11 = '"&AC6&"') AND ('"&AD6&"' = '' OR challenges.Challenge_12 = '"&AD6&"') AND ('"&AE6&"' = '' OR challenges.Challenge_13 = '"&AE6&"') AND ('"&AF6&"' = '' OR locations.Country = '"&AF6&"') AND ('"&AG6&"' = '' OR locations.Geographic_Area = '"&AG6&"') AND ('"&AH6&"' = '' OR elimination.Elimination = '"&AH6&"') AND ('"&AI6&"' = '' OR twists.Twist = '"&AI6&"')", "challenges", $A$1:$O$458, "locations", A460:D917, "elimination", A920:C1377, "twists", A1380:D1837, "winners", A1840:C2297)} -> Season # | Q7: Leg # | R7: Challenge 1 | S7: Challenge 2 | T7: Challenge 3 | U7: Challenge 4 | V7: Challenge 5 | W7: Challenge 6 | X7: Challenge 7 | Y7: Challenge 8 | Z7: Challenge 9 | AA7: Challenge 10 | AB7: Challenge 11 | AC7: Challenge 12 | AD7: Challenge 13 | AE7: Country | AF7: Area of World | AG7: Elimination | AH7: Twist | AI7: Twist Challenge # | AJ7: Leg Winner | AN7: {=_xldudf_SQLOOKUP(_xlfn._LONGTEXT("SELECT COUNT(*) as 'Your query returned this many legs:' FROM challenges INNER JOIN locations ON challenges.Season_Num=locations.Season_Num AND challenges.Leg_Num=locations.Leg_Num INNER JOIN elimination ON challenges.Season_Num=elimination.Season_Num AND"," challenges.Leg_Num=elimination.Leg_Num INNER JOIN twists ON challenges.Season_Num=twists.Season_Num AND challenges.Leg_Num=twists.Leg_Num INNER JOIN winners ON challenges.Season_Num=winners.Season_Num AND challenges.Leg_Num=winners.Leg_Num WHERE ('")&R6&"' = '' OR challenges.Leg_Num = '"&R6&"') AND ('"&Q6&"' = '' OR challenges.Season_Num = '"&Q6&"') AND ('"&S6&"' = '' OR challenges.Challenge_1 = '"&S6&"') AND ('"&T6&"' = '' OR challenges.Challenge_2 = '"&T6&"') AND ('"&U6&"' = '' OR challenges.Challenge_3 = '"&U6&"') AND ('"&V6&"' = '' OR challenges.Challenge_4 = '"&V6&"') AND ('"&W6&"' = '' OR challenges.Challenge_5 = '"&W6&"') AND ('"&X6&"' = '' OR challenges.Challenge_6 = '"&X6&"') AND ('"&Y6&"' = '' OR challenges.Challenge_7 = '"&Y6&"') AND ('"&Z6&"' = '' OR challenges.Challenge_8 = '"&Z6&"') AND ('"&AA6&"' = '' OR challenges.Challenge_9 = '"&AA6&"') AND ('"&AB6&"' = '' OR challenges.Challenge_10 = '"&AB6&"') AND ('"&AC6&"' = '' OR challenges.Challenge_11 = '"&AC6&"') AND ('"&AD6&"' = '' OR challenges.Challenge_12 = '"&AD6&"') AND ('"&AE6&"' = '' OR challenges.Challenge_13 = '"&AE6&"') AND ('"&AF6&"' = '' OR locations.Country = '"&AF6&"') AND ('"&AG6&"' = '' OR locations.Geographic_Area = '"&AG6&"') AND ('"&AH6&"' = '' OR elimination.Elimination = '"&AH6&"') AND ('"&AI6&"' = '' OR twists.Twist = '"&AI6&"')", "challenges", $A$1:$O$458, "locations", A460:D917, "elimination", A920:C1377, "twists", A1380:D1837, "winners", A1840:C2297)} -> Your query returned this many legs:
A8: 1 | B8: 7 | C8: Fast Forward | D8: Detour | E8: Route Info | F8: Road Block | G8: Route Info | P8: 1 | Q8: 1 | R8: Route Info | S8: Route Info | T8: Fast Forward | U8: Route Info | V8: Detour | W8: Route Info | AE8: Zambia | AF8: Southern Africa | AG8: Yes | AJ8: Rob & Brennan | AN8: 457
A9: 1 | B9: 8 | C9: Route Info | D9: Fast Forward | E9: Route Info | F9: Detour | G9: Route Info | H9: Road Block | I9: Route Info | P9: 1 | Q9: 2 | R9: Fast Forward | S9: Route Info | T9: Detour | U9: Route Info | V9: Road Block | AE9: France | AF9: Western Europe | AG9: Yes | AJ9: Pat & Brenda
A10: 1 | B10: 9 | C10: Fast Forward | D10: Route Info | E10: Detour | F10: Road Block | G10: Route Info | P10: 1 | Q10: 3 | R10: Fast Forward | S10: Route Info | T10: Detour | U10: Route Info | V10: Road Block | W10: Route Info | AE10: France | AF10: Western Europe | AG10: Yes | AJ10: Kevin & Drew
A11: 1 | B11: 10 | C11: Fast Forward | D11: Route Info | E11: Detour | F11: Route Info | G11: Road Block | H11: Route Info | I11: Route Info | P11: 1 | Q11: 4 | R11: Fast Forward | S11: Route Info | T11: Detour | U11: Route Info | V11: Road Block | AE11: Tunisia | AF11: Northern Africa | AG11: Yes | AJ11: Joe & Bill
A12: 1 | B12: 11 | C12: Fast Forward | D12: Route Info | E12: Detour | F12: Route Info | G12: Route Info | H12: Road Block | P12: 1 | Q12: 5 | R12: Fast Forward | S12: Route Info | T12: Detour | U12: Route Info | V12: Road Block | W12: Route Info | AE12: Tunisia | AF12: Northern Africa | AG12: Yes | AJ12: Kevin & Drew
A13: 1 | B13: 12 | C13: Route Info | D13: Route Info | E13: Detour | F13: Route Info | G13: Route Info | H13: Route Info | I13: Road Block | J13: Route Info | P13: 1 | Q13: 6 | R13: Route Info | S13: Fast Forward | T13: Route Info | U13: Detour | V13: Route Info | W13: Road Block | AE13: Italy | AF13: Southern Europe | AG13: No | AJ13: Frank & Margarita
A14: 1 | B14: Final | C14: Route Info | D14: Detour | E14: Road Block | F14: Route Info | G14: Route Info | P14: 1 | Q14: 7 | R14: Fast Forward | S14: Detour | T14: Route Info | U14: Road Block | V14: Route Info | AE14: India | AF14: South Asia | AG14: Yes | AJ14: Frank & Margarita
A15: 2 | B15: 1 | C15: Route Info | D15: Route Info | E15: Fast Forward | F15: Route Info | G15: Detour | H15: Route Info | P15: 1 | Q15: 8 | R15: Route Info | S15: Fast Forward | T15: Route Info | U15: Detour | V15: Route Info | W15: Road Block | X15: Route Info | AE15: India | AF15: South Asia | AG15: No | AJ15: Kevin & Drew
A16: 2 | B16: 2 | C16: Route Info | D16: Fast Forward | E16: Route Info | F16: Detour | G16: Route Info | H16: Route Info | I16: Road Block | J16: Route Info | P16: 1 | Q16: 9 | R16: Fast Forward | S16: Route Info | T16: Detour | U16: Road Block | V16: Route Info | AE16: Thailand | AF16: South East Asia | AG16: Yes | AJ16: Rob & Brennan
A17: 2 | B17: 3 | C17: Route Info | D17: Fast Forward | E17: Route Info | F17: Detour | G17: Route Info | H17: Road Block | P17: 1 | Q17: 10 | R17: Fast Forward | S17: Route Info | T17: Detour | U17: Route Info | V17: Road Block | W17: Route Info | X17: Route Info | AE17: Thailand | AF17: South East Asia | AG17: No | AJ17: Rob & Brennan
A18: 2 | B18: 4 | C18: Route Info | D18: Route Info | E18: Fast Forward | F18: Route Info | G18: Route Info | H18: Detour | I18: Route Info | J18: Route Info | K18: Road Block | L18: Route Info | P18: 1 | Q18: 11 | R18: Fast Forward | S18: Route Info | T18: Detour | U18: Route Info | V18: Route Info | W18: Road Block | AE18: China | AF18: East Asia | AG18: Yes | AJ18: Frank & Margarita
A19: 2 | B19: 5 | C19: Fast Forward | D19: Route Info | E19: Detour | F19: Route Info | G19: Road Block | H19: Route Info | P19: 1 | Q19: 12 | R19: Route Info | S19: Route Info | T19: Detour | U19: Route Info | V19: Route Info | W19: Route Info | X19: Road Block | Y19: Route Info | AE19: USA | AF19: North America | AG19: No | AJ19: Rob & Brennan | AQ19: Dropdown Lists
A20: 2 | B20: 6 | C20: Fast Forward | D20: Route Info | E20: Detour | F20: Route Info | G20: Road Block | H20: Route Info | P20: 1 | Q20: Final | R20: Route Info | S20: Detour | T20: Road Block | U20: Route Info | V20: Route Info | AE20: USA | AF20: North America | AG20: Final Leg | AJ20: Rob & Brennan | AP20: Season # | AQ20: Leg # | AR20: Challenge Type | AS20: Country | AT20: Area | AU20: Elimination | AV20: Twist
A21: 2 | B21: 7 | C21: Route Info | D21: Route Info | E21: Fast Forward | F21: Route Info | G21: Detour | H21: Route Info | I21: Road Block | J21: Route Info | P21: 2 | Q21: 1 | R21: Route Info | S21: Route Info | T21: Fast Forward | U21: Route Info | V21: Detour | W21: Route Info | AE21: Brazil | AF21: South America | AG21: Yes | AJ21: Tara & Wil | AP21: 1 | AQ21: 1 | AR21: Route Info | AS21: Argentina | AT21: Caribbean | AU21: Yes | AV21: Double U-Turn
A22: 2 | B22: 8 | C22: Fast Forward | D22: Route Info | E22: Route Info | F22: Detour | G22: Route Info | H22: Road Block | I22: Route Info | P22: 2 | Q22: 2 | R22: Route Info | S22: Fast Forward | T22: Route Info | U22: Detour | V22: Route Info | W22: Route Info | X22: Road Block | Y22: Route Info | AE22: Brazil | AF22: South America | AG22: Yes | AJ22: Shola & Doyin | AP22: 2 | AQ22: 2 | AR22: Road Block | AS22: Armenia | AT22: Central America | AU22: No | AV22: Driver's Seat
A23: 2 | B23: 9 | C23: Fast Forward | D23: Route Info | E23: Route Info | F23: Detour | G23: Route Info | H23: Road Block | I23: Route Info | P23: 2 | Q23: 3 | R23: Route Info | S23: Fast Forward | T23: Route Info | U23: Detour | V23: Route Info | W23: Road Block | AE23: South Africa | AF23: Southern Africa | AG23: Yes | AJ23: Oswald & Danny | AP23: 3 | AQ23: 3 | AR23: Detour | AS23: Australia | AT23: Central Europe | AU23: Final Leg | AV23: Express Pass
A24: 2 | B24: 10 | C24: Fast Forward | D24: Route Info | E24: Route Info | F24: Detour | G24: Route Info | H24: Road Block | P24: 2 | Q24: 4 | R24: Route Info | S24: Route Info | T24: Fast Forward | U24: Route Info | V24: Route Info | W24: Detour | X24: Route Info | Y24: Route Info | Z24: Road Block | AA24: Route Info | AE24: Namibia | AF24: Southern Africa | AG24: Yes | AJ24: Oswald & Danny | AP24: 4 | AQ24: 4 | AR24: Fast Forward | AS24: Austria | AT24: East Africa | AV24: Head-to-Head
A25: 2 | B25: 11 | C25: Route Info | D25: Fast Forward | E25: Route Info | F25: Detour | G25: Route Info | H25: Road Block | I25: Route Info | P25: 2 | Q25: 5 | R25: Fast Forward | S25: Route Info | T25: Detour | U25: Route Info | V25: Road Block | W25: Route Info | AE25: Thailand | AF25: South East Asia | AG25: Yes | AJ25: Chris & Alex | AP25: 5 | AQ25: 5 | AR25: Speed Bump | AS25: Azerbaijan | AT25: East Asia | AV25: Intersection
A26: 2 | B26: 12 | C26: Route Info | D26: Route Info | E26: Route Info | F26: Detour | G26: Route Info | H26: Road Block | I26: Route Info | P26: 2 | Q26: 6 | R26: Fast Forward | S26: Route Info | T26: Detour | U26: Route Info | V26: Road Block | W26: Route Info | AE26: Thailand | AF26: South East Asia | AG26: No | AJ26: Mary & Peach | AP26: 6 | AQ26: 6 | AR26: Hazard | AS26: Bahrain | AT26: Eastern Europe | AV26: Partner Swap
A27: 2 | B27: Final | C27: Route Info | D27: Route Info | E27: Route Info | F27: Route Info | G27: Route Info | H27: Route Info | I27: Road Block | J27: Route Info | K27: Route Info | P27: 2 | Q27: 7 | R27: Route Info | S27: Route Info | T27: Fast Forward | U27: Route Info | V27: Detour | W27: Route Info | X27: Road Block | Y27: Route Info | AE27: China | AF27: East Asia | AG27: Yes | AJ27: Gary & Dave | AP27: 7 | AQ27: 7 | AR27: Express Pass | AS27: Bangladesh | AT27: Middle East | AV27: Save
A28: 3 | B28: 1 | C28: Route Info | D28: Route Info | E28: Fast Forward | F28: Route Info | G28: Detour | H28: Route Info | P28: 2 | Q28: 8 | R28: Fast Forward | S28: Route Info | T28: Route Info | U28: Detour | V28: Route Info | W28: Road Block | X28: Route Info | AE28: Australia | AF28: Oceania | AG28: No | AJ28: Oswald & Danny | AP28: 8 | AQ28: 8 | AR28: City Sprint | AS28: Barbados | AT28: North America | AV28: Scramble
A29: 3 | B29: 2 | C29: Fast Forward | D29: Route Info | E29: Route Info | F29: Detour | G29: Route Info | H29: Road Block | I29: Route Info | P29: 2 | Q29: 9 | R29: Fast Forward | S29: Route Info | T29: Route Info | U29: Detour | V29: Route Info | W29: Road Block | X29: Route Info | AE29: Australia | AF29: Oceania | AG29: Yes | AJ29: Chris & Alex | AP29: 9 | AQ29: 9 | AR29: Fork-in-Road | AS29: Belgium | AT29: Northern Africa | AV29: U-Turn
A30: 3 | B30: 3 | C30: Fast Forward | D30: Route Info | E30: Detour | F30: Route Info | G30: Road Block | H30: Route Info | P30: 2 | Q30: 10 | R30: Fast Forward | S30: Route Info | T30: Route Info | U30: Detour | V30: Route Info | W30: Road Block | AE30: New Zealand | AF30: Oceania | AG30: No | AJ30: Blake & Paige | AP30: 10 | AQ30: 10 | AS30: Bolivia | AT30: Northern Europe | AV30: Yield
A31: 3 | B31: 4 | C31: Fast Forward | D31: Route Info | E31: Route Info | F31: Detour | G31: Route Info | H31: Road Block | I31: Route Info | P31: 2 | Q31: 11 | R31: Route Info | S31: Fast Forward | T31: Route Info | U31: Detour | V31: Route Info | W31: Road Block | X31: Route Info | AE31: New Zealand | AF31: Oceania | AG31: Yes | AJ31: Tara & Wil | AP31: 11 | AQ31: 11 | AS31: Botswana | AT31: Oceania
A32: 3 | B32: 5 | C32: Fast Forward | D32: Route Info | E32: Detour | F32: Route Info | G32: Route Info | H32: Road Block | I32: Route Info | P32: 2 | Q32: 12 | R32: Route Info | S32: Route Info | T32: Route Info | U32: Detour | V32: Route Info | W32: Road Block | X32: Route Info | AE32: USA | AF32: North America | AG32: No | AJ32: Tara & Wil\nBlake & Paige | AP32: 12 | AQ32: 12 | AS32: Brazil | AT32: South America
A33: 3 | B33: 6 | C33: Route Info | D33: Fast Forward | E33: Route Info | F33: Detour | G33: Route Info | H33: Road Block | I33: Route Info | P33: 2 | Q33: Final | R33: Route Info | S33: Route Info | T33: Route Info | U33: Route Info | V33: Route Info | W33: Route Info | X33: Road Block | Y33: Route Info | Z33: Route Info | AE33: USA | AF33: North America | AG33: Final Leg | AJ33: Chris & Alex | AP33: 13 | AQ33: Final | AS33: Bulgaria | AT33: South Asia
A34: 3 | B34: 7 | C34: Route Info | D34: Fast Forward | E34: Route Info | F34: Detour | G34: Route Info | H34: Road Block | I34: Route Info | P34: 3 | Q34: 1 | R34: Route Info | S34: Route Info | T34: Fast Forward | U34: Route Info | V34: Detour | W34: Route Info | AE34: Mexico | AF34: North America | AG34: Yes | AJ34: Ken & Gerard | AP34: 14 | AS34: Burkina Faso | AT34: South East Asia
A35: 3 | B35: 8 | C35: Route Info | D35: Fast Forward | E35: Route Info | F35: Route Info | G35: Detour | H35: Route Info | I35: Road Block | J35: Route Info | P35: 3 | Q35: 2 | R35: Fast Forward | S35: Route Info | T35: Route Info | U35: Detour | V35: Route Info | W35: Road Block | X35: Route Info | AE35: Mexico | AF35: North America | AG35: Yes | AJ35: Derek & Drew | AP35: 15 | AS35: Cambodia | AT35: Southern Africa
A36: 3 | B36: 9 | C36: Route Info | D36: Fast Forward | E36: Route Info | F36: Detour | G36: Route Info | H36: Road Block | I36: Route Info | P36: 3 | Q36: 3 | R36: Fast Forward | S36: Route Info | T36: Detour | U36: Route Info | V36: Road Block | W36: Route Info | AE36: England\nScotland | AF36: Western Europe\nWestern Europe | AG36: Yes | AJ36: Derek & Drew | AP36: 16 | AS36: Canada | AT36: Southern Europe
A37: 3 | B37: 10 | C37: Route Info | D37: Route Info | E37: Route Info | F37: Route Info | G37: Detour | H37: Fast Forward | I37: Route Info | J37: Road Block | K37: Route Info | P37: 3 | Q37: 4 | R37: Fast Forward | S37: Route Info | T37: Route Info | U37: Detour | V37: Route Info | W37: Road Block | X37: Route Info | AE37: Portugal | AF37: Western Europe | AG37: Yes | AJ37: Ken & Gerard | AP37: 17 | AS37: Chile | AT37: West Africa
A38: 3 | B38: 11 | C38: Route Info | D38: Fast Forward | E38: Route Info | F38: Detour | G38: Route Info | H38: Road Block | P38: 3 | Q38: 5 | R38: Fast Forward | S38: Route Info | T38: Detour | U38: Route Info | V38: Route Info | W38: Road Block | X38: Route Info | AE38: Morocco | AF38: Northern Africa | AG38: Yes | AJ38: Ken & Gerard | AP38: 18 | AS38: China | AT38: West Asia
A39: 3 | B39: 12 | C39: Route Info | D39: Route Info | E39: Detour | F39: Route Info | G39: Road Block | H39: Route Info | P39: 3 | Q39: 6 | R39: Route Info | S39: Fast Forward | T39: Route Info | U39: Detour | V39: Route Info | W39: Road Block | X39: Route Info | AE39: Morocco | AF39: Northern Africa | AG39: Yes | AJ39: Teri & Ian | AP39: 19 | AS39: Colombia | AT39: Western Europe
A40: 3 | B40: Final | C40: Route Info | D40: Route Info | E40: Route Info | F40: Detour | G40: Route Info | H40: Route Info | I40: Route Info | J40: Road Block | K40: Route Info | P40: 3 | Q40: 7 | R40: Route Info | S40: Fast Forward | T40: Route Info | U40: Detour | V40: Route Info | W40: Road Block | X40: Route Info | AE40: Germany\nAustria | AF40: Central Europe\nCentral Europe | AG40: Yes | AJ40: Flo & Zach | AP40: 20 | AS40: Costa Rica
A41: 4 | B41: 1 | C41: Route Info | D41: Route Info | E41: Fast Forward | F41: Route Info | G41: Detour | H41: Route Info | P41: 3 | Q41: 8 | R41: Route Info | S41: Fast Forward | T41: Route Info | U41: Route Info | V41: Detour | W41: Route Info | X41: Road Block | Y41: Route Info | AE41: Switzerland | AF41: Central Europe | AG41: No | AJ41: Derek & Drew | AP41: 21 | AS41: Croatia
A42: 4 | B42: 2 | C42: Route Info | D42: Fast Forward | E42: Route Info | F42: Detour | G42: Route Info | H42: Road Block | I42: Route Info | P42: 3 | Q42: 9 | R42: Route Info | S42: Fast Forward | T42: Route Info | U42: Detour | V42: Route Info | W42: Road Block | X42: Route Info | AE42: Switzerland | AF42: Central Europe | AG42: No | AJ42: John Vito & Jill | AP42: 22 | AS42: Czech Republic
A43: 4 | B43: 3 | C43: Route Info | D43: Fast Forward | E43: Route Info | F43: Detour | G43: Route Info | H43: Road Block | I43: Route Info | P43: 3 | Q43: 10 | R43: Route Info | S43: Route Info | T43: Route Info | U43: Route Info | V43: Detour | W43: Fast Forward | X43: Route Info | Y43: Road Block | Z43: Route Info | AE43: Malaysia\nSingapore | AF43: South East Asia\nSouth East Asia | AG43: Yes | AJ43: Derek & Drew | AP43: 23 | AS43: Denmark
A44: 4 | B44: 4 | C44: Route Info | D44: Road Block | E44: Route Info | F44: Fast Forward | G44: Route Info | H44: Detour | I44: Route Info | P44: 3 | Q44: 11 | R44: Route Info | S44: Fast Forward | T44: Route Info | U44: Detour | V44: Route Info | W44: Road Block | AE44: Vietnam | AF44: South East Asia | AG44: Yes | AJ44: Teri & Ian | AP44: 24 | AS44: Dominican Republic
A45: 4 | B45: 5 | C45: Route Info | D45: Fast Forward | E45: Route Info | F45: Detour | G45: Route Info | H45: Road Block | I45: Route Info | P45: 3 | Q45: 12 | R45: Route Info | S45: Route Info | T45: Detour | U45: Route Info | V45: Road Block | W45: Route Info | AE45: Vietnam | AF45: South East Asia | AG45: No | AJ45: Teri & Ian | AP45: 25 | AS45: Ecuador
A46: 4 | B46: 6 | C46: Route Info | D46: Fast Forward | E46: Route Info | F46: Detour | G46: Route Info | H46: Road Block | I46: Route Info | P46: 3 | Q46: Final | R46: Route Info | S46: Route Info | T46: Route Info | U46: Detour | V46: Route Info | W46: Route Info | X46: Route Info | Y46: Road Block | Z46: Route Info | AE46: USA | AF46: North America | AG46: Final Leg | AJ46: Flo & Zach | AP46: 26 | AS46: Egypt
A47: 4 | B47: 7 | C47: Route Info | D47: Fast Forward | E47: Route Info | F47: Road Block | G47: Route Info | H47: Detour | I47: Route Info | P47: 4 | Q47: 1 | R47: Route Info | S47: Route Info | T47: Fast Forward | U47: Route Info | V47: Detour | W47: Route Info | AE47: Italy | AF47: Western Europe | AG47: Yes | AJ47: Millie & Chuck\nSteve & Josh\nAmanda & Chris | AP47: 27 | AS47: England
A48: 4 | B48: 8 | C48: Route Info | D48: Fast Forward | E48: Route Info | F48: Detour | G48: Route Info | H48: Road Block | P48: 4 | Q48: 2 | R48: Route Info | S48: Fast Forward | T48: Route Info | U48: Detour | V48: Route Info | W48: Road Block | X48: Route Info | AE48: Italy | AF48: Southern Europe | AG48: Yes | AJ48: Steve & Dave | AP48: 28 | AS48: Estonia
A49: 4 | B49: 9 | C49: Route Info | D49: Fast Forward | E49: Route Info | F49: Detour | G49: Route Info | H49: Road Block | I49: Route Info | P49: 4 | Q49: 3 | R49: Route Info | S49: Fast Forward | T49: Route Info | U49: Detour | V49: Route Info | W49: Road Block | X49: Route Info | AE49: Austria | AF49: Central Europe | AG49: Yes | AJ49: Steve & Josh | AP49: 29 | AS49: Ethiopia
A50: 4 | B50: 10 | C50: Route Info | D50: Route Info | E50: Fast Forward | F50: Route Info | G50: Road Block | H50: Route Info | I50: Detour | J50: Route Info | P50: 4 | Q50: 4 | R50: Route Info | S50: Road Block | T50: Route Info | U50: Fast Forward | V50: Route Info | W50: Detour | X50: Route Info | AE50: France | AF50: Western Europe | AG50: Yes | AJ50: Tian & Jaree | AP50: 30 | AS50: Finland
A51: 4 | B51: 11 | C51: Route Info | D51: Fast Forward | E51: Route Info | F51: Detour | G51: Route Info | H51: Road Block | I51: Route Info | P51: 4 | Q51: 5 | R51: Route Info | S51: Fast Forward | T51: Route Info | U51: Detour | V51: Route Info | W51: Road Block | X51: Route Info | AE51: Netherlands | AF51: Central Europe | AG51: Yes | AJ51: Millie & Chuck | AP51: 31 | AS51: France
A52: 4 | B52: 12 | C52: Route Info | D52: Route Info | E52: Route Info | F52: Route Info | G52: Detour | H52: Route Info | I52: Road Block | J52: Route Info | P52: 4 | Q52: 6 | R52: Route Info | S52: Fast Forward | T52: Route Info | U52: Detour | V52: Route Info | W52: Road Block | X52: Route Info | AE52: India | AF52: South Asia | AG52: Yes | AJ52: David & Jeff | AP52: 32 | AS52: French Polynesia
A53: 4 | B53: Final | C53: Route Info | D53: Route Info | E53: Detour | F53: Route Info | G53: Road Block | H53: Route Info | I53: Route Info | J53: Route Info | K53: Route Info | L53: Route Info | P53: 4 | Q53: 7 | R53: Route Info | S53: Fast Forward | T53: Route Info | U53: Road Block | V53: Route Info | W53: Detour | X53: Route Info | AE53: India | AF53: South Asia | AG53: Yes | AJ53: David & Jeff | AP53: 33 | AS53: Georgia
A54: 5 | B54: 1 | C54: Route Info | D54: Route Info | E54: Route Info | F54: Route Info | G54: Route Info | H54: Route Info | I54: Detour | J54: Route Info | P54: 4 | Q54: 8 | R54: Route Info | S54: Fast Forward | T54: Route Info | U54: Detour | V54: Route Info | W54: Road Block | AE54: Malaysia | AF54: South East Asia | AG54: No | AJ54: Jon & Al | AP54: 34 | AS54: Germany
A55: 5 | B55: 2 | C55: Route Info | D55: Route Info | E55: Detour | F55: Route Info | G55: Road Block | H55: Route Info | P55: 4 | Q55: 9 | R55: Route Info | S55: Fast Forward | T55: Route Info | U55: Detour | V55: Route Info | W55: Road Block | X55: Route Info | AE55: Malaysia | AF55: South East Asia | AG55: Yes | AJ55: Reichen & Chip | AP55: 35 | AS55: Ghana
A56: 5 | B56: 3 | C56: Route Info | D56: Route Info | E56: Road Block | F56: Route Info | G56: Detour | H56: Route Info | P56: 4 | Q56: 10 | R56: Route Info | S56: Route Info | T56: Fast Forward | U56: Route Info | V56: Road Block | W56: Route Info | X56: Detour | Y56: Route Info | AE56: South Korea | AF56: East Asia | AG56: No | AJ56: Kelly & Jon | AP56: 36 | AS56: Greece
A57: 5 | B57: 4 | C57: Route Info | D57: Detour | E57: Route Info | F57: Route Info | G57: Road Block | H57: Route Info | P57: 4 | Q57: 11 | R57: Route Info | S57: Fast Forward | T57: Route Info | U57: Detour | V57: Route Info | W57: Road Block | X57: Route Info | AE57: Australia | AF57: Oceania | AG57: Yes | AJ57: David & Jeff | AP57: 37 | AS57: Guam
A58: 5 | B58: 5 | C58: Route Info | D58: Route Info | E58: Fast Forward | F58: Route Info | G58: Road Block | H58: Route Info | I58: Detour | J58: Route Info | P58: 4 | Q58: 12 | R58: Route Info | S58: Route Info | T58: Route Info | U58: Route Info | V58: Detour | W58: Route Info | X58: Road Block | Y58: Route Info | AE58: Australia | AF58: Oceania | AG58: No | AJ58: David & Jeff | AP58: 38 | AS58: Hungary
A59: 5 | B59: 6 | C59: Route Info | D59: Route Info | E59: Detour | F59: Route Info | G59: Road Block | H59: Route Info | P59: 4 | Q59: Final | R59: Route Info | S59: Route Info | T59: Detour | U59: Route Info | V59: Road Block | W59: Route Info | X59: Route Info | Y59: Route Info | Z59: Route Info | AA59: Route Info | AE59: USA | AF59: North America | AG59: Final Leg | AJ59: Reichen & Chip | AS59: Iceland
A60: 5 | B60: 7 | C60: Route Info | D60: Route Info | E60: Detour | F60: Route Info | G60: Road Block | H60: Route Info | P60: 5 | Q60: 1 | R60: Route Info | S60: Route Info | T60: Route Info | U60: Route Info | V60: Route Info | W60: Route Info | X60: Detour | Y60: Route Info | AE60: Uruguay | AF60: South America | AG60: Yes | AH60: Yield | AI60: 6 | AJ60: Alison & Donny | AS60: India
A61: 5 | B61: 8 | C61: Route Info | D61: Route Info | E61: Road Block | F61: Route Info | G61: Detour | H61: Route Info | P61: 5 | Q61: 2 | R61: Route Info | S61: Route Info | T61: Detour | U61: Route Info | V61: Road Block | W61: Route Info | AE61: Argentina | AF61: South America | AG61: Yes | AH61: Yield | AI61: 3 | AJ61: Brandon & Nicole | AS61: Indonesia
A62: 5 | B62: 9 | C62: Route Info | D62: Route Info | E62: Route Info | F62: Fast Forward | G62: Route Info | H62: Road Block | I62: Route Info | J62: Detour | K62: Route Info | P62: 5 | Q62: 3 | R62: Route Info | S62: Route Info | T62: Road Block | U62: Route Info | V62: Detour | W62: Route Info | AE62: Argentina | AF62: South America | AG62: Yes | AH62: Yield | AI62: 3 | AJ62: Colin & Christie | AS62: Ireland
A63: 5 | B63: 10 | C63: Route Info | D63: Detour | E63: Route Info | F63: Road Block | P63: 5 | Q63: 4 | R63: Route Info | S63: Detour | T63: Route Info | U63: Route Info | V63: Road Block | W63: Route Info | AE63: Russia | AF63: Eastern Europe | AG63: Yes | AH63: Yield | AI63: 2 | AJ63: Chip & Kim | AS63: Italy
A64: 5 | B64: 11 | C64: Route Info | D64: Road Block | E64: Route Info | F64: Route Info | G64: Route Info | H64: Detour | I64: Route Info | P64: 5 | Q64: 5 | R64: Route Info | S64: Route Info | T64: Fast Forward | U64: Route Info | V64: Road Block | W64: Route Info | X64: Detour | Y64: Route Info | AE64: Egypt | AF64: Northern Africa | AG64: No | AH64: Yield | AI64: 5 | AJ64: Colin & Christie | AS64: Jamaica
A65: 5 | B65: 12 | C65: Route Info | D65: Route Info | E65: Route Info | F65: Route Info | G65: Route Info | H65: Road Block | I65: Route Info | P65: 5 | Q65: 6 | R65: Route Info | S65: Route Info | T65: Detour | U65: Route Info | V65: Road Block | W65: Route Info | AE65: Egypt | AF65: Northern Africa | AG65: Yes | AH65: Yield | AI65: 3 | AJ65: Colin & Christie | AS65: Japan
A66: 5 | B66: Final | C66: Route Info | D66: Route Info | E66: Road Block | F66: Route Info | G66: Route Info | H66: Detour | I66: Route Info | J66: Route Info | K66: Route Info | P66: 5 | Q66: 7 | R66: Route Info | S66: Route Info | T66: Detour | U66: Route Info | V66: Road Block | W66: Route Info | AE66: Tanzania | AF66: East Africa | AG66: Yes | AH66: Yield | AI66: 3 | AJ66: Chip & Kim | AS66: Jordan
A67: 6 | B67: 1 | C67: Route Info | D67: Route Info | E67: Route Info | F67: Route Info | G67: Route Info | H67: Route Info | I67: Detour | J67: Route Info | P67: 5 | Q67: 8 | R67: Route Info | S67: Route Info | T67: Road Block | U67: Route Info | V67: Detour | W67: Route Info | AE67: UAE | AF67: Middle East | AG67: No | AH67: Yield | AI67: 3 | AJ67: Colin & Christie | AS67: Kazakhstan
A68: 6 | B68: 2 | C68: Route Info | D68: Road Block | E68: Route Info | F68: Route Info | G68: Route Info | H68: Route Info | I68: Detour | J68: Route Info | P68: 5 | Q68: 9 | R68: Route Info | S68: Route Info | T68: Route Info | U68: Fast Forward | V68: Route Info | W68: Road Block | X68: Route Info | Y68: Detour | Z68: Route Info | AE68: India | AF68: South Asia | AG68: No | AH68: Yield | AI68: 4 | AJ68: Colin & Christie | AS68: Kuwait
A69: 6 | B69: 3 | C69: Route Info | D69: Route Info | E69: Route Info | F69: Detour | G69: Route Info | H69: Road Block | I69: Route Info | P69: 5 | Q69: 10 | R69: Route Info | S69: Detour | T69: Route Info | U69: Road Block | AE69: New Zealand | AF69: Oceania | AG69: Yes | AH69: Yield | AI69: 2 | AJ69: Colin & Christie | AS69: Laos
A70: 6 | B70: 4 | C70: Route Info | D70: Route Info | E70: Route Info | F70: Route Info | G70: Detour | H70: Route Info | I70: Road Block | J70: Route Info | P70: 5 | Q70: 11 | R70: Route Info | S70: Road Block | T70: Route Info | U70: Route Info | V70: Route Info | W70: Detour | X70: Route Info | AE70: Philippines | AF70: South East Asia | AG70: No | AH70: Yield | AI70: 4 | AJ70: Chip & Kim | AS70: Liechtenstein
A71: 6 | B71: 5 | C71: Route Info | D71: Route Info | E71: Route Info | F71: Detour | G71: Route Info | H71: Road Block | I71: Route Info | P71: 5 | Q71: 12 | R71: Route Info | S71: Route Info | T71: Route Info | U71: Route Info | V71: Route Info | W71: Road Block | X71: Route Info | AE71: Philippines | AF71: South East Asia | AG71: Yes | AH71: Yield | AI71: 4 | AJ71: Brandon & Nicole | AS71: Lithuania
A72: 6 | B72: 6 | C72: Route Info | D72: Route Info | E72: Road Block | F72: Route Info | G72: Detour | H72: Route Info | I72: Route Info | J72: Fast Forward | K72: Route Info | L72: Detour | M72: Route Info | N72: Road Block | O72: Route Info | P72: 5 | Q72: Final | R72: Route Info | S72: Route Info | T72: Road Block | U72: Route Info | V72: Route Info | W72: Detour | X72: Route Info | Y72: Route Info | Z72: Route Info | AE72: Canada\nUSA | AF72: North America | AG72: Final Leg | AJ72: Chip & Kim | AS72: Madagascar
A73: 6 | B73: 7 | C73: Route Info | D73: Route Info | E73: Fast Forward | F73: Route Info | G73: Detour | H73: Route Info | I73: Road Block | J73: Route Info | P73: 6 | Q73: 1 | R73: Route Info | S73: Route Info | T73: Route Info | U73: Route Info | V73: Route Info | W73: Route Info | X73: Detour | Y73: Route Info | AE73: Iceland | AF73: Northern Europe | AG73: Yes | AJ73: Hayden & Aaron | AS73: Malawi
A74: 6 | B74: 8 | C74: Route Info | D74: Route Info | E74: Route Info | F74: Detour | G74: Route Info | H74: Road Block | I74: Route Info | P74: 6 | Q74: 2 | R74: Route Info | S74: Road Block | T74: Route Info | U74: Route Info | V74: Route Info | W74: Route Info | X74: Detour | Y74: Route Info | AE74: Norway | AF74: Northern Europe | AG74: Yes | AJ74: Kris & Jon | AS74: Malaysia
A75: 6 | B75: 9 | C75: Route Info | D75: Route Info | E75: Route Info | F75: Detour | G75: Route Info | H75: Route Info | I75: Road Block | P75: 6 | Q75: 3 | R75: Route Info | S75: Route Info | T75: Route Info | U75: Detour | V75: Route Info | W75: Road Block | X75: Route Info | AE75: Sweden | AF75: Northern Europe | AG75: Yes | AH75: Yield | AI75: 6 | AJ75: Hayden & Aaron | AS75: Malta
A76: 6 | B76: 10 | C76: Route Info | D76: Route Info | E76: Road Block | F76: Route Info | G76: Route Info | H76: Detour | I76: Route Info | P76: 6 | Q76: 4 | R76: Route Info | S76: Route Info | T76: Route Info | U76: Route Info | V76: Detour | W76: Route Info | X76: Road Block | Y76: Route Info | AE76: Senegal | AF76: West Africa | AG76: No | AJ76: Kris & Jon | AS76: Mauritius
A77: 6 | B77: 11 | C77: Route Info | D77: Detour | E77: Route Info | F77: Route Info | G77: Road Block | H77: Route Info | P77: 6 | Q77: 5 | R77: Route Info | S77: Route Info | T77: Route Info | U77: Detour | V77: Route Info | W77: Road Block | X77: Route Info | AE77: Germany | AF77: Central Europe | AG77: Yes | AJ77: Freddy & Kendra | AS77: Mexico
A78: 6 | B78: Final | C78: Route Info | D78: Detour | E78: Route Info | F78: Road Block | G78: Route Info | H78: Route Info | I78: Route Info | P78: 6 | Q78: 6 | R78: Route Info | S78: Route Info | T78: Road Block | U78: Route Info | V78: Detour | W78: Route Info | X78: Route Info | Y78: Fast Forward | Z78: Route Info | AA78: Detour | AB78: Route Info | AC78: Road Block | AD78: Route Info | AE78: Hungary | AF78: Central Europe | AG78: Yes | AJ78: Lori & Bolo | AS78: Monaco
A79: 7 | B79: 1 | C79: Route Info | D79: Route Info | E79: Route Info | F79: Route Info | G79: Route Info | H79: Detour | I79: Route Info | J79: Route Info | P79: 6 | Q79: 7 | R79: Route Info | S79: Route Info | T79: Fast Forward | U79: Route Info | V79: Detour | W79: Route Info | X79: Road Block | Y79: Route Info | AE79: France | AF79: Western Europe | AG79: No | AJ79: Adam & Rebecca | AS79: Morocco
A80: 7 | B80: 2 | C80: Route Info | D80: Road Block | E80: Route Info | F80: Detour | G80: Route Info | P80: 6 | Q80: 8 | R80: Route Info | S80: Route Info | T80: Route Info | U80: Detour | V80: Route Info | W80: Road Block | X80: Route Info | AE80: France\nEthiopia | AF80: Western Europe\nEast Africa | AG80: Yes | AH80: Yield | AI80: 6 | AJ80: Hayden & Aaron | AS80: Mozambique
A81: 7 | B81: 3 | C81: Route Info | D81: Detour | E81: Route Info | F81: Road Block | G81: Route Info | P81: 6 | Q81: 9 | R81: Route Info | S81: Route Info | T81: Route Info | U81: Detour | V81: Route Info | W81: Route Info | X81: Road Block | AE81: Sri Lanka | AF81: South Asia | AG81: Yes | AJ81: Kris & Jon | AS81: Namibia
A82: 7 | B82: 4 | C82: Route Info | D82: Road Block | E82: Route Info | F82: Route Info | G82: Detour | H82: Route Info | P82: 6 | Q82: 10 | R82: Route Info | S82: Route Info | T82: Road Block | U82: Route Info | V82: Route Info | W82: Detour | X82: Route Info | AE82: China | AF82: East Asia | AG82: No | AH82: Yield | AI82: 3 | AJ82: Hayden & Aaron | AS82: Netherlands
A83: 7 | B83: 5 | C83: Route Info | D83: Fast Forward | E83: Detour | F83: Route Info | G83: Road Block | H83: Route Info | I83: Route Info | P83: 6 | Q83: 11 | R83: Route Info | S83: Detour | T83: Route Info | U83: Route Info | V83: Road Block | W83: Route Info | AE83: China | AF83: East Asia | AG83: Yes | AJ83: Kris & Jon | AS83: New Zealand
A84: 7 | B84: 6 | C84: Route Info | D84: Route Info | E84: Road Block | F84: Route Info | G84: Detour | H84: Route Info | P84: 6 | Q84: Final | R84: Route Info | S84: Detour | T84: Route Info | U84: Road Block | V84: Route Info | W84: Route Info | X84: Route Info | AE84: USA | AF84: North America | AG84: Final Leg | AJ84: Freddy & Kendra | AS84: Northern Ireland
A85: 7 | B85: 7 | C85: Route Info | D85: Detour | E85: Route Info | F85: Road Block | G85: Route Info | P85: 7 | Q85: 1 | R85: Route Info | S85: Route Info | T85: Route Info | U85: Route Info | V85: Route Info | W85: Detour | X85: Route Info | Y85: Route Info | AE85: Peru | AF85: South America | AG85: Yes | AJ85: Debbie & Bianca | AS85: Norway
A86: 7 | B86: 8 | C86: Route Info | D86: Route Info | E86: Road Block | F86: Route Info | G86: Detour | H86: Route Info | P86: 7 | Q86: 2 | R86: Route Info | S86: Road Block | T86: Route Info | U86: Detour | V86: Route Info | AE86: Chile | AF86: South America | AG86: Yes | AJ86: Rob & Amber | AS86: Oman
A87: 7 | B87: 9 | C87: Route Info | D87: Route Info | E87: Route Info | F87: Fast Forward | G87: Detour | H87: Route Info | I87: Road Block | J87: Route Info | P87: 7 | Q87: 3 | R87: Route Info | S87: Detour | T87: Route Info | U87: Road Block | V87: Route Info | AE87: Argentina | AF87: South America | AG87: Yes | AH87: Yield | AI87: 2 | AJ87: Lynn & Alex | AS87: Panama
A88: 7 | B88: 10 | C88: Route Info | D88: Route Info | E88: Detour | F88: Route Info | G88: Road Block | H88: Route Info | P88: 7 | Q88: 4 | R88: Route Info | S88: Road Block | T88: Route Info | U88: Route Info | V88: Detour | W88: Route Info | AE88: Argentina | AF88: South America | AG88: Yes | AJ88: Rob & Amber | AS88: Paraguay
A89: 7 | B89: 11 | C89: Route Info | D89: Route Info | E89: Route Info | F89: Detour | G89: Route Info | H89: Road Block | I89: Route Info | P89: 7 | Q89: 5 | R89: Route Info | S89: Fast Forward | T89: Detour | U89: Route Info | V89: Road Block | W89: Route Info | X89: Route Info | AE89: South Africa | AF89: Southern Africa | AG89: No | AJ89: Ray & Deana | AS89: Peru
A90: 7 | B90: 12 | C90: Route Info | D90: Road Block | E90: Route Info | F90: Detour | G90: Route Info | P90: 7 | Q90: 6 | R90: Route Info | S90: Route Info | T90: Road Block | U90: Route Info | V90: Detour | W90: Route Info | AE90: Botswana | AF90: Southern Africa | AG90: Yes | AJ90: Ron & Kelly | AS90: Philippines
A91: 7 | B91: Final | C91: Route Info | D91: Route Info | E91: Detour | F91: Route Info | G91: Route Info | H91: Road Block | I91: Route Info | J91: Route Info | K91: Route Info | P91: 7 | Q91: 7 | R91: Route Info | S91: Detour | T91: Route Info | U91: Road Block | V91: Route Info | AE91: Botswana | AF91: Southern Africa | AG91: Yes | AJ91: Rob & Amber | AS91: Poland
A92: 8 | B92: 1 | C92: Route Info | D92: Route Info | E92: Route Info | F92: Route Info | G92: Route Info | H92: Route Info | I92: Detour | J92: Route Info | P92: 7 | Q92: 8 | R92: Route Info | S92: Route Info | T92: Road Block | U92: Route Info | V92: Detour | W92: Route Info | AE92: India | AF92: South Asia | AG92: No | AJ92: Rob & Amber | AS92: Portugal
A93: 8 | B93: 2 | C93: Route Info | D93: Route Info | E93: Route Info | F93: Road Block | G93: Route Info | H93: Detour | P93: 7 | Q93: 9 | R93: Route Info | S93: Route Info | T93: Route Info | U93: Fast Forward | V93: Detour | W93: Route Info | X93: Road Block | Y93: Route Info | AE93: India | AF93: South Asia | AG93: Yes | AJ93: Uchenna & Joyce | AS93: Puerto Rico
A94: 8 | B94: 3 | C94: Route Info | D94: Detour | E94: Route Info | F94: Route Info | G94: Road Block | H94: Route Info | I94: Route Info | P94: 7 | Q94: 10 | R94: Route Info | S94: Route Info | T94: Detour | U94: Route Info | V94: Road Block | W94: Route Info | AE94: Turkey | AF94: Middle East | AG94: No | AJ94: Uchenna & Joyce | AS94: Romania
A95: 8 | B95: 4 | C95: Route Info | D95: Route Info | E95: Route Info | F95: Route Info | G95: Road Block | H95: Route Info | I95: Route Info | J95: Route Info | K95: Detour | L95: Route Info | P95: 7 | Q95: 11 | R95: Route Info | S95: Route Info | T95: Route Info | U95: Detour | V95: Route Info | W95: Road Block | X95: Route Info | AE95: England | AF95: Western Europe | AG95: Yes | AJ95: Rob & Amber | AS95: Russia
A96: 8 | B96: 5 | C96: Route Info | D96: Fast Forward | E96: Detour | F96: Route Info | G96: Road Block | H96: Route Info | P96: 7 | Q96: 12 | R96: Route Info | S96: Road Block | T96: Route Info | U96: Detour | V96: Route Info | AE96: Jamaica | AF96: Caribbean | AG96: No | AJ96: Ron & Kelly | AS96: Scotland
A97: 8 | B97: 6 | C97: Route Info | D97: Route Info | E97: Road Block | F97: Route Info | G97: Detour | H97: Route Info | P97: 7 | Q97: Final | R97: Route Info | S97: Route Info | T97: Detour | U97: Route Info | V97: Route Info | W97: Road Block | X97: Route Info | Y97: Route Info | Z97: Route Info | AE97: Puerto Rico\nUSA | AF97: Caribbean\nNorth America | AG97: Final Leg | AJ97: Uchenna & Joyce | AS97: Senegal
A98: 8 | B98: 7 | C98: Route Info | D98: Route Info | E98: Detour | F98: Route Info | G98: Road Block | H98: Route Info | P98: 8 | Q98: 1 | R98: Route Info | S98: Route Info | T98: Route Info | U98: Route Info | V98: Route Info | W98: Route Info | X98: Detour | Y98: Route Info | AE98: USA | AF98: North America | AG98: Yes | AJ98: Godlewski Family | AS98: Seychelles
A99: 8 | B99: 8 | C99: Route Info | D99: Road Block | E99: Route Info | F99: Route Info | G99: Detour | H99: Route Info | P99: 8 | Q99: 2 | R99: Route Info | S99: Route Info | T99: Route Info | U99: Road Block | V99: Route Info | W99: Detour | AE99: USA | AF99: North America | AG99: Yes | AJ99: Weaver Family | AS99: Singapore
A100: 8 | B100: 9 | C100: Route Info | D100: Route Info | E100: Route Info | F100: Detour | G100: Route Info | H100: Route Info | I100: Route Info | J100: Road Block | K100: Route Info | P100: 8 | Q100: 3 | R100: Route Info | S100: Detour | T100: Route Info | U100: Route Info | V100: Road Block | W100: Route Info | X100: Route Info | AE100: USA | AF100: North America | AG100: Yes | AJ100: Bransen Family | AS100: Slovenia
...

Sheet Keywords
B4: Keywords
B6: Keywords are indicators of things that "happened" on each leg of the race. These include common types of challenges and phenomenon that occur during multiple different seasons of TAR.
B8: Definitions: | C8: Legs include:
B9: Animals | C9: challenge(s) that involve riding, herding, and/or working with animals in some way, such as riding an elephant or towing a field with an ox.
B10: Attention to Detail | C10: challenge(s) that involve some level of attention to detail, such as setting a dinner table or locating a specific tile.
B11: Balance | C11: challenge(s) that require team member(s) to balance in some way.
B12: Biking | C12: challenge(s) that require team member(s) to ride any type of bicycle to move around.
B13: Building | C13: challenge(s) that require the assembly of something - provided instructions or otherwise.
B14: Cooking | C14: challenge(s) that require team member(s) to cook something to the acceptance of judges, like cooking fish over a fire, but not necessarily consume it.
B15: Counting | C15: challenge(s) that require team member(s) to count specific things, like beans placed in urns.
B16: Dancing | C16: challenge(s) that require team member(s) to learn choreographed moves to perform for judges, may include routines other than dancing such as color guard or martial arts.
B17: Driving | C17: team member(s) driving some kind of automobile to move around, most commonly driving a car to the next clue, almost always includes navigating.
B18: Flags | C18: challenge(s) that require team member(s) to identify international/domestic flags.
B19: Food | C19: challenge(s) where team member(s) are required to consume food and/or drinks, not applicable for teams voluntarily consuming food and/or drinks.
... B36: Travel Issues | C36: team(s) running into any kind of issues traveling during the leg, such as flight delays, car troubles, getting lost, etc.
C38: *NOTE: many challenges fufill multiple keywords, hopefully in the future I can lay out what keywords apply to each challenge throughout TAR
B40: Keywords Logged per Season:
B41: Seasons | C41: Total | D41: Animals | E41: ATD | F41: Balance | G41: Biking | H41: Building | I41: Cooking | J41: Counting | K41: Dancing | L41: Driving | M41: Flags | N41: Food | O41: Geography | P41: HEC | Q41: Heights | R41: Language | S41: Math | T41: Memory | U41: Music | V41: Navigation | W41: Pain | X41: Painting | Y41: PS | Z41: Puzzle | AA41: Searching | AB41: Selling | AC41: Singing | AD41: Swimming | AE41: Travel Issues
B42: Season 1 | C42: =SUM($D42:$AE42) -> 54 | D42: =COUNTIF(Logs!$Q$9:'Logs'!$AC$17, "*"&D$41&"*") -> 5 | E42: =COUNTIF(Logs!$Q$9:'Logs'!$AC$17, "Attention to Detail") -> 0 | F42: =COUNTIF(Logs!$Q$9:'Logs'!$AC$17, "*"&F$41&"*") -> 0 | G42: =COUNTIF(Logs!$Q$9:'Logs'!$AC$17, "*"&G$41&"*") -> 1 | H42: =COUNTIF(Logs!$Q$9:'Logs'!$AC$17, "*"&H$41&"*") -> 0 | I42: =COUNTIF(Logs!$Q$9:'Logs'!$AC$17, "*"&I$41&"*") -> 0 | J42: =COUNTIF(Logs!$Q$9:'Logs'!$AC$17, "*"&J$41&"*") -> 1 | K42: =COUNTIF(Logs!$Q$9:'Logs'!$AC$17, "*"&K$41&"*") -> 0 | L42: =COUNTIF(Logs!$Q$9:'Logs'!$AC$17, "*"&L$41&"*") -> 5 | M42: =COUNTIF(Logs!$Q$9:'Logs'!$AC$17, "*"&M$41&"*") -> 1 | ... O42: =COUNTIF(Logs!$Q$9:'Logs'!$AC$17, "*"&O$41&"*") -> 0 | P42: =COUNTIF(Logs!$Q$9:'Logs'!$AC$17, "Hand Eye Coordination") -> 1 | Q42: =COUNTIF(Logs!$Q$9:'Logs'!$AC$17, "*"&Q$41&"*") -> 3 | R42: =COUNTIF(Logs!$Q$9:'Logs'!$AC$17, "*"&R$41&"*") -> 2 | S42: =COUNTIF(Logs!$Q$9:'Logs'!$AC$17, "*"&S$41&"*") -> 0 | T42: =COUNTIF(Logs!$Q$9:'Logs'!$AC$17, "Memorization") -> 0 | U42: =COUNTIF(Logs!$Q$9:'Logs'!$AC$17, "*"&U$41&"*") -> 0 | V42: =COUNTIF(Logs!$Q$9:'Logs'!$AC$17, "*"&V$41&"*") -> 3 | W42: =COUNTIF(Logs!$Q$9:'Logs'!$AC$17, W$41) -> 2 | X42: =COUNTIF(Logs!$Q$9:'Logs'!$AC$17, "*"&X$41&"*") -> 0 | Y42: =COUNTIF(Logs!$Q$9:'Logs'!$AC$17, "Physical Strength") -> 7 | Z42: =COUNTIF(Logs!$Q$9:'Logs'!$AC$17, "*"&Z$41&"*") -> 2 | AA42: =COUNTIF(Logs!$Q$9:'Logs'!$AC$17, "*"&AA$41&"*") -> 10 | AB42: =COUNTIF(Logs!$Q$9:'Logs'!$AC$17, "*"&AB$41&"*") -> 0 | AC42: =COUNTIF(Logs!$Q$9:'Logs'!$AC$17, "*"&AC$41&"*") -> 0 | AD42: =COUNTIF(Logs!$Q$9:'Logs'!$AC$17, "*"&AD$41&"*") -> 1 | AE42: =COUNTIF(Logs!$Q$9:'Logs'!$AC$17, "*"&AE$41&"*") -> 9
B43: Season 2 | C43: =SUM($D43:$AE43) -> 57 | D43: =COUNTIF(Logs!$Q$27:'Logs'!$AC$35, "*"&D$41&"*") -> 2 | E43: =COUNTIF(Logs!$Q$27:'Logs'!$AC$35, "Attention to Detail") -> 0 | F43: =COUNTIF(Logs!$Q$27:'Logs'!$AC$35, "*"&F$41&"*") -> 1 | G43: =COUNTIF(Logs!$Q$27:'Logs'!$AC$35, "*"&G$41&"*") -> 1 | H43: =COUNTIF(Logs!$Q$27:'Logs'!$AC$35, "*"&H$41&"*") -> 0 | I43: =COUNTIF(Logs!$Q$27:'Logs'!$AC$35, "*"&I$41&"*") -> 0 | J43: =COUNTIF(Logs!$Q$27:'Logs'!$AC$35, "*"&J$41&"*") -> 0 | K43: =COUNTIF(Logs!$Q$27:'Logs'!$AC$35, "*"&K$41&"*") -> 1 | L43: =COUNTIF(Logs!$Q$27:'Logs'!$AC$35, "*"&L$41&"*") -> 10 | M43: =COUNTIF(Logs!$Q$27:'Logs'!$AC$35, "*"&M$41&"*") -> 0 | ... O43: =COUNTIF(Logs!$Q$27:'Logs'!$AC$35, "*"&O$41&"*") -> 0 | P43: =COUNTIF(Logs!$Q$27:'Logs'!$AC$35, "Hand Eye Coordination") -> 3 | Q43: =COUNTIF(Logs!$Q$27:'Logs'!$AC$35, "*"&Q$41&"*") -> 5 | R43: =COUNTIF(Logs!$Q$27:'Logs'!$AC$35, "*"&R$41&"*") -> 1 | S43: =COUNTIF(Logs!$Q$27:'Logs'!$AC$35, "*"&S$41&"*") -> 0 | T43: =COUNTIF(Logs!$Q$27:'Logs'!$AC$35, "Memorization") -> 0 | U43: =COUNTIF(Logs!$Q$27:'Logs'!$AC$35, "*"&U$41&"*") -> 0 | V43: =COUNTIF(Logs!$Q$27:'Logs'!$AC$35, "*"&V$41&"*") -> 0 | W43: =COUNTIF(Logs!$Q$27:'Logs'!$AC$35,W$41) -> 0 | X43: =COUNTIF(Logs!$Q$27:'Logs'!$AC$35, "*"&X$41&"*") -> 0 | Y43: =COUNTIF(Logs!$Q$27:'Logs'!$AC$35, "Physical Strength") -> 9 | Z43: =COUNTIF(Logs!$Q$27:'Logs'!$AC$35, "*"&Z$41&"*") -> 0 | AA43: =COUNTIF(Logs!$Q$27:'Logs'!$AC$35, "*"&AA$41&"*") -> 8 | AB43: =COUNTIF(Logs!$Q$27:'Logs'!$AC$35, "*"&AB$41&"*") -> 1 | AC43: =COUNTIF(Logs!$Q$27:'Logs'!$AC$35, "*"&AC$41&"*") -> 0 | AD43: =COUNTIF(Logs!$Q$27:'Logs'!$AC$35, "*"&AD$41&"*") -> 2 | AE43: =COUNTIF(Logs!$Q$27:'Logs'!$AC$35, "*"&AE$41&"*") -> 10
B44: Season 3 | C44: =SUM($D44:$AE44) -> 67 | D44: =COUNTIF(Logs!$Q$45:'Logs'!$AC$53, "*"&D$41&"*") -> 3 | E44: =COUNTIF(Logs!$Q$45:'Logs'!$AC$53, "Attention to Detail") -> 1 | F44: =COUNTIF(Logs!$Q$45:'Logs'!$AC$53, "*"&F$41&"*") -> 2 | G44: =COUNTIF(Logs!$Q$45:'Logs'!$AC$53, "*"&G$41&"*") -> 4 | H44: =COUNTIF(Logs!$Q$45:'Logs'!$AC$53, "*"&H$41&"*") -> 1 | I44: =COUNTIF(Logs!$Q$45:'Logs'!$AC$53, "*"&I$41&"*") -> 0 | J44: =COUNTIF(Logs!$Q$45:'Logs'!$AC$53, "*"&J$41&"*") -> 1 | K44: =COUNTIF(Logs!$Q$45:'Logs'!$AC$53, "*"&K$41&"*") -> 0 | L44: =COUNTIF(Logs!$Q$45:'Logs'!$AC$53, "*"&L$41&"*") -> 11 | M44: =COUNTIF(Logs!$Q$45:'Logs'!$AC$53, "*"&M$41&"*") -> 1 | ... O44: =COUNTIF(Logs!$Q$45:'Logs'!$AC$53, "*"&O$41&"*") -> 0 | P44: =COUNTIF(Logs!$Q$45:'Logs'!$AC$53,"Hand Eye Coordination") -> 3 | Q44: =COUNTIF(Logs!$Q$45:'Logs'!$AC$53, "*"&Q$41&"*") -> 6 | R44: =COUNTIF(Logs!$Q$45:'Logs'!$AC$53, "*"&R$41&"*") -> 1 | S44: =COUNTIF(Logs!$Q$45:'Logs'!$AC$53, "*"&S$41&"*") -> 0 | T44: =COUNTIF(Logs!$Q$45:'Logs'!$AC$53, "Memorization") -> 1 | U44: =COUNTIF(Logs!$Q$45:'Logs'!$AC$53, "*"&U$41&"*") -> 0 | V44: =COUNTIF(Logs!$Q$45:'Logs'!$AC$53, "*"&V$41&"*") -> 1 | W44: =COUNTIF(Logs!$Q$45:'Logs'!$AC$53,W$41) -> 0 | X44: =COUNTIF(Logs!$Q$45:'Logs'!$AC$53, "*"&X$41&"*") -> 0 | Y44: =COUNTIF(Logs!$Q$45:'Logs'!$AC$53, "Physical Strength") -> 8 | Z44: =COUNTIF(Logs!$Q$45:'Logs'!$AC$53, "*"&Z$41&"*") -> 0 | AA44: =COUNTIF(Logs!$Q$45:'Logs'!$AC$53, "*"&AA$41&"*") -> 8 | AB44: =COUNTIF(Logs!$Q$45:'Logs'!$AC$53, "*"&AB$41&"*") -> 2 | AC44: =COUNTIF(Logs!$Q$45:'Logs'!$AC$53, "*"&AC$41&"*") -> 0 | AD44: =COUNTIF(Logs!$Q$45:'Logs'!$AC$53, "*"&AD$41&"*") -> 2 | AE44: =COUNTIF(Logs!$Q$45:'Logs'!$AC$53, "*"&AE$41&"*") -> 10
B45: Season 4 | C45: =SUM($D45:$AE45) -> 58 | D45: =COUNTIF(Logs!$Q$63:'Logs'!$AC$71, "*"&D$41&"*") -> 6 | E45: =COUNTIF(Logs!$Q$63:'Logs'!$AC$71, "Attention to Detail") -> 0 | F45: =COUNTIF(Logs!$Q$63:'Logs'!$AC$71, "*"&F$41&"*") -> 1 | G45: =COUNTIF(Logs!$Q$63:'Logs'!$AC$71, "*"&G$41&"*") -> 2 | H45: =COUNTIF(Logs!$Q$63:'Logs'!$AC$71, "*"&H$41&"*") -> 0 | I45: =COUNTIF(Logs!$Q$63:'Logs'!$AC$71, "*"&I$41&"*") -> 0 | J45: =COUNTIF(Logs!$Q$63:'Logs'!$AC$71, "*"&J$41&"*") -> 0 | K45: =COUNTIF(Logs!$Q$63:'Logs'!$AC$71, "*"&K$41&"*") -> 0 | L45: =COUNTIF(Logs!$Q$63:'Logs'!$AC$71, "*"&L$41&"*") -> 6 | M45: =COUNTIF(Logs!$Q$63:'Logs'!$AC$71, "*"&M$41&"*") -> 0 | ... O45: =COUNTIF(Logs!$Q$63:'Logs'!$AC$71, "*"&O$41&"*") -> 0 | P45: =COUNTIF(Logs!$Q$63:'Logs'!$AC$71,"Hand Eye Coordination") -> 1 | Q45: =COUNTIF(Logs!$Q$63:'Logs'!$AC$71, "*"&Q$41&"*") -> 6 | R45: =COUNTIF(Logs!$Q$63:'Logs'!$AC$71, "*"&R$41&"*") -> 0 | S45: =COUNTIF(Logs!$Q$63:'Logs'!$AC$71, "*"&S$41&"*") -> 0 | T45: =COUNTIF(Logs!$Q$63:'Logs'!$AC$71, "Memorization") -> 0 | U45: =COUNTIF(Logs!$Q$63:'Logs'!$AC$71, "*"&U$41&"*") -> 0 | V45: =COUNTIF(Logs!$Q$63:'Logs'!$AC$71, "*"&V$41&"*") -> 3 | W45: =COUNTIF(Logs!$Q$63:'Logs'!$AC$71, W$41) -> 2 | X45: =COUNTIF(Logs!$Q$63:'Logs'!$AC$71, "*"&X$41&"*") -> 0 | Y45: =COUNTIF(Logs!$Q$63:'Logs'!$AC$71, "Physical Strength") -> 9 | Z45: =COUNTIF(Logs!$Q$63:'Logs'!$AC$71, "*"&Z$41&"*") -> 2 | AA45: =COUNTIF(Logs!$Q$63:'Logs'!$AC$71, "*"&AA$41&"*") -> 7 | AB45: =COUNTIF(Logs!$Q$63:'Logs'!$AC$71, "*"&AB$41&"*") -> 0 | AC45: =COUNTIF(Logs!$Q$63:'Logs'!$AC$71, "*"&AC$41&"*") -> 0 | AD45: =COUNTIF(Logs!$Q$63:'Logs'!$AC$71, "*"&AD$41&"*") -> 3 | AE45: =COUNTIF(Logs!$Q$63:'Logs'!$AC$71, "*"&AE$41&"*") -> 9 | AG45: Keywords Logged per Leg:
B46: Season 5 | C46: =SUM($D46:$AE46) -> 63 | D46: =COUNTIF(Logs!$Q$81:'Logs'!$AC$88, "*"&D$41&"*") -> 6 | E46: =COUNTIF(Logs!$Q$81:'Logs'!$AC$88, "Attention to Detail") -> 1 | F46: =COUNTIF(Logs!$Q$81:'Logs'!$AC$88, "*"&F$41&"*") -> 0 | G46: =COUNTIF(Logs!$Q$81:'Logs'!$AC$88, "*"&G$41&"*") -> 3 | H46: =COUNTIF(Logs!$Q$81:'Logs'!$AC$88, "*"&H$41&"*") -> 0 | I46: =COUNTIF(Logs!$Q$81:'Logs'!$AC$88, "*"&I$41&"*") -> 1 | J46: =COUNTIF(Logs!$Q$81:'Logs'!$AC$88, "*"&J$41&"*") -> 0 | K46: =COUNTIF(Logs!$Q$81:'Logs'!$AC$88, "*"&K$41&"*") -> 0 | L46: =COUNTIF(Logs!$Q$81:'Logs'!$AC$88, "*"&L$41&"*") -> 8 | M46: =COUNTIF(Logs!$Q$81:'Logs'!$AC$88, "*"&M$41&"*") -> 1 | ... O46: =COUNTIF(Logs!$Q$81:'Logs'!$AC$88, "*"&O$41&"*") -> 0 | P46: =COUNTIF(Logs!$Q$81:'Logs'!$AC$88,"Hand Eye Coordination") -> 1 | Q46: =COUNTIF(Logs!$Q$81:'Logs'!$AC$88, "*"&Q$41&"*") -> 6 | R46: =COUNTIF(Logs!$Q$81:'Logs'!$AC$88, "*"&R$41&"*") -> 0 | S46: =COUNTIF(Logs!$Q$81:'Logs'!$AC$88, "*"&S$41&"*") -> 0 | T46: =COUNTIF(Logs!$Q$81:'Logs'!$AC$88, "Memorization") -> 0 | U46: =COUNTIF(Logs!$Q$81:'Logs'!$AC$88, "*"&U$41&"*") -> 0 | V46: =COUNTIF(Logs!$Q$81:'Logs'!$AC$88, "*"&V$41&"*") -> 2 | W46: =COUNTIF(Logs!$Q$81:'Logs'!$AC$88, W$41) -> 1 | X46: =COUNTIF(Logs!$Q$81:'Logs'!$AC$88, "*"&X$41&"*") -> 0 | Y46: =COUNTIF(Logs!$Q$81:'Logs'!$AC$88, "Physical Strength") -> 10 | Z46: =COUNTIF(Logs!$Q$81:'Logs'!$AC$88, "*"&Z$41&"*") -> 1 | AA46: =COUNTIF(Logs!$Q$81:'Logs'!$AC$88, "*"&AA$41&"*") -> 6 | AB46: =COUNTIF(Logs!$Q$81:'Logs'!$AC$88, "*"&AB$41&"*") -> 0 | AC46: =COUNTIF(Logs!$Q$81:'Logs'!$AC$88, "*"&AC$41&"*") -> 0 | AD46: =COUNTIF(Logs!$Q$81:'Logs'!$AC$88, "*"&AD$41&"*") -> 2 | AE46: =COUNTIF(Logs!$Q$81:'Logs'!$AC$88, "*"&AE$41&"*") -> 11 | AG46: Leg # | AH46: Animals | AI46: ATD | AJ46: Balance | AK46: Biking | AL46: Building | AM46: Cooking | AN46: Counting | AO46: Dancing | AP46: Driving | AQ46: Flags | AR46: Food | AS46: Geography | AT46: Hand Eye Coordination | AU46: Heights | AV46: Language | AW46: Math | AX46: Memorization | AY46: Music | AZ46: Navigation | BA46: Pain | BB46: Painting | BC46: Physical Strength | BD46: Puzzle | BE46: Searching | BF46: Selling | BG46: Singing | BH46: Swimming | BI46: Travel Issues | BJ46: Totals
B47: Season 6 | C47: =SUM($D47:$AE47) -> 61 | D47: =COUNTIF(Logs!$Q$101:'Logs'!$AB$110, "*"&D$41&"*") -> 3 | E47: =COUNTIF(Logs!$Q$101:'Logs'!$AB$110, "Attention to Detail") -> 2 | F47: =COUNTIF(Logs!$Q$101:'Logs'!$AB$110, "*"&F$41&"*") -> 2 | G47: =COUNTIF(Logs!$Q$101:'Logs'!$AB$110, "*"&G$41&"*") -> 2 | H47: =COUNTIF(Logs!$Q$101:'Logs'!$AB$110, "*"&H$41&"*") -> 1 | I47: =COUNTIF(Logs!$Q$101:'Logs'!$AB$110, "*"&I$41&"*") -> 1 | J47: =COUNTIF(Logs!$Q$101:'Logs'!$AB$110, "*"&J$41&"*") -> 1 | K47: =COUNTIF(Logs!$Q$101:'Logs'!$AB$110, "*"&K$41&"*") -> 0 | L47: =COUNTIF(Logs!$Q$101:'Logs'!$AB$110, "*"&L$41&"*") -> 7 | M47: =COUNTIF(Logs!$Q$101:'Logs'!$AB$110, "*"&M$41&"*") -> 0 | ... O47: =COUNTIF(Logs!$Q$101:'Logs'!$AB$110, "*"&O$41&"*") -> 0 | P47: =COUNTIF(Logs!$Q$101:'Logs'!$AB$110, "Hand Eye Coordination") -> 3 | Q47: =COUNTIF(Logs!$Q$101:'Logs'!$AB$110, "*"&Q$41&"*") -> 5 | R47: =COUNTIF(Logs!$Q$101:'Logs'!$AB$110, "*"&R$41&"*") -> 0 | S47: =COUNTIF(Logs!$Q$101:'Logs'!$AB$110, "*"&S$41&"*") -> 0 | T47: =COUNTIF(Logs!$Q$101:'Logs'!$AB$110, "Memorization") -> 0 | U47: =COUNTIF(Logs!$Q$101:'Logs'!$AB$110, "*"&U$41&"*") -> 0 | V47: =COUNTIF(Logs!$Q$101:'Logs'!$AB$110, "*"&V$41&"*") -> 2 | W47: =COUNTIF(Logs!$Q$101:'Logs'!$AB$110,W$41) -> 0 | X47: =COUNTIF(Logs!$Q$101:'Logs'!$AB$110, "*"&X$41&"*") -> 1 | Y47: =COUNTIF(Logs!$Q$101:'Logs'!$AB$110, "Physical Strength") -> 10 | Z47: =COUNTIF(Logs!$Q$101:'Logs'!$AB$110, "*"&Z$41&"*") -> 0 | AA47: =COUNTIF(Logs!$Q$101:'Logs'!$AB$110, "*"&AA$41&"*") -> 7 | AB47: =COUNTIF(Logs!$Q$101:'Logs'!$AB$110, "*"&AB$41&"*") -> 0 | AC47: =COUNTIF(Logs!$Q$101:'Logs'!$AB$110, "*"&AC$41&"*") -> 0 | AD47: =COUNTIF(Logs!$Q$101:'Logs'!$AB$110, "*"&AD$41&"*") -> 3 | AE47: =COUNTIF(Logs!$Q$101:'Logs'!$AB$110, "*"&AE$41&"*") -> 8 | AG47: Leg 1 | AH47: =COUNTIF(Logs!$Q$9:'Logs'!$Q$1001, "*"&AH$46&"*") -> 5 | AI47: =COUNTIF(Logs!$Q$9:'Logs'!$Q$1001, "Attention to Detail") -> 10 | AJ47: =COUNTIF(Logs!$Q$9:'Logs'!$Q$1001, "*"&AJ$46&"*") -> 4 | AK47: =COUNTIF(Logs!$Q$9:'Logs'!$Q$1001, "*"&AK$46&"*") -> 2 | AL47: =COUNTIF(Logs!$Q$9:'Logs'!$Q$1001, "*"&AL$46&"*") -> 3 | AM47: =COUNTIF(Logs!$Q$9:'Logs'!$Q$1001, "*"&AM$46&"*") -> 1 | AN47: =COUNTIF(Logs!$Q$9:'Logs'!$Q$1001, "*"&AN$46&"*") -> 0 | AO47: =COUNTIF(Logs!$Q$9:'Logs'!$Q$1001, "*"&AO$46&"*") -> 4 | AP47: =COUNTIF(Logs!$Q$9:'Logs'!$Q$1001, "*"&AP$46&"*") -> 24 | AQ47: =COUNTIF(Logs!$Q$9:'Logs'!$Q$1001, "*"&AQ$46&"*") -> 1 | ... AZ47: =COUNTIF(Logs!$Q$9:'Logs'!$Q$1001, "*"&AZ$46&"*") -> 1 | BA47: =COUNTIF(Logs!$Q$9:'Logs'!$Q$1001, BA$46) -> 2 | BB47: =COUNTIF(Logs!$Q$9:'Logs'!$Q$1001, "*"&BB$46&"*") -> 1 | BC47: =COUNTIF(Logs!$Q$9:'Logs'!$Q$1001, "*"&BC$46&"*") -> 29 | BD47: =COUNTIF(Logs!$Q$9:'Logs'!$Q$1001, "*"&BD$46&"*") -> 7 | BE47: =COUNTIF(Logs!$Q$9:'Logs'!$Q$1001, "*"&BE$46&"*") -> 22 | BF47: =COUNTIF(Logs!$Q$9:'Logs'!$Q$1001, "*"&BF$46&"*") -> 1 | BG47: =COUNTIF(Logs!$Q$9:'Logs'!$Q$1001, "*"&BG$46&"*") -> 1 | BH47: =COUNTIF(Logs!$Q$9:'Logs'!$Q$1001, "*"&BH$46&"*") -> 0 | BI47: =COUNTIF(Logs!$Q$9:'Logs'!$Q$1001, "*"&BI$46&"*") -> 30 | BJ47: =SUM(Table37[[#This Row],[Animals]:[Travel Issues]]) -> 185
B48: Season 7 | C48: =SUM($D48:$AE48) -> 55 | D48: =COUNTIF(Logs!$Q$120:'Logs'!$AC$128, "*"&D$41&"*") -> 5 | E48: =COUNTIF(Logs!$Q$120:'Logs'!$AC$128, "Attention to Detail") -> 1 | F48: =COUNTIF(Logs!$Q$120:'Logs'!$AC$128, "*"&F$41&"*") -> 2 | G48: =COUNTIF(Logs!$Q$120:'Logs'!$AC$128, "*"&G$41&"*") -> 1 | H48: =COUNTIF(Logs!$Q$120:'Logs'!$AC$128, "*"&H$41&"*") -> 1 | I48: =COUNTIF(Logs!$Q$120:'Logs'!$AC$128, "*"&I$41&"*") -> 0 | J48: =COUNTIF(Logs!$Q$120:'Logs'!$AC$128, "*"&J$41&"*") -> 0 | K48: =COUNTIF(Logs!$Q$120:'Logs'!$AC$128, "*"&K$41&"*") -> 0 | L48: =COUNTIF(Logs!$Q$120:'Logs'!$AC$128, "*"&L$41&"*") -> 8 | M48: =COUNTIF(Logs!$Q$120:'Logs'!$AC$128, "*"&M$41&"*") -> 0 | ... O48: =COUNTIF(Logs!$Q$120:'Logs'!$AC$128, "*"&O$41&"*") -> 0 | P48: =COUNTIF(Logs!$Q$120:'Logs'!$AC$128, "Hand Eye Coordination") -> 2 | Q48: =COUNTIF(Logs!$Q$120:'Logs'!$AC$128, "*"&Q$41&"*") -> 4 | R48: =COUNTIF(Logs!$Q$120:'Logs'!$AC$128, "*"&R$41&"*") -> 0 | S48: =COUNTIF(Logs!$Q$120:'Logs'!$AC$128, "*"&S$41&"*") -> 0 | T48: =COUNTIF(Logs!$Q$120:'Logs'!$AC$128, "Memorization") -> 0 | U48: =COUNTIF(Logs!$Q$120:'Logs'!$AC$128, "*"&U$41&"*") -> 0 | V48: =COUNTIF(Logs!$Q$120:'Logs'!$AC$128, "*"&V$41&"*") -> 2 | W48: =COUNTIF(Logs!$Q$120:'Logs'!$AC$128, W$41) -> 1 | X48: =COUNTIF(Logs!$Q$120:'Logs'!$AC$128, "*"&X$41&"*") -> 0 | Y48: =COUNTIF(Logs!$Q$120:'Logs'!$AC$128, "Physical Strength") -> 7 | Z48: =COUNTIF(Logs!$Q$120:'Logs'!$AC$128, "*"&Z$41&"*") -> 1 | AA48: =COUNTIF(Logs!$Q$120:'Logs'!$AC$128, "*"&AA$41&"*") -> 8 | AB48: =COUNTIF(Logs!$Q$120:'Logs'!$AC$128, "*"&AB$41&"*") -> 1 | AC48: =COUNTIF(Logs!$Q$120:'Logs'!$AC$128, "*"&AC$41&"*") -> 0 | AD48: =COUNTIF(Logs!$Q$120:'Logs'!$AC$128, "*"&AD$41&"*") -> 1 | AE48: =COUNTIF(Logs!$Q$120:'Logs'!$AC$128, "*"&AE$41&"*") -> 9 | AG48: Leg 2 | AH48: =COUNTIF(Logs!$R$9:'Logs'!$R$1001, "*"&AH$46&"*") -> 6 | AI48: =COUNTIF(Logs!$R$9:'Logs'!$R$1001, "Attention to Detail") -> 18 | AJ48: =COUNTIF(Logs!$R$9:'Logs'!$R$1001, "*"&AJ$46&"*") -> 5 | AK48: =COUNTIF(Logs!$R$9:'Logs'!$R$1001, "*"&AK$46&"*") -> 1 | AL48: =COUNTIF(Logs!$R$9:'Logs'!$R$1001, "*"&AL$46&"*") -> 6 | AM48: =COUNTIF(Logs!$R$9:'Logs'!$R$1001, "*"&AM$46&"*") -> 3 | AN48: =COUNTIF(Logs!$R$9:'Logs'!$R$1001, "*"&AN$46&"*") -> 0 | AO48: =COUNTIF(Logs!$R$9:'Logs'!$R$1001, "*"&AO$46&"*") -> 4 | AP48: =COUNTIF(Logs!$R$9:'Logs'!$R$1001, "*"&AP$46&"*") -> 14 | AQ48: =COUNTIF(Logs!$R$9:'Logs'!$R$1001, "*"&AQ$46&"*") -> 1 | ... AZ48: =COUNTIF(Logs!$R$9:'Logs'!$R$1001, "*"&AZ$46&"*") -> 2 | BA48: =COUNTIF(Logs!$R$9:'Logs'!$R$1001, BA$46) -> 1 | BB48: =COUNTIF(Logs!$R$9:'Logs'!$R$1001, "*"&BB$46&"*") -> 2 | BC48: =COUNTIF(Logs!$R$9:'Logs'!$R$1001, "*"&BC$46&"*") -> 26 | BD48: =COUNTIF(Logs!$R$9:'Logs'!$R$1001, "*"&BD$46&"*") -> 5 | BE48: =COUNTIF(Logs!$R$9:'Logs'!$R$1001, "*"&BE$46&"*") -> 22 | BF48: =COUNTIF(Logs!$R$9:'Logs'!$R$1001, "*"&BF$46&"*") -> 1 | BG48: =COUNTIF(Logs!$R$9:'Logs'!$R$1001, "*"&BG$46&"*") -> 1 | BH48: =COUNTIF(Logs!$R$9:'Logs'!$R$1001, "*"&BH$46&"*") -> 3 | BI48: =COUNTIF(Logs!$R$9:'Logs'!$R$1001, "*"&BI$46&"*") -> 27 | BJ48: =SUM(Table37[[#This Row],[Animals]:[Travel Issues]]) -> 175
B49: Season 8 | C49: =SUM($D49:$AE49) -> 56 | D49: =COUNTIF(Logs!$Q$139:'Logs'!$AC$147, "*"&D$41&"*") -> 2 | E49: =COUNTIF(Logs!$Q$139:'Logs'!$AC$147, "Attention to Detail") -> 3 | F49: =COUNTIF(Logs!$Q$139:'Logs'!$AC$147, "*"&F$41&"*") -> 0 | G49: =COUNTIF(Logs!$Q$139:'Logs'!$AC$147, "*"&G$41&"*") -> 2 | H49: =COUNTIF(Logs!$Q$139:'Logs'!$AC$147, "*"&H$41&"*") -> 3 | I49: =COUNTIF(Logs!$Q$139:'Logs'!$AC$147, "*"&I$41&"*") -> 1 | J49: =COUNTIF(Logs!$Q$139:'Logs'!$AC$147, "*"&J$41&"*") -> 0 | K49: =COUNTIF(Logs!$Q$139:'Logs'!$AC$147, "*"&K$41&"*") -> 0 | L49: =COUNTIF(Logs!$Q$139:'Logs'!$AC$147, "*"&L$41&"*") -> 11 | M49: =COUNTIF(Logs!$Q$139:'Logs'!$AC$147, "*"&M$41&"*") -> 0 | ... O49: =COUNTIF(Logs!$Q$139:'Logs'!$AC$147, "*"&O$41&"*") -> 1 | P49: =COUNTIF(Logs!$Q$139:'Logs'!$AC$147, "Hand Eye Coordination") -> 2 | Q49: =COUNTIF(Logs!$Q$139:'Logs'!$AC$147, "*"&Q$41&"*") -> 4 | R49: =COUNTIF(Logs!$Q$139:'Logs'!$AC$147, "*"&R$41&"*") -> 0 | S49: =COUNTIF(Logs!$Q$139:'Logs'!$AC$147, "*"&S$41&"*") -> 0 | T49: =COUNTIF(Logs!$Q$139:'Logs'!$AC$147, "Memorization") -> 0 | U49: =COUNTIF(Logs!$Q$139:'Logs'!$AC$147, "*"&U$41&"*") -> 0 | V49: =COUNTIF(Logs!$Q$139:'Logs'!$AC$147, "*"&V$41&"*") -> 1 | W49: =COUNTIF(Logs!$Q$139:'Logs'!$AC$147, W$41) -> 1 | X49: =COUNTIF(Logs!$Q$139:'Logs'!$AC$147, "*"&X$41&"*") -> 1 | Y49: =COUNTIF(Logs!$Q$139:'Logs'!$AC$147, "Physical Strength") -> 10 | Z49: =COUNTIF(Logs!$Q$139:'Logs'!$AC$147, "*"&Z$41&"*") -> 0 | AA49: =COUNTIF(Logs!$Q$139:'Logs'!$AC$147, "*"&AA$41&"*") -> 6 | AB49: =COUNTIF(Logs!$Q$139:'Logs'!$AC$147, "*"&AB$41&"*") -> 0 | AC49: =COUNTIF(Logs!$Q$139:'Logs'!$AC$147, "*"&AC$41&"*") -> 0 | AD49: =COUNTIF(Logs!$Q$139:'Logs'!$AC$147, "*"&AD$41&"*") -> 1 | AE49: =COUNTIF(Logs!$Q$139:'Logs'!$AC$147, "*"&AE$41&"*") -> 7 | AG49: Leg 3 | AH49: =COUNTIF(Logs!$S$9:'Logs'!$S$1001, "*"&AH$46&"*") -> 7 | AI49: =COUNTIF(Logs!$S$9:'Logs'!$S$1001, "Attention to Detail") -> 18 | AJ49: =COUNTIF(Logs!$S$9:'Logs'!$S$1001, "*"&AJ$46&"*") -> 6 | AK49: =COUNTIF(Logs!$S$9:'Logs'!$S$1001, "*"&AK$46&"*") -> 7 | AL49: =COUNTIF(Logs!$S$9:'Logs'!$S$1001, "*"&AL$46&"*") -> 5 | AM49: =COUNTIF(Logs!$S$9:'Logs'!$S$1001, "*"&AM$46&"*") -> 5 | AN49: =COUNTIF(Logs!$S$9:'Logs'!$S$1001, "*"&AN$46&"*") -> 1 | AO49: =COUNTIF(Logs!$S$9:'Logs'!$S$1001, "*"&AO$46&"*") -> 7 | AP49: =COUNTIF(Logs!$S$9:'Logs'!$S$1001, "*"&AP$46&"*") -> 14 | AQ49: =COUNTIF(Logs!$S$9:'Logs'!$S$1001, "*"&AQ$46&"*") -> 0 | ... AZ49: =COUNTIF(Logs!$S$9:'Logs'!$S$1001, "*"&AZ$46&"*") -> 1 | BA49: =COUNTIF(Logs!$S$9:'Logs'!$S$1001, BA$46) -> 2 | BB49: =COUNTIF(Logs!$S$9:'Logs'!$S$1001, "*"&BB$46&"*") -> 0 | BC49: =COUNTIF(Logs!$S$9:'Logs'!$S$1001, "*"&BC$46&"*") -> 25 | BD49: =COUNTIF(Logs!$S$9:'Logs'!$S$1001, "*"&BD$46&"*") -> 4 | BE49: =COUNTIF(Logs!$S$9:'Logs'!$S$1001, "*"&BE$46&"*") -> 14 | BF49: =COUNTIF(Logs!$S$9:'Logs'!$S$1001, "*"&BF$46&"*") -> 2 | BG49: =COUNTIF(Logs!$S$9:'Logs'!$S$1001, "*"&BG$46&"*") -> 1 | BH49: =COUNTIF(Logs!$S$9:'Logs'!$S$1001, "*"&BH$46&"*") -> 1 | BI49: =COUNTIF(Logs!$S$9:'Logs'!$S$1001, "*"&BI$46&"*") -> 28 | BJ49: =SUM(Table37[[#This Row],[Animals]:[Travel Issues]]) -> 176
B50: Season 9 | C50: =SUM($D50:$AE50) -> 66 | D50: =COUNTIF(Logs!$Q$159:'Logs'!$AC$167, "*"&D$41&"*") -> 3 | E50: =COUNTIF(Logs!$Q$159:'Logs'!$AC$167, "Attention to Detail") -> 2 | F50: =COUNTIF(Logs!$Q$159:'Logs'!$AC$167, "*"&F$41&"*") -> 1 | G50: =COUNTIF(Logs!$Q$159:'Logs'!$AC$167, "*"&G$41&"*") -> 2 | H50: =COUNTIF(Logs!$Q$159:'Logs'!$AC$167, "*"&H$41&"*") -> 3 | I50: =COUNTIF(Logs!$Q$159:'Logs'!$AC$167, "*"&I$41&"*") -> 0 | J50: =COUNTIF(Logs!$Q$159:'Logs'!$AC$167, "*"&J$41&"*") -> 1 | K50: =COUNTIF(Logs!$Q$159:'Logs'!$AC$167, "*"&K$41&"*") -> 1 | L50: =COUNTIF(Logs!$Q$159:'Logs'!$AC$167, "*"&L$41&"*") -> 11 | M50: =COUNTIF(Logs!$Q$159:'Logs'!$AC$167, "*"&M$41&"*") -> 1 | ... O50: =COUNTIF(Logs!$Q$159:'Logs'!$AC$167, "*"&O$41&"*") -> 0 | P50: =COUNTIF(Logs!$Q$159:'Logs'!$AC$167, "Hand Eye Coordination") -> 1 | Q50: =COUNTIF(Logs!$Q$159:'Logs'!$AC$167, "*"&Q$41&"*") -> 4 | R50: =COUNTIF(Logs!$Q$159:'Logs'!$AC$167, "*"&R$41&"*") -> 1 | S50: =COUNTIF(Logs!$Q$159:'Logs'!$AC$167, "*"&S$41&"*") -> 0 | T50: =COUNTIF(Logs!$Q$159:'Logs'!$AC$167, "Memorization") -> 1 | U50: =COUNTIF(Logs!$Q$159:'Logs'!$AC$167, "*"&U$41&"*") -> 1 | V50: =COUNTIF(Logs!$Q$159:'Logs'!$AC$167, "*"&V$41&"*") -> 0 | W50: =COUNTIF(Logs!$Q$159:'Logs'!$AC$167, W$41) -> 1 | X50: =COUNTIF(Logs!$Q$159:'Logs'!$AC$167, "*"&X$41&"*") -> 0 | Y50: =COUNTIF(Logs!$Q$159:'Logs'!$AC$167, "Physical Strength") -> 9 | Z50: =COUNTIF(Logs!$Q$159:'Logs'!$AC$167, "*"&Z$41&"*") -> 1 | AA50: =COUNTIF(Logs!$Q$159:'Logs'!$AC$167, "*"&AA$41&"*") -> 8 | AB50: =COUNTIF(Logs!$Q$159:'Logs'!$AC$167, "*"&AB$41&"*") -> 1 | AC50: =COUNTIF(Logs!$Q$159:'Logs'!$AC$167, "*"&AC$41&"*") -> 0 | AD50: =COUNTIF(Logs!$Q$159:'Logs'!$AC$167, "*"&AD$41&"*") -> 2 | AE50: =COUNTIF(Logs!$Q$159:'Logs'!$AC$167, "*"&AE$41&"*") -> 10 | AG50: Leg 4 | AH50: =COUNTIF(Logs!$T$9:'Logs'!$T$1001, "*"&AH$46&"*") -> 9 | AI50: =COUNTIF(Logs!$T$9:'Logs'!$T$1001, "Attention to Detail") -> 20 | AJ50: =COUNTIF(Logs!$T$9:'Logs'!$T$1001, "*"&AJ$46&"*") -> 2 | AK50: =COUNTIF(Logs!$T$9:'Logs'!$T$1001, "*"&AK$46&"*") -> 3 | AL50: =COUNTIF(Logs!$T$9:'Logs'!$T$1001, "*"&AL$46&"*") -> 12 | AM50: =COUNTIF(Logs!$T$9:'Logs'!$T$1001, "*"&AM$46&"*") -> 2 | AN50: =COUNTIF(Logs!$T$9:'Logs'!$T$1001, "*"&AN$46&"*") -> 1 | AO50: =COUNTIF(Logs!$T$9:'Logs'!$T$1001, "*"&AO$46&"*") -> 4 | AP50: =COUNTIF(Logs!$T$9:'Logs'!$T$1001, "*"&AP$46&"*") -> 17 | AQ50: =COUNTIF(Logs!$T$9:'Logs'!$T$1001, "*"&AQ$46&"*") -> 2 | ... AZ50: =COUNTIF(Logs!$T$9:'Logs'!$T$1001, "*"&AZ$46&"*") -> 3 | BA50: =COUNTIF(Logs!$T$9:'Logs'!$T$1001,BA$46) -> 3 | BB50: =COUNTIF(Logs!$T$9:'Logs'!$T$1001, "*"&BB$46&"*") -> 0 | BC50: =COUNTIF(Logs!$T$9:'Logs'!$T$1001, "*"&BC$46&"*") -> 27 | BD50: =COUNTIF(Logs!$T$9:'Logs'!$T$1001, "*"&BD$46&"*") -> 9 | BE50: =COUNTIF(Logs!$T$9:'Logs'!$T$1001, "*"&BE$46&"*") -> 13 | BF50: =COUNTIF(Logs!$T$9:'Logs'!$T$1001, "*"&BF$46&"*") -> 1 | BG50: =COUNTIF(Logs!$T$9:'Logs'!$T$1001, "*"&BG$46&"*") -> 0 | BH50: =COUNTIF(Logs!$T$9:'Logs'!$T$1001, "*"&BH$46&"*") -> 2 | BI50: =COUNTIF(Logs!$T$9:'Logs'!$T$1001, "*"&BI$46&"*") -> 20 | BJ50: =SUM(Table37[[#This Row],[Animals]:[Travel Issues]]) -> 180
B51: Season 10 | C51: =SUM($D51:$AE51) -> 64 | D51: =COUNTIF(Logs!$Q$177:'Logs'!$AB$188, "*"&D$41&"*") -> 2 | E51: =COUNTIF(Logs!$Q$177:'Logs'!$AB$188, "Attention to Detail") -> 6 | F51: =COUNTIF(Logs!$Q$177:'Logs'!$AB$188, "*"&F$41&"*") -> 0 | G51: =COUNTIF(Logs!$Q$177:'Logs'!$AB$188, "*"&G$41&"*") -> 2 | H51: =COUNTIF(Logs!$Q$177:'Logs'!$AB$188, "*"&H$41&"*") -> 1 | I51: =COUNTIF(Logs!$Q$177:'Logs'!$AB$188, "*"&I$41&"*") -> 1 | J51: =COUNTIF(Logs!$Q$177:'Logs'!$AB$188, "*"&J$41&"*") -> 0 | K51: =COUNTIF(Logs!$Q$177:'Logs'!$AB$188, "*"&K$41&"*") -> 1 | L51: =COUNTIF(Logs!$Q$177:'Logs'!$AB$188, "*"&L$41&"*") -> 9 | M51: =COUNTIF(Logs!$Q$177:'Logs'!$AB$188, "*"&M$41&"*") -> 0 | ... O51: =COUNTIF(Logs!$Q$177:'Logs'!$AB$188, "*"&O$41&"*") -> 0 | P51: =COUNTIF(Logs!$Q$177:'Logs'!$AB$188, "Hand Eye Coordination") -> 2 | Q51: =COUNTIF(Logs!$Q$177:'Logs'!$AB$188, "*"&Q$41&"*") -> 3 | R51: =COUNTIF(Logs!$Q$177:'Logs'!$AB$188, "*"&R$41&"*") -> 1 | S51: =COUNTIF(Logs!$Q$177:'Logs'!$AB$188, "*"&S$41&"*") -> 0 | T51: =COUNTIF(Logs!$Q$177:'Logs'!$AB$188,"Memorization") -> 0 | U51: =COUNTIF(Logs!$Q$177:'Logs'!$AB$188, "*"&U$41&"*") -> 0 | V51: =COUNTIF(Logs!$Q$177:'Logs'!$AB$188, "*"&V$41&"*") -> 0 | W51: =COUNTIF(Logs!$Q$177:'Logs'!$AB$188, W$41) -> 2 | X51: =COUNTIF(Logs!$Q$177:'Logs'!$AB$188, "*"&X$41&"*") -> 1 | Y51: =COUNTIF(Logs!$Q$177:'Logs'!$AB$188, "Physical Strength") -> 9 | Z51: =COUNTIF(Logs!$Q$177:'Logs'!$AB$188, "*"&Z$41&"*") -> 2 | AA51: =COUNTIF(Logs!$Q$177:'Logs'!$AB$188, "*"&AA$41&"*") -> 5 | AB51: =COUNTIF(Logs!$Q$177:'Logs'!$AB$188, "*"&AB$41&"*") -> 1 | AC51: =COUNTIF(Logs!$Q$177:'Logs'!$AB$188, "*"&AC$41&"*") -> 1 | AD51: =COUNTIF(Logs!$Q$177:'Logs'!$AB$188, "*"&AD$41&"*") -> 1 | AE51: =COUNTIF(Logs!$Q$177:'Logs'!$AB$188, "*"&AE$41&"*") -> 11 | AG51: Leg 5 | AH51: =COUNTIF(Logs!$U$9:'Logs'!$U$1001, "*"&AH$46&"*") -> 7 | AI51: =COUNTIF(Logs!$U$9:'Logs'!$U$1001, "Attention to Detail") -> 14 | AJ51: =COUNTIF(Logs!$U$9:'Logs'!$U$1001, "*"&AJ$46&"*") -> 6 | AK51: =COUNTIF(Logs!$U$9:'Logs'!$U$1001, "*"&AK$46&"*") -> 1 | AL51: =COUNTIF(Logs!$U$9:'Logs'!$U$1001, "*"&AL$46&"*") -> 14 | AM51: =COUNTIF(Logs!$U$9:'Logs'!$U$1001, "*"&AM$46&"*") -> 4 | AN51: =COUNTIF(Logs!$U$9:'Logs'!$U$1001, "*"&AN$46&"*") -> 1 | AO51: =COUNTIF(Logs!$U$9:'Logs'!$U$1001, "*"&AO$46&"*") -> 4 | AP51: =COUNTIF(Logs!$U$9:'Logs'!$U$1001, "*"&AP$46&"*") -> 19 | AQ51: =COUNTIF(Logs!$U$9:'Logs'!$U$1001, "*"&AQ$46&"*") -> 0 | ... AZ51: =COUNTIF(Logs!$U$9:'Logs'!$U$1001, "*"&AZ$46&"*") -> 2 | BA51: =COUNTIF(Logs!$U$9:'Logs'!$U$1001, BA$46) -> 0 | BB51: =COUNTIF(Logs!$U$9:'Logs'!$U$1001, "*"&BB$46&"*") -> 1 | BC51: =COUNTIF(Logs!$U$9:'Logs'!$U$1001, "*"&BC$46&"*") -> 24 | BD51: =COUNTIF(Logs!$U$9:'Logs'!$U$1001, "*"&BD$46&"*") -> 5 | BE51: =COUNTIF(Logs!$U$9:'Logs'!$U$1001, "*"&BE$46&"*") -> 20 | BF51: =COUNTIF(Logs!$U$9:'Logs'!$U$1001, "*"&BF$46&"*") -> 2 | BG51: =COUNTIF(Logs!$U$9:'Logs'!$U$1001, "*"&BG$46&"*") -> 1 | BH51: =COUNTIF(Logs!$U$9:'Logs'!$U$1001, "*"&BH$46&"*") -> 1 | BI51: =COUNTIF(Logs!$U$9:'Logs'!$U$1001, "*"&BI$46&"*") -> 25 | BJ51: =SUM(Table37[[#This Row],[Animals]:[Travel Issues]]) -> 176
B52: Season 11 | C52: =SUM($D52:$AE52) -> 59 | D52: =COUNTIF(Logs!$Q$198:'Logs'!$AC$206, "*"&D$41&"*") -> 4 | E52: =COUNTIF(Logs!$Q$198:'Logs'!$AC$206, "Attention to Detail") -> 4 | F52: =COUNTIF(Logs!$Q$198:'Logs'!$AC$206, "*"&F$41&"*") -> 2 | G52: =COUNTIF(Logs!$Q$198:'Logs'!$AC$206, "*"&G$41&"*") -> 0 | H52: =COUNTIF(Logs!$Q$198:'Logs'!$AC$206, "*"&H$41&"*") -> 1 | I52: =COUNTIF(Logs!$Q$198:'Logs'!$AC$206, "*"&I$41&"*") -> 2 | J52: =COUNTIF(Logs!$Q$198:'Logs'!$AC$206, "*"&J$41&"*") -> 0 | K52: =COUNTIF(Logs!$Q$198:'Logs'!$AC$206, "*"&K$41&"*") -> 0 | L52: =COUNTIF(Logs!$Q$198:'Logs'!$AC$206, "*"&L$41&"*") -> 8 | M52: =COUNTIF(Logs!$Q$198:'Logs'!$AC$206, "*"&M$41&"*") -> 0 | ... O52: =COUNTIF(Logs!$Q$198:'Logs'!$AC$206, "*"&O$41&"*") -> 0 | P52: =COUNTIF(Logs!$Q$198:'Logs'!$AC$206, "Hand Eye Coordination") -> 1 | Q52: =COUNTIF(Logs!$Q$198:'Logs'!$AC$206, "*"&Q$41&"*") -> 2 | R52: =COUNTIF(Logs!$Q$198:'Logs'!$AC$206, "*"&R$41&"*") -> 0 | S52: =COUNTIF(Logs!$Q$198:'Logs'!$AC$206, "*"&S$41&"*") -> 1 | T52: =COUNTIF(Logs!$Q$198:'Logs'!$AC$206, "Memorization") -> 1 | U52: =COUNTIF(Logs!$Q$198:'Logs'!$AC$206, "*"&U$41&"*") -> 0 | V52: =COUNTIF(Logs!$Q$198:'Logs'!$AC$206, "*"&V$41&"*") -> 2 | W52: =COUNTIF(Logs!$Q$198:'Logs'!$AC$206, W$41) -> 0 | X52: =COUNTIF(Logs!$Q$198:'Logs'!$AC$206, "*"&X$41&"*") -> 1 | Y52: =COUNTIF(Logs!$Q$198:'Logs'!$AC$206, "Physical Strength") -> 8 | Z52: =COUNTIF(Logs!$Q$198:'Logs'!$AC$206, "*"&Z$41&"*") -> 3 | AA52: =COUNTIF(Logs!$Q$198:'Logs'!$AC$206, "*"&AA$41&"*") -> 8 | AB52: =COUNTIF(Logs!$Q$198:'Logs'!$AC$206, "*"&AB$41&"*") -> 1 | AC52: =COUNTIF(Logs!$Q$198:'Logs'!$AC$206, "*"&AC$41&"*") -> 0 | AD52: =COUNTIF(Logs!$Q$198:'Logs'!$AC$206, "*"&AD$41&"*") -> 1 | AE52: =COUNTIF(Logs!$Q$198:'Logs'!$AC$206, "*"&AE$41&"*") -> 7 | AG52: Leg 6 | AH52: =COUNTIF(Logs!$V$9:'Logs'!$V$1001, "*"&AH$46&"*") -> 10 | AI52: =COUNTIF(Logs!$V$9:'Logs'!$V$1001, "Attention to Detail") -> 15 | AJ52: =COUNTIF(Logs!$V$9:'Logs'!$V$1001, "*"&AJ$46&"*") -> 4 | AK52: =COUNTIF(Logs!$V$9:'Logs'!$V$1001, "*"&AK$46&"*") -> 2 | AL52: =COUNTIF(Logs!$V$9:'Logs'!$V$1001, "*"&AL$46&"*") -> 7 | AM52: =COUNTIF(Logs!$V$9:'Logs'!$V$1001, "*"&AM$46&"*") -> 4 | AN52: =COUNTIF(Logs!$V$9:'Logs'!$V$1001, "*"&AN$46&"*") -> 1 | AO52: =COUNTIF(Logs!$V$9:'Logs'!$V$1001, "*"&AO$46&"*") -> 1 | AP52: =COUNTIF(Logs!$V$9:'Logs'!$V$1001, "*"&AP$46&"*") -> 17 | AQ52: =COUNTIF(Logs!$V$9:'Logs'!$V$1001, "*"&AQ$46&"*") -> 0 | ... AZ52: =COUNTIF(Logs!$V$9:'Logs'!$V$1001, "*"&AZ$46&"*") -> 3 | BA52: =COUNTIF(Logs!$V$9:'Logs'!$V$1001,BA$46) -> 2 | BB52: =COUNTIF(Logs!$V$9:'Logs'!$V$1001, "*"&BB$46&"*") -> 3 | BC52: =COUNTIF(Logs!$V$9:'Logs'!$V$1001, "*"&BC$46&"*") -> 24 | BD52: =COUNTIF(Logs!$V$9:'Logs'!$V$1001, "*"&BD$46&"*") -> 8 | BE52: =COUNTIF(Logs!$V$9:'Logs'!$V$1001, "*"&BE$46&"*") -> 18 | BF52: =COUNTIF(Logs!$V$9:'Logs'!$V$1001, "*"&BF$46&"*") -> 2 | BG52: =COUNTIF(Logs!$V$9:'Logs'!$V$1001, "*"&BG$46&"*") -> 3 | BH52: =COUNTIF(Logs!$V$9:'Logs'!$V$1001, "*"&BH$46&"*") -> 2 | BI52: =COUNTIF(Logs!$V$9:'Logs'!$V$1001, "*"&BI$46&"*") -> 25 | BJ52: =SUM(Table37[[#This Row],[Animals]:[Travel Issues]]) -> 185
B53: Season 12 | C53: =SUM($D53:$AE53) -> 52 | D53: =COUNTIF(Logs!$Q$215:'Logs'!$AA$223, "*"&D$41&"*") -> 2 | E53: =COUNTIF(Logs!$Q$215:'Logs'!$AA$223, "Attention to Detail") -> 1 | F53: =COUNTIF(Logs!$Q$215:'Logs'!$AA$223, "*"&F$41&"*") -> 1 | G53: =COUNTIF(Logs!$Q$215:'Logs'!$AA$223, "*"&G$41&"*") -> 4 | H53: =COUNTIF(Logs!$Q$215:'Logs'!$AA$223, "*"&H$41&"*") -> 1 | I53: =COUNTIF(Logs!$Q$215:'Logs'!$AA$223, "*"&I$41&"*") -> 0 | J53: =COUNTIF(Logs!$Q$215:'Logs'!$AA$223, "*"&J$41&"*") -> 1 | K53: =COUNTIF(Logs!$Q$215:'Logs'!$AA$223, "*"&K$41&"*") -> 2 | L53: =COUNTIF(Logs!$Q$215:'Logs'!$AA$223, "*"&L$41&"*") -> 6 | M53: =COUNTIF(Logs!$Q$215:'Logs'!$AA$223, "*"&M$41&"*") -> 0 | ... O53: =COUNTIF(Logs!$Q$215:'Logs'!$AA$223, "*"&O$41&"*") -> 0 | P53: =COUNTIF(Logs!$Q$215:'Logs'!$AA$223, "Hand Eye Coordination") -> 1 | Q53: =COUNTIF(Logs!$Q$215:'Logs'!$AA$223, "*"&Q$41&"*") -> 4 | R53: =COUNTIF(Logs!$Q$215:'Logs'!$AA$223, "*"&R$41&"*") -> 2 | S53: =COUNTIF(Logs!$Q$215:'Logs'!$AA$223, "*"&S$41&"*") -> 0 | T53: =COUNTIF(Logs!$Q$215:'Logs'!$AA$223, "Memorization") -> 1 | U53: =COUNTIF(Logs!$Q$215:'Logs'!$AA$223, "*"&U$41&"*") -> 0 | V53: =COUNTIF(Logs!$Q$215:'Logs'!$AA$223, "*"&V$41&"*") -> 0 | W53: =COUNTIF(Logs!$Q$215:'Logs'!$AA$223, W$41) -> 3 | X53: =COUNTIF(Logs!$Q$215:'Logs'!$AA$223, "*"&X$41&"*") -> 0 | Y53: =COUNTIF(Logs!$Q$215:'Logs'!$AA$223, "Physical Strength") -> 8 | Z53: =COUNTIF(Logs!$Q$215:'Logs'!$AA$223, "*"&Z$41&"*") -> 2 | AA53: =COUNTIF(Logs!$Q$215:'Logs'!$AA$223, "*"&AA$41&"*") -> 6 | AB53: =COUNTIF(Logs!$Q$215:'Logs'!$AA$223, "*"&AB$41&"*") -> 0 | AC53: =COUNTIF(Logs!$Q$215:'Logs'!$AA$223, "*"&AC$41&"*") -> 0 | AD53: =COUNTIF(Logs!$Q$215:'Logs'!$AA$223, "*"&AD$41&"*") -> 0 | AE53: =COUNTIF(Logs!$Q$215:'Logs'!$AA$223, "*"&AE$41&"*") -> 5 | AG53: Leg 7 | AH53: =COUNTIF(Logs!$W$9:'Logs'!$W$1001, "*"&AH$46&"*") -> 9 | AI53: =COUNTIF(Logs!$W$9:'Logs'!$W$1001, "Attention to Detail") -> 16 | AJ53: =COUNTIF(Logs!$W$9:'Logs'!$W$1001, "*"&AJ$46&"*") -> 4 | AK53: =COUNTIF(Logs!$W$9:'Logs'!$W$1001, "*"&AK$46&"*") -> 7 | AL53: =COUNTIF(Logs!$W$9:'Logs'!$W$1001, "*"&AL$46&"*") -> 7 | AM53: =COUNTIF(Logs!$W$9:'Logs'!$W$1001, "*"&AM$46&"*") -> 4 | AN53: =COUNTIF(Logs!$W$9:'Logs'!$W$1001, "*"&AN$46&"*") -> 2 | AO53: =COUNTIF(Logs!$W$9:'Logs'!$W$1001, "*"&AO$46&"*") -> 7 | AP53: =COUNTIF(Logs!$W$9:'Logs'!$W$1001, "*"&AP$46&"*") -> 19 | AQ53: =COUNTIF(Logs!$W$9:'Logs'!$W$1001, "*"&AQ$46&"*") -> 0 | ... AZ53: =COUNTIF(Logs!$W$9:'Logs'!$W$1001, "*"&AZ$46&"*") -> 2 | BA53: =COUNTIF(Logs!$W$9:'Logs'!$W$1001, BA$46) -> 2 | BB53: =COUNTIF(Logs!$W$9:'Logs'!$W$1001, "*"&BB$46&"*") -> 2 | BC53: =COUNTIF(Logs!$W$9:'Logs'!$W$1001, "*"&BC$46&"*") -> 20 | BD53: =COUNTIF(Logs!$W$9:'Logs'!$W$1001, "*"&BD$46&"*") -> 8 | BE53: =COUNTIF(Logs!$W$9:'Logs'!$W$1001, "*"&BE$46&"*") -> 18 | BF53: =COUNTIF(Logs!$W$9:'Logs'!$W$1001, "*"&BF$46&"*") -> 1 | BG53: =COUNTIF(Logs!$W$9:'Logs'!$W$1001, "*"&BG$46&"*") -> 2 | BH53: =COUNTIF(Logs!$W$9:'Logs'!$W$1001, "*"&BH$46&"*") -> 6 | BI53: =COUNTIF(Logs!$W$9:'Logs'!$W$1001, "*"&BI$46&"*") -> 23 | BJ53: =SUM(Table37[[#This Row],[Animals]:[Travel Issues]]) -> 192
B54: Season 13 | C54: =SUM($D54:$AE54) -> 47 | D54: =COUNTIF(Logs!$Q$233:'Logs'!$AA$241, "*"&D$41&"*") -> 0 | E54: =COUNTIF(Logs!$Q$233:'Logs'!$AA$241, "Attention to Detail") -> 6 | F54: =COUNTIF(Logs!$Q$233:'Logs'!$AA$241, "*"&F$41&"*") -> 0 | G54: =COUNTIF(Logs!$Q$233:'Logs'!$AA$241, "*"&G$41&"*") -> 1 | H54: =COUNTIF(Logs!$Q$233:'Logs'!$AA$241, "*"&H$41&"*") -> 1 | I54: =COUNTIF(Logs!$Q$233:'Logs'!$AA$241, "*"&I$41&"*") -> 0 | J54: =COUNTIF(Logs!$Q$233:'Logs'!$AA$241, "*"&J$41&"*") -> 1 | K54: =COUNTIF(Logs!$Q$233:'Logs'!$AA$241, "*"&K$41&"*") -> 1 | L54: =COUNTIF(Logs!$Q$233:'Logs'!$AA$241, "*"&L$41&"*") -> 3 | M54: =COUNTIF(Logs!$Q$233:'Logs'!$AA$241, "*"&M$41&"*") -> 0 | ... O54: =COUNTIF(Logs!$Q$233:'Logs'!$AA$241, "*"&O$41&"*") -> 0 | P54: =COUNTIF(Logs!$Q$233:'Logs'!$AA$241, "Hand Eye Coordination") -> 1 | Q54: =COUNTIF(Logs!$Q$233:'Logs'!$AA$241, "*"&Q$41&"*") -> 2 | R54: =COUNTIF(Logs!$Q$233:'Logs'!$AA$241, "*"&R$41&"*") -> 0 | S54: =COUNTIF(Logs!$Q$233:'Logs'!$AA$241, "*"&S$41&"*") -> 1 | T54: =COUNTIF(Logs!$Q$233:'Logs'!$AA$241, "Memorization") -> 1 | U54: =COUNTIF(Logs!$Q$233:'Logs'!$AA$241, "*"&U$41&"*") -> 1 | V54: =COUNTIF(Logs!$Q$233:'Logs'!$AA$241, "*"&V$41&"*") -> 0 | W54: =COUNTIF(Logs!$Q$233:'Logs'!$AA$241, W$41) -> 1 | X54: =COUNTIF(Logs!$Q$233:'Logs'!$AA$241, "*"&X$41&"*") -> 1 | Y54: =COUNTIF(Logs!$Q$233:'Logs'!$AA$241,"Physical Strength") -> 7 | Z54: =COUNTIF(Logs!$Q$233:'Logs'!$AA$241, "*"&Z$41&"*") -> 1 | AA54: =COUNTIF(Logs!$Q$233:'Logs'!$AA$241, "*"&AA$41&"*") -> 8 | AB54: =COUNTIF(Logs!$Q$233:'Logs'!$AA$241, "*"&AB$41&"*") -> 2 | AC54: =COUNTIF(Logs!$Q$233:'Logs'!$AA$241, "*"&AC$41&"*") -> 0 | AD54: =COUNTIF(Logs!$Q$233:'Logs'!$AA$241, "*"&AD$41&"*") -> 0 | AE54: =COUNTIF(Logs!$Q$233:'Logs'!$AA$241, "*"&AE$41&"*") -> 6 | AG54: Leg 8 | AH54: =COUNTIF(Logs!$X$9:'Logs'!$X$1001, "*"&AH$46&"*") -> 13 | AI54: =COUNTIF(Logs!$X$9:'Logs'!$X$1001,"Attention to Detail") -> 21 | AJ54: =COUNTIF(Logs!$X$9:'Logs'!$X$1001, "*"&AJ$46&"*") -> 3 | AK54: =COUNTIF(Logs!$X$9:'Logs'!$X$1001, "*"&AK$46&"*") -> 3 | AL54: =COUNTIF(Logs!$X$9:'Logs'!$X$1001, "*"&AL$46&"*") -> 8 | AM54: =COUNTIF(Logs!$X$9:'Logs'!$X$1001, "*"&AM$46&"*") -> 6 | AN54: =COUNTIF(Logs!$X$9:'Logs'!$X$1001, "*"&AN$46&"*") -> 1 | AO54: =COUNTIF(Logs!$X$9:'Logs'!$X$1001, "*"&AO$46&"*") -> 5 | AP54: =COUNTIF(Logs!$X$9:'Logs'!$X$1001, "*"&AP$46&"*") -> 17 | AQ54: =COUNTIF(Logs!$X$9:'Logs'!$X$1001, "*"&AQ$46&"*") -> 0 | ... AZ54: =COUNTIF(Logs!$X$9:'Logs'!$X$1001, "*"&AZ$46&"*") -> 4 | BA54: =COUNTIF(Logs!$X$9:'Logs'!$X$1001, BA$46) -> 1 | BB54: =COUNTIF(Logs!$X$9:'Logs'!$X$1001, "*"&BB$46&"*") -> 1 | BC54: =COUNTIF(Logs!$X$9:'Logs'!$X$1001, "*"&BC$46&"*") -> 26 | BD54: =COUNTIF(Logs!$X$9:'Logs'!$X$1001, "*"&BD$46&"*") -> 5 | BE54: =COUNTIF(Logs!$X$9:'Logs'!$X$1001, "*"&BE$46&"*") -> 19 | BF54: =COUNTIF(Logs!$X$9:'Logs'!$X$1001, "*"&BF$46&"*") -> 1 | BG54: =COUNTIF(Logs!$X$9:'Logs'!$X$1001, "*"&BG$46&"*") -> 2 | BH54: =COUNTIF(Logs!$X$9:'Logs'!$X$1001, "*"&BH$46&"*") -> 1 | BI54: =COUNTIF(Logs!$X$9:'Logs'!$X$1001, "*"&BI$46&"*") -> 22 | BJ54: =SUM(Table37[[#This Row],[Animals]:[Travel Issues]]) -> 193
B55: Season 14 | C55: =SUM($D55:$AE55) -> 54 | D55: =COUNTIF(Logs!$Q$250:'Logs'!$AB$258, "*"&D$41&"*") -> 3 | E55: =COUNTIF(Logs!$Q$250:'Logs'!$AB$258, "Attention to Detail") -> 3 | F55: =COUNTIF(Logs!$Q$250:'Logs'!$AB$258, "*"&F$41&"*") -> 2 | G55: =COUNTIF(Logs!$Q$250:'Logs'!$AB$258, "*"&G$41&"*") -> 1 | H55: =COUNTIF(Logs!$Q$250:'Logs'!$AB$258, "*"&H$41&"*") -> 2 | I55: =COUNTIF(Logs!$Q$250:'Logs'!$AB$258, "*"&I$41&"*") -> 0 | J55: =COUNTIF(Logs!$Q$250:'Logs'!$AB$258, "*"&J$41&"*") -> 0 | K55: =COUNTIF(Logs!$Q$250:'Logs'!$AB$258, "*"&K$41&"*") -> 2 | L55: =COUNTIF(Logs!$Q$250:'Logs'!$AB$258, "*"&L$41&"*") -> 3 | M55: =COUNTIF(Logs!$Q$250:'Logs'!$AB$258, "*"&M$41&"*") -> 0 | ... O55: =COUNTIF(Logs!$Q$250:'Logs'!$AB$258, "*"&O$41&"*") -> 0 | P55: =COUNTIF(Logs!$Q$250:'Logs'!$AB$258, "Hand Eye Coordination") -> 0 | Q55: =COUNTIF(Logs!$Q$250:'Logs'!$AB$258, "*"&Q$41&"*") -> 2 | R55: =COUNTIF(Logs!$Q$250:'Logs'!$AB$258, "*"&R$41&"*") -> 4 | S55: =COUNTIF(Logs!$Q$250:'Logs'!$AB$258, "*"&S$41&"*") -> 0 | T55: =COUNTIF(Logs!$Q$250:'Logs'!$AB$258,"Memorization") -> 2 | U55: =COUNTIF(Logs!$Q$250:'Logs'!$AB$258, "*"&U$41&"*") -> 0 | V55: =COUNTIF(Logs!$Q$250:'Logs'!$AB$258, "*"&V$41&"*") -> 0 | W55: =COUNTIF(Logs!$Q$250:'Logs'!$AB$258,W$41) -> 2 | X55: =COUNTIF(Logs!$Q$250:'Logs'!$AB$258, "*"&X$41&"*") -> 2 | Y55: =COUNTIF(Logs!$Q$250:'Logs'!$AB$258, "Physical Strength") -> 8 | Z55: =COUNTIF(Logs!$Q$250:'Logs'!$AB$258, "*"&Z$41&"*") -> 2 | AA55: =COUNTIF(Logs!$Q$250:'Logs'!$AB$258, "*"&AA$41&"*") -> 8 | AB55: =COUNTIF(Logs!$Q$250:'Logs'!$AB$258, "*"&AB$41&"*") -> 0 | AC55: =COUNTIF(Logs!$Q$250:'Logs'!$AB$258, "*"&AC$41&"*") -> 1 | AD55: =COUNTIF(Logs!$Q$250:'Logs'!$AB$258, "*"&AD$41&"*") -> 1 | AE55: =COUNTIF(Logs!$Q$250:'Logs'!$AB$258, "*"&AE$41&"*") -> 4 | AG55: Leg 9 | AH55: =COUNTIF(Logs!$Y$9:'Logs'!$Y$1001, "*"&AH$46&"*") -> 12 | AI55: =COUNTIF(Logs!$Y$9:'Logs'!$Y$1001, "Attention to Detail") -> 15 | AJ55: =COUNTIF(Logs!$Y$9:'Logs'!$Y$1001, "*"&AJ$46&"*") -> 3 | AK55: =COUNTIF(Logs!$Y$9:'Logs'!$Y$1001, "*"&AK$46&"*") -> 6 | AL55: =COUNTIF(Logs!$Y$9:'Logs'!$Y$1001, "*"&AL$46&"*") -> 9 | AM55: =COUNTIF(Logs!$Y$9:'Logs'!$Y$1001, "*"&AM$46&"*") -> 2 | AN55: =COUNTIF(Logs!$Y$9:'Logs'!$Y$1001, "*"&AN$46&"*") -> 1 | AO55: =COUNTIF(Logs!$Y$9:'Logs'!$Y$1001, "*"&AO$46&"*") -> 2 | AP55: =COUNTIF(Logs!$Y$9:'Logs'!$Y$1001, "*"&AP$46&"*") -> 14 | AQ55: =COUNTIF(Logs!$Y$9:'Logs'!$Y$1001, "*"&AQ$46&"*") -> 0 | ... AZ55: =COUNTIF(Logs!$Y$9:'Logs'!$Y$1001, "*"&AZ$46&"*") -> 0 | BA55: =COUNTIF(Logs!$Y$9:'Logs'!$Y$1001,BA$46) -> 6 | BB55: =COUNTIF(Logs!$Y$9:'Logs'!$Y$1001, "*"&BB$46&"*") -> 2 | BC55: =COUNTIF(Logs!$Y$9:'Logs'!$Y$1001, "*"&BC$46&"*") -> 28 | BD55: =COUNTIF(Logs!$Y$9:'Logs'!$Y$1001, "*"&BD$46&"*") -> 5 | BE55: =COUNTIF(Logs!$Y$9:'Logs'!$Y$1001, "*"&BE$46&"*") -> 20 | BF55: =COUNTIF(Logs!$Y$9:'Logs'!$Y$1001, "*"&BF$46&"*") -> 4 | BG55: =COUNTIF(Logs!$Y$9:'Logs'!$Y$1001, "*"&BG$46&"*") -> 1 | BH55: =COUNTIF(Logs!$Y$9:'Logs'!$Y$1001, "*"&BH$46&"*") -> 4 | BI55: =COUNTIF(Logs!$Y$9:'Logs'!$Y$1001, "*"&BI$46&"*") -> 23 | BJ55: =SUM(Table37[[#This Row],[Animals]:[Travel Issues]]) -> 197
B56: Season 15 | C56: =SUM($D56:$AE56) -> 54 | D56: =COUNTIF(Logs!$Q$267:'Logs'!$AB$275, "*"&D$41&"*") -> 1 | E56: =COUNTIF(Logs!$Q$267:'Logs'!$AB$275, "Attention to Detail") -> 2 | F56: =COUNTIF(Logs!$Q$267:'Logs'!$AB$275, "*"&F$41&"*") -> 0 | G56: =COUNTIF(Logs!$Q$267:'Logs'!$AB$275, "*"&G$41&"*") -> 1 | H56: =COUNTIF(Logs!$Q$267:'Logs'!$AB$275, "*"&H$41&"*") -> 2 | I56: =COUNTIF(Logs!$Q$267:'Logs'!$AB$275, "*"&I$41&"*") -> 2 | J56: =COUNTIF(Logs!$Q$267:'Logs'!$AB$275, "*"&J$41&"*") -> 1 | K56: =COUNTIF(Logs!$Q$267:'Logs'!$AB$275, "*"&K$41&"*") -> 1 | L56: =COUNTIF(Logs!$Q$267:'Logs'!$AB$275, "*"&L$41&"*") -> 2 | M56: =COUNTIF(Logs!$Q$267:'Logs'!$AB$275, "*"&M$41&"*") -> 0 | ... O56: =COUNTIF(Logs!$Q$267:'Logs'!$AB$275, "*"&O$41&"*") -> 0 | P56: =COUNTIF(Logs!$Q$267:'Logs'!$AB$275, "Hand Eye Coordination") -> 3 | Q56: =COUNTIF(Logs!$Q$267:'Logs'!$AB$275, "*"&Q$41&"*") -> 3 | R56: =COUNTIF(Logs!$Q$267:'Logs'!$AB$275, "*"&R$41&"*") -> 3 | S56: =COUNTIF(Logs!$Q$267:'Logs'!$AB$275, "*"&S$41&"*") -> 2 | T56: =COUNTIF(Logs!$Q$267:'Logs'!$AB$275, "Memorization") -> 0 | U56: =COUNTIF(Logs!$Q$267:'Logs'!$AB$275, "*"&U$41&"*") -> 0 | V56: =COUNTIF(Logs!$Q$267:'Logs'!$AB$275, "*"&V$41&"*") -> 0 | W56: =COUNTIF(Logs!$Q$267:'Logs'!$AB$275, W$41) -> 2 | X56: =COUNTIF(Logs!$Q$267:'Logs'!$AB$275, "*"&X$41&"*") -> 0 | Y56: =COUNTIF(Logs!$Q$267:'Logs'!$AB$275,"Physical Strength") -> 8 | Z56: =COUNTIF(Logs!$Q$267:'Logs'!$AB$275, "*"&Z$41&"*") -> 4 | AA56: =COUNTIF(Logs!$Q$267:'Logs'!$AB$275, "*"&AA$41&"*") -> 8 | AB56: =COUNTIF(Logs!$Q$267:'Logs'!$AB$275, "*"&AB$41&"*") -> 2 | AC56: =COUNTIF(Logs!$Q$267:'Logs'!$AB$275, "*"&AC$41&"*") -> 0 | AD56: =COUNTIF(Logs!$Q$267:'Logs'!$AB$275, "*"&AD$41&"*") -> 1 | AE56: =COUNTIF(Logs!$Q$267:'Logs'!$AB$275, "*"&AE$41&"*") -> 3 | AG56: Leg 10 | AH56: =COUNTIF(Logs!$Z$9:'Logs'!$Z$600, "*"&AH46&"*") + COUNTIF(Logs!$Z$623:'Logs'!$Z$1001, "*"&AH46&"*") -> 7 | AI56: =COUNTIF(Logs!$Z$9:'Logs'!$Z$600, "Attention to Detail") + COUNTIF(Logs!$Z$623:'Logs'!$Z$1001, "Attention to Detail") -> 14 | AJ56: =COUNTIF(Logs!$Z$9:'Logs'!$Z$600, "*"&AJ46&"*") + COUNTIF(Logs!$Z$623:'Logs'!$Z$1001, "*"&AJ46&"*") -> 3 | AK56: =COUNTIF(Logs!$Z$9:'Logs'!$Z$600, "*"&AK46&"*") + COUNTIF(Logs!$Z$623:'Logs'!$Z$1001, "*"&AK46&"*") -> 4 | AL56: =COUNTIF(Logs!$Z$9:'Logs'!$Z$600, "*"&AL46&"*") + COUNTIF(Logs!$Z$623:'Logs'!$Z$1001, "*"&AL46&"*") -> 6 | AM56: =COUNTIF(Logs!$Z$9:'Logs'!$Z$600, "*"&AM46&"*") + COUNTIF(Logs!$Z$623:'Logs'!$Z$1001, "*"&AM46&"*") -> 5 | AN56: =COUNTIF(Logs!$Z$9:'Logs'!$Z$600, "*"&AN46&"*") + COUNTIF(Logs!$Z$623:'Logs'!$Z$1001, "*"&AN46&"*") -> 2 | AO56: =COUNTIF(Logs!$Z$9:'Logs'!$Z$600, "*"&AO46&"*") + COUNTIF(Logs!$Z$623:'Logs'!$Z$1001, "*"&AO46&"*") -> 2 | AP56: =COUNTIF(Logs!$Z$9:'Logs'!$Z$600, "*"&AP46&"*") + COUNTIF(Logs!$Z$623:'Logs'!$Z$1001, "*"&AP46&"*") -> 15 | AQ56: =COUNTIF(Logs!$Z$9:'Logs'!$Z$600, "*"&AQ46&"*") + COUNTIF(Logs!$Z$623:'Logs'!$Z$1001, "*"&AQ46&"*") -> 1 | ... AZ56: =COUNTIF(Logs!$Z$9:'Logs'!$Z$600, "*"&AZ46&"*") + COUNTIF(Logs!$Z$623:'Logs'!$Z$1001, "*"&AZ46&"*") -> 2 | BA56: =COUNTIF(Logs!$Z$9:'Logs'!$Z$600, BA$46) + COUNTIF(Logs!$Z$623:'Logs'!$Z$1001, BA$46) -> 3 | BB56: =COUNTIF(Logs!$Z$9:'Logs'!$Z$600, "*"&BB46&"*") + COUNTIF(Logs!$Z$623:'Logs'!$Z$1001, "*"&BB46&"*") -> 2 | BC56: =COUNTIF(Logs!$Z$9:'Logs'!$Z$600, "*"&BC46&"*") + COUNTIF(Logs!$Z$623:'Logs'!$Z$1001, "*"&BC46&"*") -> 27 | BD56: =COUNTIF(Logs!$Z$9:'Logs'!$Z$600, "*"&BD46&"*") + COUNTIF(Logs!$Z$623:'Logs'!$Z$1001, "*"&BD46&"*") -> 2 | BE56: =COUNTIF(Logs!$Z$9:'Logs'!$Z$600, "*"&BE46&"*") + COUNTIF(Logs!$Z$623:'Logs'!$Z$1001, "*"&BE46&"*") -> 22 | BF56: =COUNTIF(Logs!$Z$9:'Logs'!$Z$600, "*"&BF46&"*") + COUNTIF(Logs!$Z$623:'Logs'!$Z$1001, "*"&BF46&"*") -> 1 | BG56: =COUNTIF(Logs!$Z$9:'Logs'!$Z$600, "*"&BG46&"*") + COUNTIF(Logs!$Z$623:'Logs'!$Z$1001, "*"&BG46&"*") -> 0 | BH56: =COUNTIF(Logs!$Z$9:'Logs'!$Z$600, "*"&BH46&"*") + COUNTIF(Logs!$Z$623:'Logs'!$Z$1001, "*"&BH46&"*") -> 7 | BI56: =COUNTIF(Logs!$Z$9:'Logs'!$Z$600, "*"&BI46&"*") + COUNTIF(Logs!$Z$623:'Logs'!$Z$1001, "*"&BI46&"*") -> 19 | BJ56: =SUM(Table37[[#This Row],[Animals]:[Travel Issues]]) -> 180
B57: Season 16 | C57: =SUM($D57:$AE57) -> 52 | D57: =COUNTIF(Logs!$Q$285:'Logs'!$AB$293, "*"&D$41&"*") -> 2 | E57: =COUNTIF(Logs!$Q$285:'Logs'!$AB$293, "Attention to Detail") -> 2 | F57: =COUNTIF(Logs!$Q$285:'Logs'!$AB$293, "*"&F$41&"*") -> 2 | G57: =COUNTIF(Logs!$Q$285:'Logs'!$AB$293, "*"&G$41&"*") -> 0 | H57: =COUNTIF(Logs!$Q$285:'Logs'!$AB$293, "*"&H$41&"*") -> 1 | I57: =COUNTIF(Logs!$Q$285:'Logs'!$AB$293, "*"&I$41&"*") -> 1 | J57: =COUNTIF(Logs!$Q$285:'Logs'!$AB$293, "*"&J$41&"*") -> 1 | K57: =COUNTIF(Logs!$Q$285:'Logs'!$AB$293, "*"&K$41&"*") -> 0 | L57: =COUNTIF(Logs!$Q$285:'Logs'!$AB$293, "*"&L$41&"*") -> 4 | M57: =COUNTIF(Logs!$Q$285:'Logs'!$AB$293, "*"&M$41&"*") -> 0 | ... O57: =COUNTIF(Logs!$Q$285:'Logs'!$AB$293, "*"&O$41&"*") -> 0 | P57: =COUNTIF(Logs!$Q$285:'Logs'!$AB$293, "Hand Eye Coordination") -> 3 | Q57: =COUNTIF(Logs!$Q$285:'Logs'!$AB$293, "*"&Q$41&"*") -> 3 | R57: =COUNTIF(Logs!$Q$285:'Logs'!$AB$293, "*"&R$41&"*") -> 1 | S57: =COUNTIF(Logs!$Q$285:'Logs'!$AB$293, "*"&S$41&"*") -> 1 | T57: =COUNTIF(Logs!$Q$285:'Logs'!$AB$293,"Memorization") -> 1 | U57: =COUNTIF(Logs!$Q$285:'Logs'!$AB$293, "*"&U$41&"*") -> 1 | V57: =COUNTIF(Logs!$Q$285:'Logs'!$AB$293, "*"&V$41&"*") -> 1 | W57: =COUNTIF(Logs!$Q$285:'Logs'!$AB$293, W$41) -> 0 | X57: =COUNTIF(Logs!$Q$285:'Logs'!$AB$293, "*"&X$41&"*") -> 1 | Y57: =COUNTIF(Logs!$Q$285:'Logs'!$AB$293, "Physical Strength") -> 4 | Z57: =COUNTIF(Logs!$Q$285:'Logs'!$AB$293, "*"&Z$41&"*") -> 3 | AA57: =COUNTIF(Logs!$Q$285:'Logs'!$AB$293, "*"&AA$41&"*") -> 7 | AB57: =COUNTIF(Logs!$Q$285:'Logs'!$AB$293, "*"&AB$41&"*") -> 1 | AC57: =COUNTIF(Logs!$Q$285:'Logs'!$AB$293, "*"&AC$41&"*") -> 0 | AD57: =COUNTIF(Logs!$Q$285:'Logs'!$AB$293, "*"&AD$41&"*") -> 2 | AE57: =COUNTIF(Logs!$Q$285:'Logs'!$AB$293, "*"&AE$41&"*") -> 9 | AG57: Leg 11 | AH57: =COUNTIF(Logs!$AA$9:'Logs'!$AA$210, "*"&AH46&"*") + COUNTIF(Logs!$AA$250:'Logs'!$AA$569, "*"&AH46&"*") + COUNTIF(Logs!$AA$623:'Logs'!$AA$632, "*"&AH46&"*")+COUNTIF(Logs!$AA$655:'Logs'!$AA$1001, "*"&AH46&"*") -> 5 | AI57: =COUNTIF(Logs!$AA$9:'Logs'!$AA$210, "Attention to Detail") + COUNTIF(Logs!$AA$250:'Logs'!$AA$569, "Attention to Detail") + COUNTIF(Logs!$AA$623:'Logs'!$AA$632, "Attention to Detail")+COUNTIF(Logs!$AA$655:'Logs'!$AA$1001, "Attention to Detail") -> 13 | AJ57: =COUNTIF(Logs!$AA$9:'Logs'!$AA$210, "*"&AJ46&"*") + COUNTIF(Logs!$AA$250:'Logs'!$AA$569, "*"&AJ46&"*") + COUNTIF(Logs!$AA$623:'Logs'!$AA$632, "*"&AJ46&"*")+COUNTIF(Logs!$AA$655:'Logs'!$AA$1001, "*"&AJ46&"*") -> 4 | AK57: =COUNTIF(Logs!$AA$9:'Logs'!$AA$210, "*"&AK46&"*") + COUNTIF(Logs!$AA$250:'Logs'!$AA$569, "*"&AK46&"*") + COUNTIF(Logs!$AA$623:'Logs'!$AA$632, "*"&AK46&"*")+COUNTIF(Logs!$AA$655:'Logs'!$AA$1001, "*"&AK46&"*") -> 2 | AL57: =COUNTIF(Logs!$AA$9:'Logs'!$AA$210, "*"&AL46&"*") + COUNTIF(Logs!$AA$250:'Logs'!$AA$569, "*"&AL46&"*") + COUNTIF(Logs!$AA$623:'Logs'!$AA$632, "*"&AL46&"*")+COUNTIF(Logs!$AA$655:'Logs'!$AA$1001, "*"&AL46&"*") -> 4 | AM57: =COUNTIF(Logs!$AA$9:'Logs'!$AA$210, "*"&AM46&"*") + COUNTIF(Logs!$AA$250:'Logs'!$AA$569, "*"&AM46&"*") + COUNTIF(Logs!$AA$623:'Logs'!$AA$632, "*"&AM46&"*")+COUNTIF(Logs!$AA$655:'Logs'!$AA$1001, "*"&AM46&"*") -> 6 | AN57: =COUNTIF(Logs!$AA$9:'Logs'!$AA$210, "*"&AN46&"*") + COUNTIF(Logs!$AA$250:'Logs'!$AA$569, "*"&AN46&"*") + COUNTIF(Logs!$AA$623:'Logs'!$AA$632, "*"&AN46&"*")+COUNTIF(Logs!$AA$655:'Logs'!$AA$1001, "*"&AN46&"*") -> 1 | AO57: =COUNTIF(Logs!$AA$9:'Logs'!$AA$210, "*"&AO46&"*") + COUNTIF(Logs!$AA$250:'Logs'!$AA$569, "*"&AO46&"*") + COUNTIF(Logs!$AA$623:'Logs'!$AA$632, "*"&AO46&"*")+COUNTIF(Logs!$AA$655:'Logs'!$AA$1001, "*"&AO46&"*") -> 4 | AP57: =COUNTIF(Logs!$AA$9:'Logs'!$AA$210, "*"&AP46&"*") + COUNTIF(Logs!$AA$250:'Logs'!$AA$569, "*"&AP46&"*") + COUNTIF(Logs!$AA$623:'Logs'!$AA$632, "*"&AP46&"*")+COUNTIF(Logs!$AA$655:'Logs'!$AA$1001, "*"&AP46&"*") -> 12 | AQ57: =COUNTIF(Logs!$AA$9:'Logs'!$AA$210, "*"&AQ46&"*") + COUNTIF(Logs!$AA$250:'Logs'!$AA$569, "*"&AQ46&"*") + COUNTIF(Logs!$AA$623:'Logs'!$AA$632, "*"&AQ46&"*")+COUNTIF(Logs!$AA$655:'Logs'!$AA$1001, "*"&AQ46&"*") -> 0 | ... AZ57: =COUNTIF(Logs!$AA$9:'Logs'!$AA$210, "*"&AZ46&"*") + COUNTIF(Logs!$AA$250:'Logs'!$AA$569, "*"&AZ46&"*") + COUNTIF(Logs!$AA$623:'Logs'!$AA$632, "*"&AZ46&"*")+COUNTIF(Logs!$AA$655:'Logs'!$AA$1001, "*"&AZ46&"*") -> 0 | BA57: =COUNTIF(Logs!$AA$9:'Logs'!$AA$210, BA$46) + COUNTIF(Logs!$AA$250:'Logs'!$AA$569, BA$46) + COUNTIF(Logs!$AA$623:'Logs'!$AA$632, BA$46)+COUNTIF(Logs!$AA$655:'Logs'!$AA$1001, BA$46) -> 4 | BB57: =COUNTIF(Logs!$AA$9:'Logs'!$AA$210, "*"&BB46&"*") + COUNTIF(Logs!$AA$250:'Logs'!$AA$569, "*"&BB46&"*") + COUNTIF(Logs!$AA$623:'Logs'!$AA$632, "*"&BB46&"*")+COUNTIF(Logs!$AA$655:'Logs'!$AA$1001, "*"&BB46&"*") -> 2 | BC57: =COUNTIF(Logs!$AA$9:'Logs'!$AA$210, "*"&BC46&"*") + COUNTIF(Logs!$AA$250:'Logs'!$AA$569, "*"&BC46&"*") + COUNTIF(Logs!$AA$623:'Logs'!$AA$632, "*"&BC46&"*")+COUNTIF(Logs!$AA$655:'Logs'!$AA$1001, "*"&BC46&"*") -> 21 | BD57: =COUNTIF(Logs!$AA$9:'Logs'!$AA$210, "*"&BD46&"*") + COUNTIF(Logs!$AA$250:'Logs'!$AA$569, "*"&BD46&"*") + COUNTIF(Logs!$AA$623:'Logs'!$AA$632, "*"&BD46&"*")+COUNTIF(Logs!$AA$655:'Logs'!$AA$1001, "*"&BD46&"*") -> 7 | BE57: =COUNTIF(Logs!$AA$9:'Logs'!$AA$210, "*"&BE46&"*") + COUNTIF(Logs!$AA$250:'Logs'!$AA$569, "*"&BE46&"*") + COUNTIF(Logs!$AA$623:'Logs'!$AA$632, "*"&BE46&"*")+COUNTIF(Logs!$AA$655:'Logs'!$AA$1001, "*"&BE46&"*") -> 15 | BF57: =COUNTIF(Logs!$AA$9:'Logs'!$AA$210, "*"&BF46&"*") + COUNTIF(Logs!$AA$250:'Logs'!$AA$569, "*"&BF46&"*") + COUNTIF(Logs!$AA$623:'Logs'!$AA$632, "*"&BF46&"*")+COUNTIF(Logs!$AA$655:'Logs'!$AA$1001, "*"&BF46&"*") -> 3 | BG57: =COUNTIF(Logs!$AA$9:'Logs'!$AA$210, "*"&BG46&"*") + COUNTIF(Logs!$AA$250:'Logs'!$AA$569, "*"&BG46&"*") + COUNTIF(Logs!$AA$623:'Logs'!$AA$632, "*"&BG46&"*")+COUNTIF(Logs!$AA$655:'Logs'!$AA$1001, "*"&BG46&"*") -> 0 | BH57: =COUNTIF(Logs!$AA$9:'Logs'!$AA$210, "*"&BH46&"*") + COUNTIF(Logs!$AA$250:'Logs'!$AA$569, "*"&BH46&"*") + COUNTIF(Logs!$AA$623:'Logs'!$AA$632, "*"&BH46&"*")+COUNTIF(Logs!$AA$655:'Logs'!$AA$1001, "*"&BH46&"*") -> 4 | BI57: =COUNTIF(Logs!$AA$9:'Logs'!$AA$210, "*"&BI46&"*") + COUNTIF(Logs!$AA$250:'Logs'!$AA$569, "*"&BI46&"*") + COUNTIF(Logs!$AA$623:'Logs'!$AA$632, "*"&BI46&"*")+COUNTIF(Logs!$AA$655:'Logs'!$AA$1001, "*"&BI46&"*") -> 21 | BJ57: =SUM(Table37[[#This Row],[Animals]:[Travel Issues]]) -> 159
B58: Season 17 | C58: =SUM($D58:$AE58) -> 67 | D58: =COUNTIF(Logs!$Q$302:'Logs'!$AB$310, "*"&D$41&"*") -> 1 | E58: =COUNTIF(Logs!$Q$302:'Logs'!$AB$310, "Attention to Detail") -> 4 | F58: =COUNTIF(Logs!$Q$302:'Logs'!$AB$310, "*"&F$41&"*") -> 5 | G58: =COUNTIF(Logs!$Q$302:'Logs'!$AB$310, "*"&G$41&"*") -> 1 | H58: =COUNTIF(Logs!$Q$302:'Logs'!$AB$310, "*"&H$41&"*") -> 4 | I58: =COUNTIF(Logs!$Q$302:'Logs'!$AB$310, "*"&I$41&"*") -> 0 | J58: =COUNTIF(Logs!$Q$302:'Logs'!$AB$310, "*"&J$41&"*") -> 0 | K58: =COUNTIF(Logs!$Q$302:'Logs'!$AB$310, "*"&K$41&"*") -> 0 | L58: =COUNTIF(Logs!$Q$302:'Logs'!$AB$310, "*"&L$41&"*") -> 6 | M58: =COUNTIF(Logs!$Q$302:'Logs'!$AB$310, "*"&M$41&"*") -> 0 | ... O58: =COUNTIF(Logs!$Q$302:'Logs'!$AB$310, "*"&O$41&"*") -> 1 | P58: =COUNTIF(Logs!$Q$302:'Logs'!$AB$310, "Hand Eye Coordination") -> 3 | Q58: =COUNTIF(Logs!$Q$302:'Logs'!$AB$310, "*"&Q$41&"*") -> 3 | R58: =COUNTIF(Logs!$Q$302:'Logs'!$AB$310, "*"&R$41&"*") -> 0 | S58: =COUNTIF(Logs!$Q$302:'Logs'!$AB$310, "*"&S$41&"*") -> 0 | T58: =COUNTIF(Logs!$Q$302:'Logs'!$AB$310, "Memorization") -> 2 | U58: =COUNTIF(Logs!$Q$302:'Logs'!$AB$310, "*"&U$41&"*") -> 2 | V58: =COUNTIF(Logs!$Q$302:'Logs'!$AB$310, "*"&V$41&"*") -> 1 | W58: =COUNTIF(Logs!$Q$302:'Logs'!$AB$310, W$41) -> 1 | X58: =COUNTIF(Logs!$Q$302:'Logs'!$AB$310, "*"&X$41&"*") -> 0 | Y58: =COUNTIF(Logs!$Q$302:'Logs'!$AB$310, "Physical Strength") -> 9 | Z58: =COUNTIF(Logs!$Q$302:'Logs'!$AB$310, "*"&Z$41&"*") -> 5 | AA58: =COUNTIF(Logs!$Q$302:'Logs'!$AB$310, "*"&AA$41&"*") -> 7 | AB58: =COUNTIF(Logs!$Q$302:'Logs'!$AB$310, "*"&AB$41&"*") -> 1 | AC58: =COUNTIF(Logs!$Q$302:'Logs'!$AB$310, "*"&AC$41&"*") -> 0 | AD58: =COUNTIF(Logs!$Q$302:'Logs'!$AB$310, "*"&AD$41&"*") -> 0 | AE58: =COUNTIF(Logs!$Q$302:'Logs'!$AB$310, "*"&AE$41&"*") -> 8 | AG58: Leg 12 | AH58: =COUNTIF(Logs!$AB$9:'Logs'!$AB$90, "*"&AH46&"*") + COUNTIF(Logs!$AB$120:'Logs'!$AB$129, "*"&AH46&"*")+ COUNTIF(Logs!$AB$159:'Logs'!$AB$168, "*"&AH46&"*")+ COUNTIF(Logs!$AB$198:'Logs'!$AB$207, "*"&AH46&"*") -> 1 | AI58: =COUNTIF(Logs!$AB$9:'Logs'!$AB$90, "Attention to Detail") + COUNTIF(Logs!$AB$120:'Logs'!$AB$129, "Attention to Detail")+ COUNTIF(Logs!$AB$159:'Logs'!$AB$168, "Attention to Detail")+ COUNTIF(Logs!$AB$198:'Logs'!$AB$207, "Attention to Detail") -> 1 | AJ58: =COUNTIF(Logs!$AB$9:'Logs'!$AB$90, "*"&AJ46&"*") + COUNTIF(Logs!$AB$120:'Logs'!$AB$129, "*"&AJ46&"*")+ COUNTIF(Logs!$AB$159:'Logs'!$AB$168, "*"&AJ46&"*")+ COUNTIF(Logs!$AB$198:'Logs'!$AB$207, "*"&AJ46&"*") -> 2 | AK58: =COUNTIF(Logs!$AB$9:'Logs'!$AB$90, "*"&AK46&"*") + COUNTIF(Logs!$AB$120:'Logs'!$AB$129, "*"&AK46&"*")+ COUNTIF(Logs!$AB$159:'Logs'!$AB$168, "*"&AK46&"*")+ COUNTIF(Logs!$AB$198:'Logs'!$AB$207, "*"&AK46&"*") -> 3 | AL58: =COUNTIF(Logs!$AB$9:'Logs'!$AB$90, "*"&AL46&"*") + COUNTIF(Logs!$AB$120:'Logs'!$AB$129, "*"&AL46&"*")+ COUNTIF(Logs!$AB$159:'Logs'!$AB$168, "*"&AL46&"*")+ COUNTIF(Logs!$AB$198:'Logs'!$AB$207, "*"&AL46&"*") -> 2 | AM58: =COUNTIF(Logs!$AB$9:'Logs'!$AB$90, "*"&AM46&"*") + COUNTIF(Logs!$AB$120:'Logs'!$AB$129, "*"&AM46&"*")+ COUNTIF(Logs!$AB$159:'Logs'!$AB$168, "*"&AM46&"*")+ COUNTIF(Logs!$AB$198:'Logs'!$AB$207, "*"&AM46&"*") -> 0 | AN58: =COUNTIF(Logs!$AB$9:'Logs'!$AB$90, "*"&AN46&"*") + COUNTIF(Logs!$AB$120:'Logs'!$AB$129, "*"&AN46&"*")+ COUNTIF(Logs!$AB$159:'Logs'!$AB$168, "*"&AN46&"*")+ COUNTIF(Logs!$AB$198:'Logs'!$AB$207, "*"&AN46&"*") -> 0 | AO58: =COUNTIF(Logs!$AB$9:'Logs'!$AB$90, "*"&AO46&"*") + COUNTIF(Logs!$AB$120:'Logs'!$AB$129, "*"&AO46&"*")+ COUNTIF(Logs!$AB$159:'Logs'!$AB$168, "*"&AO46&"*")+ COUNTIF(Logs!$AB$198:'Logs'!$AB$207, "*"&AO46&"*") -> 0 | AP58: =COUNTIF(Logs!$AB$9:'Logs'!$AB$90, "*"&AP46&"*") + COUNTIF(Logs!$AB$120:'Logs'!$AB$129, "*"&AP46&"*")+ COUNTIF(Logs!$AB$159:'Logs'!$AB$168, "*"&AP46&"*")+ COUNTIF(Logs!$AB$198:'Logs'!$AB$207, "*"&AP46&"*") -> 5 | AQ58: =COUNTIF(Logs!$AB$9:'Logs'!$AB$90, "*"&AQ46&"*") + COUNTIF(Logs!$AB$120:'Logs'!$AB$129, "*"&AQ46&"*")+ COUNTIF(Logs!$AB$159:'Logs'!$AB$168, "*"&AQ46&"*")+ COUNTIF(Logs!$AB$198:'Logs'!$AB$207, "*"&AQ46&"*") -> 1 | ... AS58: =COUNTIF(Logs!$AB$9:'Logs'!$AB$90, "*"&AS46&"*") + COUNTIF(Logs!$AB$120:'Logs'!$AB$129, "*"&AS46&"*")+ COUNTIF(Logs!$AB$159:'Logs'!$AB$168, "*"&AS46&"*")+ COUNTIF(Logs!$AB$198:'Logs'!$AB$207, "*"&AS46&"*") -> 0 | AT58: =COUNTIF(Logs!$AB$9:'Logs'!$AB$90, "Hand Eye Coordination") + COUNTIF(Logs!$AB$120:'Logs'!$AB$129, "Hand Eye Coordination")+ COUNTIF(Logs!$AB$159:'Logs'!$AB$168, "Hand Eye Coordination")+ COUNTIF(Logs!$AB$198:'Logs'!$AB$207, "Hand Eye Coordination") -> 0 | AU58: =COUNTIF(Logs!$AB$9:'Logs'!$AB$90, "*"&AU46&"*") + COUNTIF(Logs!$AB$120:'Logs'!$AB$129, "*"&AU46&"*")+ COUNTIF(Logs!$AB$159:'Logs'!$AB$168, "*"&AU46&"*")+ COUNTIF(Logs!$AB$198:'Logs'!$AB$207, "*"&AU46&"*") -> 1 | AV58: =COUNTIF(Logs!$AB$9:'Logs'!$AB$90, "*"&AV46&"*") + COUNTIF(Logs!$AB$120:'Logs'!$AB$129, "*"&AV46&"*")+ COUNTIF(Logs!$AB$159:'Logs'!$AB$168, "*"&AV46&"*")+ COUNTIF(Logs!$AB$198:'Logs'!$AB$207, "*"&AV46&"*") -> 0 | AW58: =COUNTIF(Logs!$AB$9:'Logs'!$AB$90, "*"&AW46&"*") + COUNTIF(Logs!$AB$120:'Logs'!$AB$129, "*"&AW46&"*")+ COUNTIF(Logs!$AB$159:'Logs'!$AB$168, "*"&AW46&"*")+ COUNTIF(Logs!$AB$198:'Logs'!$AB$207, "*"&AW46&"*") -> 0 | AX58: =COUNTIF(Logs!$AB$9:'Logs'!$AB$90, "*"&AX46&"*") + COUNTIF(Logs!$AB$120:'Logs'!$AB$129, "*"&AX46&"*")+ COUNTIF(Logs!$AB$159:'Logs'!$AB$168, "*"&AX46&"*")+ COUNTIF(Logs!$AB$198:'Logs'!$AB$207, "*"&AX46&"*") -> 0 | AY58: =COUNTIF(Logs!$AB$9:'Logs'!$AB$90, "*"&AY46&"*") + COUNTIF(Logs!$AB$120:'Logs'!$AB$129, "*"&AY46&"*")+ COUNTIF(Logs!$AB$159:'Logs'!$AB$168, "*"&AY46&"*")+ COUNTIF(Logs!$AB$198:'Logs'!$AB$207, "*"&AY46&"*") -> 0 | AZ58: =COUNTIF(Logs!$AB$9:'Logs'!$AB$90, "*"&AZ46&"*") + COUNTIF(Logs!$AB$120:'Logs'!$AB$129, "*"&AZ46&"*")+ COUNTIF(Logs!$AB$159:'Logs'!$AB$168, "*"&AZ46&"*")+ COUNTIF(Logs!$AB$198:'Logs'!$AB$207, "*"&AZ46&"*") -> 1 | BA58: =COUNTIF(Logs!$AB$9:'Logs'!$AB$90, BA$46) + COUNTIF(Logs!$AB$120:'Logs'!$AB$129, BA$46)+ COUNTIF(Logs!$AB$159:'Logs'!$AB$168, BA$46)+ COUNTIF(Logs!$AB$198:'Logs'!$AB$207, BA$46) -> 0 | BB58: =COUNTIF(Logs!$AB$9:'Logs'!$AB$90, "*"&BB46&"*") + COUNTIF(Logs!$AB$120:'Logs'!$AB$129, "*"&BB46&"*")+ COUNTIF(Logs!$AB$159:'Logs'!$AB$168, "*"&BB46&"*")+ COUNTIF(Logs!$AB$198:'Logs'!$AB$207, "*"&BB46&"*") -> 0 | BC58: =COUNTIF(Logs!$AB$9:'Logs'!$AB$90, "Physical Strength") + COUNTIF(Logs!$AB$120:'Logs'!$AB$129, "Physical Strength")+ COUNTIF(Logs!$AB$159:'Logs'!$AB$168, "Physical Strength")+ COUNTIF(Logs!$AB$198:'Logs'!$AB$207, "Physical Strength") -> 6 | BD58: =COUNTIF(Logs!$AB$9:'Logs'!$AB$90, "*"&BD46&"*") + COUNTIF(Logs!$AB$120:'Logs'!$AB$129, "*"&BD46&"*")+ COUNTIF(Logs!$AB$159:'Logs'!$AB$168, "*"&BD46&"*")+ COUNTIF(Logs!$AB$198:'Logs'!$AB$207, "*"&BD46&"*") -> 0 | BE58: =COUNTIF(Logs!$AB$9:'Logs'!$AB$90, "*"&BE46&"*") + COUNTIF(Logs!$AB$120:'Logs'!$AB$129, "*"&BE46&"*")+ COUNTIF(Logs!$AB$159:'Logs'!$AB$168, "*"&BE46&"*")+ COUNTIF(Logs!$AB$198:'Logs'!$AB$207, "*"&BE46&"*") -> 7 | BF58: =COUNTIF(Logs!$AB$9:'Logs'!$AB$90, "*"&BF46&"*") + COUNTIF(Logs!$AB$120:'Logs'!$AB$129, "*"&BF46&"*")+ COUNTIF(Logs!$AB$159:'Logs'!$AB$168, "*"&BF46&"*")+ COUNTIF(Logs!$AB$198:'Logs'!$AB$207, "*"&BF46&"*") -> 0 | BG58: =COUNTIF(Logs!$AB$9:'Logs'!$AB$90, "*"&BG46&"*") + COUNTIF(Logs!$AB$120:'Logs'!$AB$129, "*"&BG46&"*")+ COUNTIF(Logs!$AB$159:'Logs'!$AB$168, "*"&BG46&"*")+ COUNTIF(Logs!$AB$198:'Logs'!$AB$207, "*"&BG46&"*") -> 0 | BH58: =COUNTIF(Logs!$AB$9:'Logs'!$AB$90, "*"&BH46&"*") + COUNTIF(Logs!$AB$120:'Logs'!$AB$129, "*"&BH46&"*")+ COUNTIF(Logs!$AB$159:'Logs'!$AB$168, "*"&BH46&"*")+ COUNTIF(Logs!$AB$198:'Logs'!$AB$207, "*"&BH46&"*") -> 2 | BI58: =COUNTIF(Logs!$AB$9:'Logs'!$AB$90, "*"&BI46&"*") + COUNTIF(Logs!$AB$120:'Logs'!$AB$129, "*"&BI46&"*")+ COUNTIF(Logs!$AB$159:'Logs'!$AB$168, "*"&BI46&"*")+ COUNTIF(Logs!$AB$198:'Logs'!$AB$207, "*"&BI46&"*") -> 6 | BJ58: =SUM(Table37[[#This Row],[Animals]:[Travel Issues]]) -> 38
B59: Season 18 | C59: =SUM($D59:$AE59) -> 62 | D59: =COUNTIF(Logs!$Q$320:'Logs'!$AB$328, "*"&D$41&"*") -> 1 | E59: =COUNTIF(Logs!$Q$320:'Logs'!$AB$328, "Attention to Detail") -> 7 | F59: =COUNTIF(Logs!$Q$320:'Logs'!$AB$328, "*"&F$41&"*") -> 0 | G59: =COUNTIF(Logs!$Q$320:'Logs'!$AB$328, "*"&G$41&"*") -> 2 | H59: =COUNTIF(Logs!$Q$320:'Logs'!$AB$328, "*"&H$41&"*") -> 2 | I59: =COUNTIF(Logs!$Q$320:'Logs'!$AB$328, "*"&I$41&"*") -> 3 | J59: =COUNTIF(Logs!$Q$320:'Logs'!$AB$328, "*"&J$41&"*") -> 0 | K59: =COUNTIF(Logs!$Q$320:'Logs'!$AB$328, "*"&K$41&"*") -> 3 | L59: =COUNTIF(Logs!$Q$320:'Logs'!$AB$328, "*"&L$41&"*") -> 5 | M59: =COUNTIF(Logs!$Q$320:'Logs'!$AB$328, "*"&M$41&"*") -> 0 | ... O59: =COUNTIF(Logs!$Q$320:'Logs'!$AB$328, "*"&O$41&"*") -> 0 | P59: =COUNTIF(Logs!$Q$320:'Logs'!$AB$328, "Hand Eye Coordination") -> 1 | Q59: =COUNTIF(Logs!$Q$320:'Logs'!$AB$328, "*"&Q$41&"*") -> 1 | R59: =COUNTIF(Logs!$Q$320:'Logs'!$AB$328, "*"&R$41&"*") -> 0 | S59: =COUNTIF(Logs!$Q$320:'Logs'!$AB$328, "*"&S$41&"*") -> 1 | T59: =COUNTIF(Logs!$Q$320:'Logs'!$AB$328, "Memorization") -> 2 | U59: =COUNTIF(Logs!$Q$320:'Logs'!$AB$328, "*"&U$41&"*") -> 0 | V59: =COUNTIF(Logs!$Q$320:'Logs'!$AB$328, "*"&V$41&"*") -> 0 | W59: =COUNTIF(Logs!$Q$320:'Logs'!$AB$328, W$41) -> 2 | X59: =COUNTIF(Logs!$Q$320:'Logs'!$AB$328, "*"&X$41&"*") -> 3 | Y59: =COUNTIF(Logs!$Q$320:'Logs'!$AB$328, "Physical Strength") -> 7 | Z59: =COUNTIF(Logs!$Q$320:'Logs'!$AB$328, "*"&Z$41&"*") -> 4 | AA59: =COUNTIF(Logs!$Q$320:'Logs'!$AB$328, "*"&AA$41&"*") -> 7 | AB59: =COUNTIF(Logs!$Q$320:'Logs'!$AB$328, "*"&AB$41&"*") -> 1 | AC59: =COUNTIF(Logs!$Q$320:'Logs'!$AB$328, "*"&AC$41&"*") -> 0 | AD59: =COUNTIF(Logs!$Q$320:'Logs'!$AB$328, "*"&AD$41&"*") -> 0 | AE59: =COUNTIF(Logs!$Q$320:'Logs'!$AB$328, "*"&AE$41&"*") -> 8 | AG59: Final Leg | AH59: =COUNTIF(Logs!$AC$9:'Logs'!$AC$1001, "*"&AH$46&"*")+COUNTIF(Logs!$AB$101:'Logs'!$AB$110, "*"&AH$46&"*")+COUNTIF(Logs!$AB$139:'Logs'!$AB$147, "*"&AH$46&"*")+COUNTIF(Logs!$AB$177:'Logs'!$AB$188, "*"&AH$46&"*")+COUNTIF(Logs!$AA$215:'Logs'!$AA$241, "*"&AH$46&"*")+COUNTIF(Logs!$AB$250:'Logs'!$AB$1001, "*"&AH$46&"*")+COUNTIF(Logs!$AA$571:'Logs'!$AA$599, "*"&AH$46&"*")+COUNTIF(Logs!$Z$607:'Logs'!$Z$615, "*"&AH$46&"*")+COUNTIF(Logs!$AA$640:'Logs'!$AA$649, "*"&AH$46&"*") -> 2 | AI59: =COUNTIF(Logs!$AC$9:'Logs'!$AC$1001,"Attention to Detail")+COUNTIF(Logs!$AB$101:'Logs'!$AB$110, "Attention to Detail")+COUNTIF(Logs!$AB$139:'Logs'!$AB$147, "Attention to Detail")+COUNTIF(Logs!$AB$177:'Logs'!$AB$188,"Attention to Detail")+COUNTIF(Logs!$AA$215:'Logs'!$AA$241,"Attention to Detail")+COUNTIF(Logs!$AB$250:'Logs'!$AB$1001,"Attention to Detail")+COUNTIF(Logs!$AA$571:'Logs'!$AA$599, "Attention to Detail")+COUNTIF(Logs!$Z$607:'Logs'!$Z$615, "Attention to Detail")+COUNTIF(Logs!$AA$640:'Logs'!$AA$649, "Attention to Detail") -> 11 | AJ59: =COUNTIF(Logs!$AC$9:'Logs'!$AC$1001, "*"&AJ$46&"*")+COUNTIF(Logs!$AB$101:'Logs'!$AB$110, "*"&AJ$46&"*")+COUNTIF(Logs!$AB$139:'Logs'!$AB$147, "*"&AJ$46&"*")+COUNTIF(Logs!$AB$177:'Logs'!$AB$188, "*"&AJ$46&"*")+COUNTIF(Logs!$AA$215:'Logs'!$AA$241, "*"&AJ$46&"*")+COUNTIF(Logs!$AB$250:'Logs'!$AB$1001, "*"&AJ$46&"*")+COUNTIF(Logs!$AA$571:'Logs'!$AA$599, "*"&AJ$46&"*")+COUNTIF(Logs!$Z$607:'Logs'!$Z$615, "*"&AJ$46&"*")+COUNTIF(Logs!$AA$640:'Logs'!$AA$649, "*"&AJ$46&"*") -> 3 | AK59: =COUNTIF(Logs!$AC$9:'Logs'!$AC$1001, "*"&AK$46&"*")+COUNTIF(Logs!$AB$101:'Logs'!$AB$110, "*"&AK$46&"*")+COUNTIF(Logs!$AB$139:'Logs'!$AB$147, "*"&AK$46&"*")+COUNTIF(Logs!$AB$177:'Logs'!$AB$188, "*"&AK$46&"*")+COUNTIF(Logs!$AA$215:'Logs'!$AA$241, "*"&AK$46&"*")+COUNTIF(Logs!$AB$250:'Logs'!$AB$1001, "*"&AK$46&"*")+COUNTIF(Logs!$AA$571:'Logs'!$AA$599, "*"&AK$46&"*")+COUNTIF(Logs!$Z$607:'Logs'!$Z$615, "*"&AK$46&"*")+COUNTIF(Logs!$AA$640:'Logs'!$AA$649, "*"&AK$46&"*") -> 2 | AL59: =COUNTIF(Logs!$AC$9:'Logs'!$AC$1001, "*"&AL$46&"*")+COUNTIF(Logs!$AB$101:'Logs'!$AB$110, "*"&AL$46&"*")+COUNTIF(Logs!$AB$139:'Logs'!$AB$147, "*"&AL$46&"*")+COUNTIF(Logs!$AB$177:'Logs'!$AB$188, "*"&AL$46&"*")+COUNTIF(Logs!$AA$215:'Logs'!$AA$241, "*"&AL$46&"*")+COUNTIF(Logs!$AB$250:'Logs'!$AB$1001, "*"&AL$46&"*")+COUNTIF(Logs!$AA$571:'Logs'!$AA$599, "*"&AL$46&"*")+COUNTIF(Logs!$Z$607:'Logs'!$Z$615, "*"&AL$46&"*")+COUNTIF(Logs!$AA$640:'Logs'!$AA$649, "*"&AL$46&"*") -> 4 | AM59: =COUNTIF(Logs!$AC$9:'Logs'!$AC$1001, "*"&AM$46&"*")+COUNTIF(Logs!$AB$101:'Logs'!$AB$110, "*"&AM$46&"*")+COUNTIF(Logs!$AB$139:'Logs'!$AB$147, "*"&AM$46&"*")+COUNTIF(Logs!$AB$177:'Logs'!$AB$188, "*"&AM$46&"*")+COUNTIF(Logs!$AA$215:'Logs'!$AA$241, "*"&AM$46&"*")+COUNTIF(Logs!$AB$250:'Logs'!$AB$1001, "*"&AM$46&"*")+COUNTIF(Logs!$AA$571:'Logs'!$AA$599, "*"&AM$46&"*")+COUNTIF(Logs!$Z$607:'Logs'!$Z$615, "*"&AM$46&"*")+COUNTIF(Logs!$AA$640:'Logs'!$AA$649, "*"&AM$46&"*") -> 2 | AN59: =COUNTIF(Logs!$AC$9:'Logs'!$AC$1001, "*"&AN$46&"*")+COUNTIF(Logs!$AB$101:'Logs'!$AB$110, "*"&AN$46&"*")+COUNTIF(Logs!$AB$139:'Logs'!$AB$147, "*"&AN$46&"*")+COUNTIF(Logs!$AB$177:'Logs'!$AB$188, "*"&AN$46&"*")+COUNTIF(Logs!$AA$215:'Logs'!$AA$241, "*"&AN$46&"*")+COUNTIF(Logs!$AB$250:'Logs'!$AB$1001, "*"&AN$46&"*")+COUNTIF(Logs!$AA$571:'Logs'!$AA$599, "*"&AN$46&"*")+COUNTIF(Logs!$Z$607:'Logs'!$Z$615, "*"&AN$46&"*")+COUNTIF(Logs!$AA$640:'Logs'!$AA$649, "*"&AN$46&"*") -> 0 | AO59: =COUNTIF(Logs!$AC$9:'Logs'!$AC$1001, "*"&AO$46&"*")+COUNTIF(Logs!$AB$101:'Logs'!$AB$110, "*"&AO$46&"*")+COUNTIF(Logs!$AB$139:'Logs'!$AB$147, "*"&AO$46&"*")+COUNTIF(Logs!$AB$177:'Logs'!$AB$188, "*"&AO$46&"*")+COUNTIF(Logs!$AA$215:'Logs'!$AA$241, "*"&AO$46&"*")+COUNTIF(Logs!$AB$250:'Logs'!$AB$1001, "*"&AO$46&"*")+COUNTIF(Logs!$AA$571:'Logs'!$AA$599, "*"&AO$46&"*")+COUNTIF(Logs!$Z$607:'Logs'!$Z$615, "*"&AO$46&"*")+COUNTIF(Logs!$AA$640:'Logs'!$AA$649, "*"&AO$46&"*") -> 0 | AP59: =COUNTIF(Logs!$AC$9:'Logs'!$AC$1001, "*"&AP$46&"*")+COUNTIF(Logs!$AB$101:'Logs'!$AB$110, "*"&AP$46&"*")+COUNTIF(Logs!$AB$139:'Logs'!$AB$147, "*"&AP$46&"*")+COUNTIF(Logs!$AB$177:'Logs'!$AB$188, "*"&AP$46&"*")+COUNTIF(Logs!$AA$215:'Logs'!$AA$241, "*"&AP$46&"*")+COUNTIF(Logs!$AB$250:'Logs'!$AB$1001, "*"&AP$46&"*")+COUNTIF(Logs!$AA$571:'Logs'!$AA$599, "*"&AP$46&"*")+COUNTIF(Logs!$Z$607:'Logs'!$Z$615, "*"&AP$46&"*")+COUNTIF(Logs!$AA$640:'Logs'!$AA$649, "*"&AP$46&"*") -> 15 | AQ59: =COUNTIF(Logs!$AC$9:'Logs'!$AC$1001, "*"&AQ$46&"*")+COUNTIF(Logs!$AB$101:'Logs'!$AB$110, "*"&AQ$46&"*")+COUNTIF(Logs!$AB$139:'Logs'!$AB$147, "*"&AQ$46&"*")+COUNTIF(Logs!$AB$177:'Logs'!$AB$188, "*"&AQ$46&"*")+COUNTIF(Logs!$AA$215:'Logs'!$AA$241, "*"&AQ$46&"*")+COUNTIF(Logs!$AB$250:'Logs'!$AB$1001, "*"&AQ$46&"*")+COUNTIF(Logs!$AA$571:'Logs'!$AA$599, "*"&AQ$46&"*")+COUNTIF(Logs!$Z$607:'Logs'!$Z$615, "*"&AQ$46&"*")+COUNTIF(Logs!$AA$640:'Logs'!$AA$649, "*"&AQ$46&"*") -> 2 | ... AZ59: =COUNTIF(Logs!$AC$9:'Logs'!$AC$1001, "*"&AZ$46&"*")+COUNTIF(Logs!$AB$101:'Logs'!$AB$110, "*"&AZ$46&"*")+COUNTIF(Logs!$AB$139:'Logs'!$AB$147, "*"&AZ$46&"*")+COUNTIF(Logs!$AB$177:'Logs'!$AB$188, "*"&AZ$46&"*")+COUNTIF(Logs!$AA$215:'Logs'!$AA$241, "*"&AZ$46&"*")+COUNTIF(Logs!$AB$250:'Logs'!$AB$1001, "*"&AZ$46&"*")+COUNTIF(Logs!$AA$571:'Logs'!$AA$599, "*"&AZ$46&"*")+COUNTIF(Logs!$Z$607:'Logs'!$Z$615, "*"&AZ$46&"*")+COUNTIF(Logs!$AA$640:'Logs'!$AA$649, "*"&AZ$46&"*") -> 2 | BA59: =COUNTIF(Logs!$AC$9:'Logs'!$AC$1001,BA$46)+COUNTIF(Logs!$AB$101:'Logs'!$AB$110, BA$46)+COUNTIF(Logs!$AB$139:'Logs'!$AB$147,BA$46)+COUNTIF(Logs!$AB$177:'Logs'!$AB$188, BA$46)+COUNTIF(Logs!$AA$215:'Logs'!$AA$241, BA$46)+COUNTIF(Logs!$AB$250:'Logs'!$AB$1001,BA$46)+COUNTIF(Logs!$AA$571:'Logs'!$AA$599,BA$46)+COUNTIF(Logs!$Z$607:'Logs'!$Z$615, BA$46)+COUNTIF(Logs!$AA$640:'Logs'!$AA$649, BA$46) -> 3 | BB59: =COUNTIF(Logs!$AC$9:'Logs'!$AC$1001, "*"&BB$46&"*")+COUNTIF(Logs!$AB$101:'Logs'!$AB$110, "*"&BB$46&"*")+COUNTIF(Logs!$AB$139:'Logs'!$AB$147, "*"&BB$46&"*")+COUNTIF(Logs!$AB$177:'Logs'!$AB$188, "*"&BB$46&"*")+COUNTIF(Logs!$AA$215:'Logs'!$AA$241, "*"&BB$46&"*")+COUNTIF(Logs!$AB$250:'Logs'!$AB$1001, "*"&BB$46&"*")+COUNTIF(Logs!$AA$571:'Logs'!$AA$599, "*"&BB$46&"*")+COUNTIF(Logs!$Z$607:'Logs'!$Z$615, "*"&BB$46&"*")+COUNTIF(Logs!$AA$640:'Logs'!$AA$649, "*"&BB$46&"*") -> 0 | BC59: =COUNTIF(Logs!$AC$9:'Logs'!$AC$1001, "*"&BC$46&"*")+COUNTIF(Logs!$AB$101:'Logs'!$AB$110, "*"&BC$46&"*")+COUNTIF(Logs!$AB$139:'Logs'!$AB$147, "*"&BC$46&"*")+COUNTIF(Logs!$AB$177:'Logs'!$AB$188, "*"&BC$46&"*")+COUNTIF(Logs!$AA$215:'Logs'!$AA$241, "*"&BC$46&"*")+COUNTIF(Logs!$AB$250:'Logs'!$AB$1001, "*"&BC$46&"*")+COUNTIF(Logs!$AA$571:'Logs'!$AA$599, "*"&BC$46&"*")+COUNTIF(Logs!$Z$607:'Logs'!$Z$615, "*"&BC$46&"*")+COUNTIF(Logs!$AA$640:'Logs'!$AA$649, "*"&BC$46&"*") -> 28 | BD59: =COUNTIF(Logs!$AC$9:'Logs'!$AC$1001, "*"&BD$46&"*")+COUNTIF(Logs!$AB$101:'Logs'!$AB$110, "*"&BD$46&"*")+COUNTIF(Logs!$AB$139:'Logs'!$AB$147, "*"&BD$46&"*")+COUNTIF(Logs!$AB$177:'Logs'!$AB$188, "*"&BD$46&"*")+COUNTIF(Logs!$AA$215:'Logs'!$AA$241, "*"&BD$46&"*")+COUNTIF(Logs!$AB$250:'Logs'!$AB$1001, "*"&BD$46&"*")+COUNTIF(Logs!$AA$571:'Logs'!$AA$599, "*"&BD$46&"*")+COUNTIF(Logs!$Z$607:'Logs'!$Z$615, "*"&BD$46&"*")+COUNTIF(Logs!$AA$640:'Logs'!$AA$649, "*"&BD$46&"*") -> 16 | BE59: =COUNTIF(Logs!$AC$9:'Logs'!$AC$1001, "*"&BE$46&"*")+COUNTIF(Logs!$AB$101:'Logs'!$AB$110, "*"&BE$46&"*")+COUNTIF(Logs!$AB$139:'Logs'!$AB$147, "*"&BE$46&"*")+COUNTIF(Logs!$AB$177:'Logs'!$AB$188, "*"&BE$46&"*")+COUNTIF(Logs!$AA$215:'Logs'!$AA$241, "*"&BE$46&"*")+COUNTIF(Logs!$AB$250:'Logs'!$AB$1001, "*"&BE$46&"*")+COUNTIF(Logs!$AA$571:'Logs'!$AA$599, "*"&BE$46&"*")+COUNTIF(Logs!$Z$607:'Logs'!$Z$615, "*"&BE$46&"*")+COUNTIF(Logs!$AA$640:'Logs'!$AA$649, "*"&BE$46&"*") -> 17 | BF59: =COUNTIF(Logs!$AC$9:'Logs'!$AC$1001, "*"&BF$46&"*")+COUNTIF(Logs!$AB$101:'Logs'!$AB$110, "*"&BF$46&"*")+COUNTIF(Logs!$AB$139:'Logs'!$AB$147, "*"&BF$46&"*")+COUNTIF(Logs!$AB$177:'Logs'!$AB$188, "*"&BF$46&"*")+COUNTIF(Logs!$AA$215:'Logs'!$AA$241, "*"&BF$46&"*")+COUNTIF(Logs!$AB$250:'Logs'!$AB$1001, "*"&BF$46&"*")+COUNTIF(Logs!$AA$571:'Logs'!$AA$599, "*"&BF$46&"*")+COUNTIF(Logs!$Z$607:'Logs'!$Z$615, "*"&BF$46&"*")+COUNTIF(Logs!$AA$640:'Logs'!$AA$649, "*"&BF$46&"*") -> 0 | BG59: =COUNTIF(Logs!$AC$9:'Logs'!$AC$1001, "*"&BG$46&"*")+COUNTIF(Logs!$AB$101:'Logs'!$AB$110, "*"&BG$46&"*")+COUNTIF(Logs!$AB$139:'Logs'!$AB$147, "*"&BG$46&"*")+COUNTIF(Logs!$AB$177:'Logs'!$AB$188, "*"&BG$46&"*")+COUNTIF(Logs!$AA$215:'Logs'!$AA$241, "*"&BG$46&"*")+COUNTIF(Logs!$AB$250:'Logs'!$AB$1001, "*"&BG$46&"*")+COUNTIF(Logs!$AA$571:'Logs'!$AA$599, "*"&BG$46&"*")+COUNTIF(Logs!$Z$607:'Logs'!$Z$615, "*"&BG$46&"*")+COUNTIF(Logs!$AA$640:'Logs'!$AA$649, "*"&BG$46&"*") -> 0 | BH59: =COUNTIF(Logs!$AC$9:'Logs'!$AC$1001, "*"&BH$46&"*")+COUNTIF(Logs!$AB$101:'Logs'!$AB$110, "*"&BH$46&"*")+COUNTIF(Logs!$AB$139:'Logs'!$AB$147, "*"&BH$46&"*")+COUNTIF(Logs!$AB$177:'Logs'!$AB$188, "*"&BH$46&"*")+COUNTIF(Logs!$AA$215:'Logs'!$AA$241, "*"&BH$46&"*")+COUNTIF(Logs!$AB$250:'Logs'!$AB$1001, "*"&BH$46&"*")+COUNTIF(Logs!$AA$571:'Logs'!$AA$599, "*"&BH$46&"*")+COUNTIF(Logs!$Z$607:'Logs'!$Z$615, "*"&BH$46&"*")+COUNTIF(Logs!$AA$640:'Logs'!$AA$649, "*"&BH$46&"*") -> 4 | BI59: =COUNTIF(Logs!$AC$9:'Logs'!$AC$1001, "*"&BI$46&"*")+COUNTIF(Logs!$AB$101:'Logs'!$AB$110, "*"&BI$46&"*")+COUNTIF(Logs!$AB$139:'Logs'!$AB$147, "*"&BI$46&"*")+COUNTIF(Logs!$AB$177:'Logs'!$AB$188, "*"&BI$46&"*")+COUNTIF(Logs!$AA$215:'Logs'!$AA$241, "*"&BI$46&"*")+COUNTIF(Logs!$AB$250:'Logs'!$AB$1001, "*"&BI$46&"*")+COUNTIF(Logs!$AA$571:'Logs'!$AA$599, "*"&BI$46&"*")+COUNTIF(Logs!$Z$607:'Logs'!$Z$615, "*"&BI$46&"*")+COUNTIF(Logs!$AA$640:'Logs'!$AA$649, "*"&BI$46&"*") -> 21 | BJ59: =SUM(Table37[[#This Row],[Animals]:[Travel Issues]]) -> 196
B60: Season 19 | C60: =SUM($D60:$AE60) -> 67 | D60: =COUNTIF(Logs!$Q$338:'Logs'!$AB$346, "*"&D$41&"*") -> 3 | E60: =COUNTIF(Logs!$Q$338:'Logs'!$AB$346, "Attention to Detail") -> 3 | F60: =COUNTIF(Logs!$Q$338:'Logs'!$AB$346, "*"&F$41&"*") -> 1 | G60: =COUNTIF(Logs!$Q$338:'Logs'!$AB$346, "*"&G$41&"*") -> 3 | H60: =COUNTIF(Logs!$Q$338:'Logs'!$AB$346, "*"&H$41&"*") -> 7 | I60: =COUNTIF(Logs!$Q$338:'Logs'!$AB$346, "*"&I$41&"*") -> 1 | J60: =COUNTIF(Logs!$Q$338:'Logs'!$AB$346, "*"&J$41&"*") -> 0 | K60: =COUNTIF(Logs!$Q$338:'Logs'!$AB$346, "*"&K$41&"*") -> 2 | L60: =COUNTIF(Logs!$Q$338:'Logs'!$AB$346, "*"&L$41&"*") -> 4 | M60: =COUNTIF(Logs!$Q$338:'Logs'!$AB$346, "*"&M$41&"*") -> 0 | ... O60: =COUNTIF(Logs!$Q$338:'Logs'!$AB$346, "*"&O$41&"*") -> 1 | P60: =COUNTIF(Logs!$Q$338:'Logs'!$AB$346, "Hand Eye Coordination") -> 1 | Q60: =COUNTIF(Logs!$Q$338:'Logs'!$AB$346, "*"&Q$41&"*") -> 4 | R60: =COUNTIF(Logs!$Q$338:'Logs'!$AB$346, "*"&R$41&"*") -> 1 | S60: =COUNTIF(Logs!$Q$338:'Logs'!$AB$346, "*"&S$41&"*") -> 0 | T60: =COUNTIF(Logs!$Q$338:'Logs'!$AB$346, "Memorization") -> 5 | U60: =COUNTIF(Logs!$Q$338:'Logs'!$AB$346, "*"&U$41&"*") -> 1 | V60: =COUNTIF(Logs!$Q$338:'Logs'!$AB$346, "*"&V$41&"*") -> 1 | W60: =COUNTIF(Logs!$Q$338:'Logs'!$AB$346, W$41) -> 1 | X60: =COUNTIF(Logs!$Q$338:'Logs'!$AB$346, "*"&X$41&"*") -> 0 | Y60: =COUNTIF(Logs!$Q$338:'Logs'!$AB$346, "Physical Strength") -> 7 | Z60: =COUNTIF(Logs!$Q$338:'Logs'!$AB$346, "*"&Z$41&"*") -> 6 | AA60: =COUNTIF(Logs!$Q$338:'Logs'!$AB$346, "*"&AA$41&"*") -> 6 | AB60: =COUNTIF(Logs!$Q$338:'Logs'!$AB$346, "*"&AB$41&"*") -> 0 | AC60: =COUNTIF(Logs!$Q$338:'Logs'!$AB$346, "*"&AC$41&"*") -> 0 | AD60: =COUNTIF(Logs!$Q$338:'Logs'!$AB$346, "*"&AD$41&"*") -> 0 | AE60: =COUNTIF(Logs!$Q$338:'Logs'!$AB$346, "*"&AE$41&"*") -> 9 | AG60: Totals | AH60: =SUM(Table37[Animals]) -> 93 | AI60: =SUM(Table37[ATD]) -> 186 | AJ60: =SUM(Table37[Balance]) -> 49 | AK60: =SUM(Table37[Biking]) -> 43 | AL60: =SUM(Table37[Building]) -> 87 | AM60: =SUM(Table37[Cooking]) -> 44 | AN60: =SUM(Table37[Counting]) -> 11 | AO60: =SUM(Table37[Dancing]) -> 44 | AP60: =SUM(Table37[Driving]) -> 202 | AQ60: =SUM(Table37[Flags]) -> 8 | AR60: =SUM(Table37[Food]) -> 66 | AS60: =SUM(Table37[Geography]) -> 7 | AT60: =SUM(Table37[Hand Eye Coordination]) -> 78 | AU60: =SUM(Table37[Heights]) -> 122 | AV60: =SUM(Table37[Language]) -> 43 | AW60: =SUM(Table37[Math]) -> 15 | AX60: =SUM(Table37[Memorization]) -> 69 | AY60: =SUM(Table37[Music]) -> 20 | AZ60: =SUM(Table37[Navigation]) -> 23 | BA60: =SUM(Table37[Pain]) -> 29 | BB60: =SUM(Table37[Painting]) -> 16 | BC60: =SUM(Table37[Physical Strength]) -> 311 | BD60: =SUM(Table37[Puzzle]) -> 81 | BE60: =SUM(Table37[Searching]) -> 227 | BF60: =SUM(Table37[Selling]) -> 19 | BG60: =SUM(Table37[Singing]) -> 12 | BH60: =SUM(Table37[Swimming]) -> 37 | BI60: =SUM(Table37[Travel Issues]) -> 290 | BJ60: =SUM(Table37[[#Totals],[Animals]:[Travel Issues]]) -> 2232
B61: Season 20 | C61: =SUM($D61:$AE61) -> 65 | D61: =COUNTIF(Logs!$Q$356:'Logs'!$AB$364, "*"&D$41&"*") -> 3 | E61: =COUNTIF(Logs!$Q$356:'Logs'!$AB$364, "Attention to Detail") -> 9 | F61: =COUNTIF(Logs!$Q$356:'Logs'!$AB$364, "*"&F$41&"*") -> 2 | G61: =COUNTIF(Logs!$Q$356:'Logs'!$AB$364, "*"&G$41&"*") -> 1 | H61: =COUNTIF(Logs!$Q$356:'Logs'!$AB$364, "*"&H$41&"*") -> 4 | I61: =COUNTIF(Logs!$Q$356:'Logs'!$AB$364, "*"&I$41&"*") -> 1 | J61: =COUNTIF(Logs!$Q$356:'Logs'!$AB$364, "*"&J$41&"*") -> 0 | K61: =COUNTIF(Logs!$Q$356:'Logs'!$AB$364, "*"&K$41&"*") -> 2 | L61: =COUNTIF(Logs!$Q$356:'Logs'!$AB$364, "*"&L$41&"*") -> 7 | M61: =COUNTIF(Logs!$Q$356:'Logs'!$AB$364, "*"&M$41&"*") -> 0 | ... O61: =COUNTIF(Logs!$Q$356:'Logs'!$AB$364, "*"&O$41&"*") -> 0 | P61: =COUNTIF(Logs!$Q$356:'Logs'!$AB$364, "Hand Eye Coordination") -> 4 | Q61: =COUNTIF(Logs!$Q$356:'Logs'!$AB$364, "*"&Q$41&"*") -> 3 | R61: =COUNTIF(Logs!$Q$356:'Logs'!$AB$364, "*"&R$41&"*") -> 0 | S61: =COUNTIF(Logs!$Q$356:'Logs'!$AB$364, "*"&S$41&"*") -> 1 | T61: =COUNTIF(Logs!$Q$356:'Logs'!$AB$364, "Memorization") -> 1 | U61: =COUNTIF(Logs!$Q$356:'Logs'!$AB$364, "*"&U$41&"*") -> 0 | V61: =COUNTIF(Logs!$Q$356:'Logs'!$AB$364, "*"&V$41&"*") -> 0 | W61: =COUNTIF(Logs!$Q$356:'Logs'!$AB$364, W$41) -> 1 | X61: =COUNTIF(Logs!$Q$356:'Logs'!$AB$364, "*"&X$41&"*") -> 1 | Y61: =COUNTIF(Logs!$Q$356:'Logs'!$AB$364, "Physical Strength") -> 8 | Z61: =COUNTIF(Logs!$Q$356:'Logs'!$AB$364, "*"&Z$41&"*") -> 2 | AA61: =COUNTIF(Logs!$Q$356:'Logs'!$AB$364, "*"&AA$41&"*") -> 4 | AB61: =COUNTIF(Logs!$Q$356:'Logs'!$AB$364, "*"&AB$41&"*") -> 1 | AC61: =COUNTIF(Logs!$Q$356:'Logs'!$AB$364, "*"&AC$41&"*") -> 1 | AD61: =COUNTIF(Logs!$Q$356:'Logs'!$AB$364, "*"&AD$41&"*") -> 0 | AE61: =COUNTIF(Logs!$Q$356:'Logs'!$AB$364, "*"&AE$41&"*") -> 7
B62: Season 21 | C62: =SUM($D62:$AE62) -> 59 | D62: =COUNTIF(Logs!$Q$374:'Logs'!$AB$382, "*"&D$41&"*") -> 2 | E62: =COUNTIF(Logs!$Q$374:'Logs'!$AB$382, "Attention to Detail") -> 6 | F62: =COUNTIF(Logs!$Q$374:'Logs'!$AB$382, "*"&F$41&"*") -> 2 | G62: =COUNTIF(Logs!$Q$374:'Logs'!$AB$382, "*"&G$41&"*") -> 0 | H62: =COUNTIF(Logs!$Q$374:'Logs'!$AB$382, "*"&H$41&"*") -> 3 | I62: =COUNTIF(Logs!$Q$374:'Logs'!$AB$382, "*"&I$41&"*") -> 2 | J62: =COUNTIF(Logs!$Q$374:'Logs'!$AB$382, "*"&J$41&"*") -> 0 | K62: =COUNTIF(Logs!$Q$374:'Logs'!$AB$382, "*"&K$41&"*") -> 3 | L62: =COUNTIF(Logs!$Q$374:'Logs'!$AB$382, "*"&L$41&"*") -> 2 | M62: =COUNTIF(Logs!$Q$374:'Logs'!$AB$382, "*"&M$41&"*") -> 0 | ... O62: =COUNTIF(Logs!$Q$374:'Logs'!$AB$382, "*"&O$41&"*") -> 0 | P62: =COUNTIF(Logs!$Q$374:'Logs'!$AB$382, "Hand Eye Coordination") -> 2 | Q62: =COUNTIF(Logs!$Q$374:'Logs'!$AB$382, "*"&Q$41&"*") -> 1 | R62: =COUNTIF(Logs!$Q$374:'Logs'!$AB$382, "*"&R$41&"*") -> 2 | S62: =COUNTIF(Logs!$Q$374:'Logs'!$AB$382, "*"&S$41&"*") -> 1 | T62: =COUNTIF(Logs!$Q$374:'Logs'!$AB$382, "Memorization") -> 1 | U62: =COUNTIF(Logs!$Q$374:'Logs'!$AB$382, "*"&U$41&"*") -> 0 | V62: =COUNTIF(Logs!$Q$374:'Logs'!$AB$382, "*"&V$41&"*") -> 0 | W62: =COUNTIF(Logs!$Q$374:'Logs'!$AB$382, W$41) -> 1 | X62: =COUNTIF(Logs!$Q$374:'Logs'!$AB$382, "*"&X$41&"*") -> 0 | Y62: =COUNTIF(Logs!$Q$374:'Logs'!$AB$382, "Physical Strength") -> 10 | Z62: =COUNTIF(Logs!$Q$374:'Logs'!$AB$382, "*"&Z$41&"*") -> 3 | AA62: =COUNTIF(Logs!$Q$374:'Logs'!$AB$382, "*"&AA$41&"*") -> 4 | AB62: =COUNTIF(Logs!$Q$374:'Logs'!$AB$382, "*"&AB$41&"*") -> 1 | AC62: =COUNTIF(Logs!$Q$374:'Logs'!$AB$382, "*"&AC$41&"*") -> 0 | AD62: =COUNTIF(Logs!$Q$374:'Logs'!$AB$382, "*"&AD$41&"*") -> 1 | AE62: =COUNTIF(Logs!$Q$374:'Logs'!$AB$382, "*"&AE$41&"*") -> 8
B63: Season 22 | C63: =SUM($D63:$AE63) -> 56 | D63: =COUNTIF(Logs!$Q$393:'Logs'!$AB$401, "*"&D$41&"*") -> 4 | E63: =COUNTIF(Logs!$Q$393:'Logs'!$AB$401, "Attention to Detail") -> 6 | F63: =COUNTIF(Logs!$Q$393:'Logs'!$AB$401, "*"&F$41&"*") -> 2 | G63: =COUNTIF(Logs!$Q$393:'Logs'!$AB$401, "*"&G$41&"*") -> 0 | H63: =COUNTIF(Logs!$Q$393:'Logs'!$AB$401, "*"&H$41&"*") -> 3 | I63: =COUNTIF(Logs!$Q$393:'Logs'!$AB$401, "*"&I$41&"*") -> 1 | J63: =COUNTIF(Logs!$Q$393:'Logs'!$AB$401, "*"&J$41&"*") -> 0 | K63: =COUNTIF(Logs!$Q$393:'Logs'!$AB$401, "*"&K$41&"*") -> 1 | L63: =COUNTIF(Logs!$Q$393:'Logs'!$AB$401, "*"&L$41&"*") -> 4 | M63: =COUNTIF(Logs!$Q$393:'Logs'!$AB$401, "*"&M$41&"*") -> 0 | ... O63: =COUNTIF(Logs!$Q$393:'Logs'!$AB$401, "*"&O$41&"*") -> 1 | P63: =COUNTIF(Logs!$Q$393:'Logs'!$AB$401, "Hand Eye Coordination") -> 3 | Q63: =COUNTIF(Logs!$Q$393:'Logs'!$AB$401, "*"&Q$41&"*") -> 4 | R63: =COUNTIF(Logs!$Q$393:'Logs'!$AB$401, "*"&R$41&"*") -> 0 | S63: =COUNTIF(Logs!$Q$393:'Logs'!$AB$401, "*"&S$41&"*") -> 0 | T63: =COUNTIF(Logs!$Q$393:'Logs'!$AB$401, "Memorization") -> 3 | U63: =COUNTIF(Logs!$Q$393:'Logs'!$AB$401, "*"&U$41&"*") -> 1 | V63: =COUNTIF(Logs!$Q$393:'Logs'!$AB$401, "*"&V$41&"*") -> 0 | W63: =COUNTIF(Logs!$Q$393:'Logs'!$AB$401, W$41) -> 0 | X63: =COUNTIF(Logs!$Q$393:'Logs'!$AB$401, "*"&X$41&"*") -> 1 | Y63: =COUNTIF(Logs!$Q$393:'Logs'!$AB$401, "Physical Strength") -> 9 | Z63: =COUNTIF(Logs!$Q$393:'Logs'!$AB$401, "*"&Z$41&"*") -> 1 | AA63: =COUNTIF(Logs!$Q$393:'Logs'!$AB$401, "*"&AA$41&"*") -> 6 | AB63: =COUNTIF(Logs!$Q$393:'Logs'!$AB$401, "*"&AB$41&"*") -> 0 | AC63: =COUNTIF(Logs!$Q$393:'Logs'!$AB$401, "*"&AC$41&"*") -> 0 | AD63: =COUNTIF(Logs!$Q$393:'Logs'!$AB$401, "*"&AD$41&"*") -> 1 | AE63: =COUNTIF(Logs!$Q$393:'Logs'!$AB$401, "*"&AE$41&"*") -> 4
B64: Season 23 | C64: =SUM($D64:$AE64) -> 55 | D64: =COUNTIF(Logs!$Q$411:'Logs'!$AB$419, "*"&D$41&"*") -> 2 | E64: =COUNTIF(Logs!$Q$411:'Logs'!$AB$419, "Attention to Detail") -> 7 | F64: =COUNTIF(Logs!$Q$411:'Logs'!$AB$419, "*"&F$41&"*") -> 0 | G64: =COUNTIF(Logs!$Q$411:'Logs'!$AB$419, "*"&G$41&"*") -> 0 | H64: =COUNTIF(Logs!$Q$411:'Logs'!$AB$419, "*"&H$41&"*") -> 3 | I64: =COUNTIF(Logs!$Q$411:'Logs'!$AB$419, "*"&I$41&"*") -> 2 | J64: =COUNTIF(Logs!$Q$411:'Logs'!$AB$419, "*"&J$41&"*") -> 0 | K64: =COUNTIF(Logs!$Q$411:'Logs'!$AB$419, "*"&K$41&"*") -> 1 | L64: =COUNTIF(Logs!$Q$411:'Logs'!$AB$419, "*"&L$41&"*") -> 2 | M64: =COUNTIF(Logs!$Q$411:'Logs'!$AB$419, "*"&M$41&"*") -> 0 | ... O64: =COUNTIF(Logs!$Q$411:'Logs'!$AB$419, "*"&O$41&"*") -> 0 | P64: =COUNTIF(Logs!$Q$411:'Logs'!$AB$419, "Hand Eye Coordination") -> 2 | Q64: =COUNTIF(Logs!$Q$411:'Logs'!$AB$419, "*"&Q$41&"*") -> 5 | R64: =COUNTIF(Logs!$Q$411:'Logs'!$AB$419, "*"&R$41&"*") -> 1 | S64: =COUNTIF(Logs!$Q$411:'Logs'!$AB$419, "*"&S$41&"*") -> 1 | T64: =COUNTIF(Logs!$Q$411:'Logs'!$AB$419, "Memorization") -> 2 | U64: =COUNTIF(Logs!$Q$411:'Logs'!$AB$419, "*"&U$41&"*") -> 1 | V64: =COUNTIF(Logs!$Q$411:'Logs'!$AB$419, "*"&V$41&"*") -> 0 | W64: =COUNTIF(Logs!$Q$411:'Logs'!$AB$419, W$41) -> 0 | X64: =COUNTIF(Logs!$Q$411:'Logs'!$AB$419, "*"&X$41&"*") -> 0 | Y64: =COUNTIF(Logs!$Q$411:'Logs'!$AB$419, "Physical Strength") -> 9 | Z64: =COUNTIF(Logs!$Q$411:'Logs'!$AB$419, "*"&Z$41&"*") -> 2 | AA64: =COUNTIF(Logs!$Q$411:'Logs'!$AB$419, "*"&AA$41&"*") -> 7 | AB64: =COUNTIF(Logs!$Q$411:'Logs'!$AB$419, "*"&AB$41&"*") -> 0 | AC64: =COUNTIF(Logs!$Q$411:'Logs'!$AB$419, "*"&AC$41&"*") -> 1 | AD64: =COUNTIF(Logs!$Q$411:'Logs'!$AB$419, "*"&AD$41&"*") -> 2 | AE64: =COUNTIF(Logs!$Q$411:'Logs'!$AB$419, "*"&AE$41&"*") -> 4
B65: Season 24 | C65: =SUM($D65:$AE65) -> 56 | D65: =COUNTIF(Logs!$Q$429:'Logs'!$AB$437, "*"&D$41&"*") -> 4 | E65: =COUNTIF(Logs!$Q$429:'Logs'!$AB$437, "Attention to Detail") -> 8 | F65: =COUNTIF(Logs!$Q$429:'Logs'!$AB$437, "*"&F$41&"*") -> 0 | G65: =COUNTIF(Logs!$Q$429:'Logs'!$AB$437, "*"&G$41&"*") -> 0 | H65: =COUNTIF(Logs!$Q$429:'Logs'!$AB$437, "*"&H$41&"*") -> 2 | I65: =COUNTIF(Logs!$Q$429:'Logs'!$AB$437, "*"&I$41&"*") -> 0 | J65: =COUNTIF(Logs!$Q$429:'Logs'!$AB$437, "*"&J$41&"*") -> 1 | K65: =COUNTIF(Logs!$Q$429:'Logs'!$AB$437, "*"&K$41&"*") -> 3 | L65: =COUNTIF(Logs!$Q$429:'Logs'!$AB$437, "*"&L$41&"*") -> 2 | M65: =COUNTIF(Logs!$Q$429:'Logs'!$AB$437, "*"&M$41&"*") -> 0 | ... O65: =COUNTIF(Logs!$Q$429:'Logs'!$AB$437, "*"&O$41&"*") -> 0 | P65: =COUNTIF(Logs!$Q$429:'Logs'!$AB$437, "Hand Eye Coordination") -> 6 | Q65: =COUNTIF(Logs!$Q$429:'Logs'!$AB$437, "*"&Q$41&"*") -> 2 | R65: =COUNTIF(Logs!$Q$429:'Logs'!$AB$437, "*"&R$41&"*") -> 1 | S65: =COUNTIF(Logs!$Q$429:'Logs'!$AB$437, "*"&S$41&"*") -> 2 | T65: =COUNTIF(Logs!$Q$429:'Logs'!$AB$437, "Memorization") -> 2 | U65: =COUNTIF(Logs!$Q$429:'Logs'!$AB$437, "*"&U$41&"*") -> 1 | V65: =COUNTIF(Logs!$Q$429:'Logs'!$AB$437, "*"&V$41&"*") -> 0 | W65: =COUNTIF(Logs!$Q$429:'Logs'!$AB$437, W$41) -> 0 | X65: =COUNTIF(Logs!$Q$429:'Logs'!$AB$437, "*"&X$41&"*") -> 0 | Y65: =COUNTIF(Logs!$Q$429:'Logs'!$AB$437, "Physical Strength") -> 7 | Z65: =COUNTIF(Logs!$Q$429:'Logs'!$AB$437, "*"&Z$41&"*") -> 1 | AA65: =COUNTIF(Logs!$Q$429:'Logs'!$AB$437, "*"&AA$41&"*") -> 6 | AB65: =COUNTIF(Logs!$Q$429:'Logs'!$AB$437, "*"&AB$41&"*") -> 0 | AC65: =COUNTIF(Logs!$Q$429:'Logs'!$AB$437, "*"&AC$41&"*") -> 0 | AD65: =COUNTIF(Logs!$Q$429:'Logs'!$AB$437, "*"&AD$41&"*") -> 0 | AE65: =COUNTIF(Logs!$Q$429:'Logs'!$AB$437, "*"&AE$41&"*") -> 8
B66: Season 25 | C66: =SUM($D66:$AE66) -> 56 | D66: =COUNTIF(Logs!$Q$447:'Logs'!$AB$455, "*"&D$41&"*") -> 3 | E66: =COUNTIF(Logs!$Q$447:'Logs'!$AB$455, "Attention to Detail") -> 9 | F66: =COUNTIF(Logs!$Q$447:'Logs'!$AB$455, "*"&F$41&"*") -> 3 | G66: =COUNTIF(Logs!$Q$447:'Logs'!$AB$455, "*"&G$41&"*") -> 1 | H66: =COUNTIF(Logs!$Q$447:'Logs'!$AB$455, "*"&H$41&"*") -> 2 | I66: =COUNTIF(Logs!$Q$447:'Logs'!$AB$455, "*"&I$41&"*") -> 0 | J66: =COUNTIF(Logs!$Q$447:'Logs'!$AB$455, "*"&J$41&"*") -> 0 | K66: =COUNTIF(Logs!$Q$447:'Logs'!$AB$455, "*"&K$41&"*") -> 0 | L66: =COUNTIF(Logs!$Q$447:'Logs'!$AB$455, "*"&L$41&"*") -> 4 | M66: =COUNTIF(Logs!$Q$447:'Logs'!$AB$455, "*"&M$41&"*") -> 0 | ... O66: =COUNTIF(Logs!$Q$447:'Logs'!$AB$455, "*"&O$41&"*") -> 1 | P66: =COUNTIF(Logs!$Q$447:'Logs'!$AB$455, "Hand Eye Coordination") -> 1 | Q66: =COUNTIF(Logs!$Q$447:'Logs'!$AB$455, "*"&Q$41&"*") -> 4 | R66: =COUNTIF(Logs!$Q$447:'Logs'!$AB$455, "*"&R$41&"*") -> 1 | S66: =COUNTIF(Logs!$Q$447:'Logs'!$AB$455, "*"&S$41&"*") -> 0 | T66: =COUNTIF(Logs!$Q$447:'Logs'!$AB$455,"Memorization") -> 2 | U66: =COUNTIF(Logs!$Q$447:'Logs'!$AB$455, "*"&U$41&"*") -> 1 | V66: =COUNTIF(Logs!$Q$447:'Logs'!$AB$455, "*"&V$41&"*") -> 0 | W66: =COUNTIF(Logs!$Q$447:'Logs'!$AB$455, W$41) -> 1 | X66: =COUNTIF(Logs!$Q$447:'Logs'!$AB$455, "*"&X$41&"*") -> 1 | Y66: =COUNTIF(Logs!$Q$447:'Logs'!$AB$455,"Physical Strength") -> 10 | Z66: =COUNTIF(Logs!$Q$447:'Logs'!$AB$455, "*"&Z$41&"*") -> 1 | AA66: =COUNTIF(Logs!$Q$447:'Logs'!$AB$455, "*"&AA$41&"*") -> 4 | AB66: =COUNTIF(Logs!$Q$447:'Logs'!$AB$455, "*"&AB$41&"*") -> 0 | AC66: =COUNTIF(Logs!$Q$447:'Logs'!$AB$455, "*"&AC$41&"*") -> 0 | AD66: =COUNTIF(Logs!$Q$447:'Logs'!$AB$455, "*"&AD$41&"*") -> 1 | AE66: =COUNTIF(Logs!$Q$447:'Logs'!$AB$455, "*"&AE$41&"*") -> 6
B67: Season 26 | C67: =SUM($D67:$AE67) -> 66 | D67: =COUNTIF(Logs!$Q$465:'Logs'!$AB$473, "*"&D$41&"*") -> 4 | E67: =COUNTIF(Logs!$Q$465:'Logs'!$AB$473, "Attention to Detail") -> 4 | F67: =COUNTIF(Logs!$Q$465:'Logs'!$AB$473, "*"&F$41&"*") -> 3 | G67: =COUNTIF(Logs!$Q$465:'Logs'!$AB$473, "*"&G$41&"*") -> 0 | H67: =COUNTIF(Logs!$Q$465:'Logs'!$AB$473, "*"&H$41&"*") -> 4 | I67: =COUNTIF(Logs!$Q$465:'Logs'!$AB$473, "*"&I$41&"*") -> 2 | J67: =COUNTIF(Logs!$Q$465:'Logs'!$AB$473, "*"&J$41&"*") -> 0 | K67: =COUNTIF(Logs!$Q$465:'Logs'!$AB$473, "*"&K$41&"*") -> 3 | L67: =COUNTIF(Logs!$Q$465:'Logs'!$AB$473, "*"&L$41&"*") -> 3 | M67: =COUNTIF(Logs!$Q$465:'Logs'!$AB$473, "*"&M$41&"*") -> 0 | ... O67: =COUNTIF(Logs!$Q$465:'Logs'!$AB$473, "*"&O$41&"*") -> 0 | P67: =COUNTIF(Logs!$Q$465:'Logs'!$AB$473, "Hand Eye Coordination") -> 4 | Q67: =COUNTIF(Logs!$Q$465:'Logs'!$AB$473, "*"&Q$41&"*") -> 4 | R67: =COUNTIF(Logs!$Q$465:'Logs'!$AB$473, "*"&R$41&"*") -> 3 | S67: =COUNTIF(Logs!$Q$465:'Logs'!$AB$473, "*"&S$41&"*") -> 1 | T67: =COUNTIF(Logs!$Q$465:'Logs'!$AB$473, "Memorization") -> 1 | U67: =COUNTIF(Logs!$Q$465:'Logs'!$AB$473, "*"&U$41&"*") -> 0 | V67: =COUNTIF(Logs!$Q$465:'Logs'!$AB$473, "*"&V$41&"*") -> 1 | W67: =COUNTIF(Logs!$Q$465:'Logs'!$AB$473,W$41) -> 0 | X67: =COUNTIF(Logs!$Q$465:'Logs'!$AB$473, "*"&X$41&"*") -> 0 | Y67: =COUNTIF(Logs!$Q$465:'Logs'!$AB$473, "Physical Strength") -> 8 | Z67: =COUNTIF(Logs!$Q$465:'Logs'!$AB$473, "*"&Z$41&"*") -> 3 | AA67: =COUNTIF(Logs!$Q$465:'Logs'!$AB$473, "*"&AA$41&"*") -> 4 | AB67: =COUNTIF(Logs!$Q$465:'Logs'!$AB$473, "*"&AB$41&"*") -> 0 | AC67: =COUNTIF(Logs!$Q$465:'Logs'!$AB$473, "*"&AC$41&"*") -> 0 | AD67: =COUNTIF(Logs!$Q$465:'Logs'!$AB$473, "*"&AD$41&"*") -> 1 | AE67: =COUNTIF(Logs!$Q$465:'Logs'!$AB$473, "*"&AE$41&"*") -> 10
B68: Season 27 | C68: =SUM($D68:$AE68) -> 50 | D68: =COUNTIF(Logs!$Q$483:'Logs'!$AB$491, "*"&D$41&"*") -> 2 | E68: =COUNTIF(Logs!$Q$483:'Logs'!$AB$491, "Attention to Detail") -> 7 | F68: =COUNTIF(Logs!$Q$483:'Logs'!$AB$491, "*"&F$41&"*") -> 1 | G68: =COUNTIF(Logs!$Q$483:'Logs'!$AB$491, "*"&G$41&"*") -> 1 | H68: =COUNTIF(Logs!$Q$483:'Logs'!$AB$491, "*"&H$41&"*") -> 2 | I68: =COUNTIF(Logs!$Q$483:'Logs'!$AB$491, "*"&I$41&"*") -> 3 | J68: =COUNTIF(Logs!$Q$483:'Logs'!$AB$491, "*"&J$41&"*") -> 0 | K68: =COUNTIF(Logs!$Q$483:'Logs'!$AB$491, "*"&K$41&"*") -> 1 | L68: =COUNTIF(Logs!$Q$483:'Logs'!$AB$491, "*"&L$41&"*") -> 1 | M68: =COUNTIF(Logs!$Q$483:'Logs'!$AB$491, "*"&M$41&"*") -> 1 | ... O68: =COUNTIF(Logs!$Q$483:'Logs'!$AB$491, "*"&O$41&"*") -> 0 | P68: =COUNTIF(Logs!$Q$483:'Logs'!$AB$491, "Hand Eye Coordination") -> 0 | Q68: =COUNTIF(Logs!$Q$483:'Logs'!$AB$491, "*"&Q$41&"*") -> 3 | R68: =COUNTIF(Logs!$Q$483:'Logs'!$AB$491, "*"&R$41&"*") -> 1 | S68: =COUNTIF(Logs!$Q$483:'Logs'!$AB$491, "*"&S$41&"*") -> 0 | T68: =COUNTIF(Logs!$Q$483:'Logs'!$AB$491, "Memorization") -> 1 | U68: =COUNTIF(Logs!$Q$483:'Logs'!$AB$491, "*"&U$41&"*") -> 1 | V68: =COUNTIF(Logs!$Q$483:'Logs'!$AB$491, "*"&V$41&"*") -> 1 | W68: =COUNTIF(Logs!$Q$483:'Logs'!$AB$491, W$41) -> 0 | X68: =COUNTIF(Logs!$Q$483:'Logs'!$AB$491, "*"&X$41&"*") -> 0 | Y68: =COUNTIF(Logs!$Q$483:'Logs'!$AB$491, "Physical Strength") -> 10 | Z68: =COUNTIF(Logs!$Q$483:'Logs'!$AB$491, "*"&Z$41&"*") -> 1 | AA68: =COUNTIF(Logs!$Q$483:'Logs'!$AB$491, "*"&AA$41&"*") -> 2 | AB68: =COUNTIF(Logs!$Q$483:'Logs'!$AB$491, "*"&AB$41&"*") -> 0 | AC68: =COUNTIF(Logs!$Q$483:'Logs'!$AB$491, "*"&AC$41&"*") -> 1 | AD68: =COUNTIF(Logs!$Q$483:'Logs'!$AB$491, "*"&AD$41&"*") -> 1 | AE68: =COUNTIF(Logs!$Q$483:'Logs'!$AB$491, "*"&AE$41&"*") -> 8
B69: Season 28 | C69: =SUM($D69:$AE69) -> 49 | D69: =COUNTIF(Logs!$Q$501:'Logs'!$AB$509, "*"&D$41&"*") -> 3 | E69: =COUNTIF(Logs!$Q$501:'Logs'!$AB$509, "Attention to Detail") -> 5 | F69: =COUNTIF(Logs!$Q$501:'Logs'!$AB$509, "*"&F$41&"*") -> 1 | G69: =COUNTIF(Logs!$Q$501:'Logs'!$AB$509, "*"&G$41&"*") -> 1 | H69: =COUNTIF(Logs!$Q$501:'Logs'!$AB$509, "*"&H$41&"*") -> 5 | I69: =COUNTIF(Logs!$Q$501:'Logs'!$AB$509, "*"&I$41&"*") -> 2 | J69: =COUNTIF(Logs!$Q$501:'Logs'!$AB$509, "*"&J$41&"*") -> 1 | K69: =COUNTIF(Logs!$Q$501:'Logs'!$AB$509, "*"&K$41&"*") -> 1 | L69: =COUNTIF(Logs!$Q$501:'Logs'!$AB$509, "*"&L$41&"*") -> 0 | M69: =COUNTIF(Logs!$Q$501:'Logs'!$AB$509, "*"&M$41&"*") -> 1 | ... O69: =COUNTIF(Logs!$Q$501:'Logs'!$AB$509, "*"&O$41&"*") -> 1 | P69: =COUNTIF(Logs!$Q$501:'Logs'!$AB$509, "Hand Eye Coordination") -> 0 | Q69: =COUNTIF(Logs!$Q$501:'Logs'!$AB$509, "*"&Q$41&"*") -> 3 | R69: =COUNTIF(Logs!$Q$501:'Logs'!$AB$509, "*"&R$41&"*") -> 0 | S69: =COUNTIF(Logs!$Q$501:'Logs'!$AB$509, "*"&S$41&"*") -> 0 | T69: =COUNTIF(Logs!$Q$501:'Logs'!$AB$509, "Memorization") -> 2 | U69: =COUNTIF(Logs!$Q$501:'Logs'!$AB$509, "*"&U$41&"*") -> 0 | V69: =COUNTIF(Logs!$Q$501:'Logs'!$AB$509, "*"&V$41&"*") -> 0 | W69: =COUNTIF(Logs!$Q$501:'Logs'!$AB$509, W$41) -> 0 | X69: =COUNTIF(Logs!$Q$501:'Logs'!$AB$509, "*"&X$41&"*") -> 0 | Y69: =COUNTIF(Logs!$Q$501:'Logs'!$AB$509, "Physical Strength") -> 9 | Z69: =COUNTIF(Logs!$Q$501:'Logs'!$AB$509, "*"&Z$41&"*") -> 2 | AA69: =COUNTIF(Logs!$Q$501:'Logs'!$AB$509, "*"&AA$41&"*") -> 4 | AB69: =COUNTIF(Logs!$Q$501:'Logs'!$AB$509, "*"&AB$41&"*") -> 1 | AC69: =COUNTIF(Logs!$Q$501:'Logs'!$AB$509, "*"&AC$41&"*") -> 0 | AD69: =COUNTIF(Logs!$Q$501:'Logs'!$AB$509, "*"&AD$41&"*") -> 1 | AE69: =COUNTIF(Logs!$Q$501:'Logs'!$AB$509, "*"&AE$41&"*") -> 5
B70: Season 29 | C70: =SUM($D70:$AE70) -> 47 | D70: =COUNTIF(Logs!$Q$519:'Logs'!$AB$527, "*"&D$41&"*") -> 0 | E70: =COUNTIF(Logs!$Q$519:'Logs'!$AB$527, "Attention to Detail") -> 5 | F70: =COUNTIF(Logs!$Q$519:'Logs'!$AB$527, "*"&F$41&"*") -> 0 | G70: =COUNTIF(Logs!$Q$519:'Logs'!$AB$527, "*"&G$41&"*") -> 1 | H70: =COUNTIF(Logs!$Q$519:'Logs'!$AB$527, "*"&H$41&"*") -> 3 | I70: =COUNTIF(Logs!$Q$519:'Logs'!$AB$527, "*"&I$41&"*") -> 3 | J70: =COUNTIF(Logs!$Q$519:'Logs'!$AB$527, "*"&J$41&"*") -> 0 | K70: =COUNTIF(Logs!$Q$519:'Logs'!$AB$527, "*"&K$41&"*") -> 1 | L70: =COUNTIF(Logs!$Q$519:'Logs'!$AB$527, "*"&L$41&"*") -> 1 | M70: =COUNTIF(Logs!$Q$519:'Logs'!$AB$527, "*"&M$41&"*") -> 1 | ... O70: =COUNTIF(Logs!$Q$519:'Logs'!$AB$527, "*"&O$41&"*") -> 0 | P70: =COUNTIF(Logs!$Q$519:'Logs'!$AB$527, "Hand Eye Coordination") -> 1 | Q70: =COUNTIF(Logs!$Q$519:'Logs'!$AB$527, "*"&Q$41&"*") -> 2 | R70: =COUNTIF(Logs!$Q$519:'Logs'!$AB$527, "*"&R$41&"*") -> 2 | S70: =COUNTIF(Logs!$Q$519:'Logs'!$AB$527, "*"&S$41&"*") -> 0 | T70: =COUNTIF(Logs!$Q$519:'Logs'!$AB$527,"Memorization") -> 2 | U70: =COUNTIF(Logs!$Q$519:'Logs'!$AB$527, "*"&U$41&"*") -> 1 | V70: =COUNTIF(Logs!$Q$519:'Logs'!$AB$527, "*"&V$41&"*") -> 0 | W70: =COUNTIF(Logs!$Q$519:'Logs'!$AB$527, W$41) -> 0 | X70: =COUNTIF(Logs!$Q$519:'Logs'!$AB$527, "*"&X$41&"*") -> 1 | Y70: =COUNTIF(Logs!$Q$519:'Logs'!$AB$527,"Physical Strength") -> 11 | Z70: =COUNTIF(Logs!$Q$519:'Logs'!$AB$527, "*"&Z$41&"*") -> 1 | AA70: =COUNTIF(Logs!$Q$519:'Logs'!$AB$527, "*"&AA$41&"*") -> 2 | AB70: =COUNTIF(Logs!$Q$519:'Logs'!$AB$527, "*"&AB$41&"*") -> 0 | AC70: =COUNTIF(Logs!$Q$519:'Logs'!$AB$527, "*"&AC$41&"*") -> 1 | AD70: =COUNTIF(Logs!$Q$519:'Logs'!$AB$527, "*"&AD$41&"*") -> 0 | AE70: =COUNTIF(Logs!$Q$519:'Logs'!$AB$527, "*"&AE$41&"*") -> 6
B71: Season 30 | C71: =SUM($D71:$AE71) -> 64 | D71: =COUNTIF(Logs!$Q$537:'Logs'!$AB$545, "*"&D$41&"*") -> 3 | E71: =COUNTIF(Logs!$Q$537:'Logs'!$AB$545, "Attention to Detail") -> 10 | F71: =COUNTIF(Logs!$Q$537:'Logs'!$AB$545, "*"&F$41&"*") -> 0 | G71: =COUNTIF(Logs!$Q$537:'Logs'!$AB$545, "*"&G$41&"*") -> 0 | H71: =COUNTIF(Logs!$Q$537:'Logs'!$AB$545, "*"&H$41&"*") -> 3 | I71: =COUNTIF(Logs!$Q$537:'Logs'!$AB$545, "*"&I$41&"*") -> 2 | J71: =COUNTIF(Logs!$Q$537:'Logs'!$AB$545, "*"&J$41&"*") -> 0 | K71: =COUNTIF(Logs!$Q$537:'Logs'!$AB$545, "*"&K$41&"*") -> 1 | L71: =COUNTIF(Logs!$Q$537:'Logs'!$AB$545, "*"&L$41&"*") -> 5 | M71: =COUNTIF(Logs!$Q$537:'Logs'!$AB$545, "*"&M$41&"*") -> 0 | ... O71: =COUNTIF(Logs!$Q$537:'Logs'!$AB$545, "*"&O$41&"*") -> 0 | P71: =COUNTIF(Logs!$Q$537:'Logs'!$AB$545, "Hand Eye Coordination") -> 0 | Q71: =COUNTIF(Logs!$Q$537:'Logs'!$AB$545, "*"&Q$41&"*") -> 3 | R71: =COUNTIF(Logs!$Q$537:'Logs'!$AB$545, "*"&R$41&"*") -> 2 | S71: =COUNTIF(Logs!$Q$537:'Logs'!$AB$545, "*"&S$41&"*") -> 2 | T71: =COUNTIF(Logs!$Q$537:'Logs'!$AB$545, "Memorization") -> 3 | U71: =COUNTIF(Logs!$Q$537:'Logs'!$AB$545, "*"&U$41&"*") -> 0 | V71: =COUNTIF(Logs!$Q$537:'Logs'!$AB$545, "*"&V$41&"*") -> 0 | W71: =COUNTIF(Logs!$Q$537:'Logs'!$AB$545, W$41) -> 0 | X71: =COUNTIF(Logs!$Q$537:'Logs'!$AB$545, "*"&X$41&"*") -> 0 | Y71: =COUNTIF(Logs!$Q$537:'Logs'!$AB$545,"Physical Strength") -> 9 | Z71: =COUNTIF(Logs!$Q$537:'Logs'!$AB$545, "*"&Z$41&"*") -> 3 | AA71: =COUNTIF(Logs!$Q$537:'Logs'!$AB$545, "*"&AA$41&"*") -> 8 | AB71: =COUNTIF(Logs!$Q$537:'Logs'!$AB$545, "*"&AB$41&"*") -> 0 | AC71: =COUNTIF(Logs!$Q$537:'Logs'!$AB$545, "*"&AC$41&"*") -> 1 | AD71: =COUNTIF(Logs!$Q$537:'Logs'!$AB$545, "*"&AD$41&"*") -> 0 | AE71: =COUNTIF(Logs!$Q$537:'Logs'!$AB$545, "*"&AE$41&"*") -> 6
B72: Season 31 | C72: =SUM($D72:$AE72) -> 59 | D72: =COUNTIF(Logs!$Q$555:'Logs'!$AB$563, "*"&D$41&"*") -> 2 | E72: =COUNTIF(Logs!$Q$555:'Logs'!$AB$563, "Attention to Detail") -> 8 | F72: =COUNTIF(Logs!$Q$555:'Logs'!$AB$563, "*"&F$41&"*") -> 1 | G72: =COUNTIF(Logs!$Q$555:'Logs'!$AB$563, "*"&G$41&"*") -> 1 | H72: =COUNTIF(Logs!$Q$555:'Logs'!$AB$563, "*"&H$41&"*") -> 4 | I72: =COUNTIF(Logs!$Q$555:'Logs'!$AB$563, "*"&I$41&"*") -> 2 | J72: =COUNTIF(Logs!$Q$555:'Logs'!$AB$563, "*"&J$41&"*") -> 0 | K72: =COUNTIF(Logs!$Q$555:'Logs'!$AB$563, "*"&K$41&"*") -> 1 | L72: =COUNTIF(Logs!$Q$555:'Logs'!$AB$563, "*"&L$41&"*") -> 3 | M72: =COUNTIF(Logs!$Q$555:'Logs'!$AB$563, "*"&M$41&"*") -> 0 | ... O72: =COUNTIF(Logs!$Q$555:'Logs'!$AB$563, "*"&O$41&"*") -> 0 | P72: =COUNTIF(Logs!$Q$555:'Logs'!$AB$563, "Hand Eye Coordination") -> 1 | Q72: =COUNTIF(Logs!$Q$555:'Logs'!$AB$563, "*"&Q$41&"*") -> 3 | R72: =COUNTIF(Logs!$Q$555:'Logs'!$AB$563, "*"&R$41&"*") -> 2 | S72: =COUNTIF(Logs!$Q$555:'Logs'!$AB$563, "*"&S$41&"*") -> 0 | T72: =COUNTIF(Logs!$Q$555:'Logs'!$AB$563, "Memorization") -> 4 | U72: =COUNTIF(Logs!$Q$555:'Logs'!$AB$563, "*"&U$41&"*") -> 1 | V72: =COUNTIF(Logs!$Q$555:'Logs'!$AB$563, "*"&V$41&"*") -> 0 | W72: =COUNTIF(Logs!$Q$555:'Logs'!$AB$563,W$41) -> 0 | X72: =COUNTIF(Logs!$Q$555:'Logs'!$AB$563, "*"&X$41&"*") -> 0 | Y72: =COUNTIF(Logs!$Q$555:'Logs'!$AB$563, "Physical Strength") -> 7 | Z72: =COUNTIF(Logs!$Q$555:'Logs'!$AB$563, "*"&Z$41&"*") -> 3 | AA72: =COUNTIF(Logs!$Q$555:'Logs'!$AB$563, "*"&AA$41&"*") -> 5 | AB72: =COUNTIF(Logs!$Q$555:'Logs'!$AB$563, "*"&AB$41&"*") -> 0 | AC72: =COUNTIF(Logs!$Q$555:'Logs'!$AB$563, "*"&AC$41&"*") -> 0 | AD72: =COUNTIF(Logs!$Q$555:'Logs'!$AB$563, "*"&AD$41&"*") -> 0 | AE72: =COUNTIF(Logs!$Q$555:'Logs'!$AB$563, "*"&AE$41&"*") -> 9
B73: Season 32 | C73: =SUM($D73:$AE73) -> 50 | D73: =COUNTIF(Logs!$Q$572:'Logs'!$AA$581, "*"&D$41&"*") -> 2 | E73: =COUNTIF(Logs!$Q$572:'Logs'!$AA$581, "Attention to Detail") -> 9 | F73: =COUNTIF(Logs!$Q$572:'Logs'!$AA$581, "*"&F$41&"*") -> 2 | G73: =COUNTIF(Logs!$Q$572:'Logs'!$AA$581, "*"&G$41&"*") -> 0 | H73: =COUNTIF(Logs!$Q$572:'Logs'!$AA$581, "*"&H$41&"*") -> 3 | I73: =COUNTIF(Logs!$Q$572:'Logs'!$AA$581, "*"&I$41&"*") -> 2 | J73: =COUNTIF(Logs!$Q$572:'Logs'!$AA$581, "*"&J$41&"*") -> 0 | K73: =COUNTIF(Logs!$Q$572:'Logs'!$AA$581, "*"&K$41&"*") -> 1 | L73: =COUNTIF(Logs!$Q$572:'Logs'!$AA$581, "*"&L$41&"*") -> 1 | M73: =COUNTIF(Logs!$Q$572:'Logs'!$AA$581, "*"&M$41&"*") -> 0 | ... O73: =COUNTIF(Logs!$Q$572:'Logs'!$AA$581, "*"&O$41&"*") -> 1 | P73: =COUNTIF(Logs!$Q$572:'Logs'!$AA$581, "Hand Eye Coordination") -> 3 | Q73: =COUNTIF(Logs!$Q$572:'Logs'!$AA$581, "*"&Q$41&"*") -> 2 | R73: =COUNTIF(Logs!$Q$572:'Logs'!$AA$581, "*"&R$41&"*") -> 2 | S73: =COUNTIF(Logs!$Q$572:'Logs'!$AA$581, "*"&S$41&"*") -> 0 | T73: =COUNTIF(Logs!$Q$572:'Logs'!$AA$581, "Memorization") -> 4 | U73: =COUNTIF(Logs!$Q$572:'Logs'!$AA$581, "*"&U$41&"*") -> 1 | V73: =COUNTIF(Logs!$Q$572:'Logs'!$AA$581, "*"&V$41&"*") -> 1 | W73: =COUNTIF(Logs!$Q$572:'Logs'!$AA$581, W$41) -> 0 | X73: =COUNTIF(Logs!$Q$572:'Logs'!$AA$581, "*"&X$41&"*") -> 0 | Y73: =COUNTIF(Logs!$Q$572:'Logs'!$AA$581, "Physical Strength") -> 3 | Z73: =COUNTIF(Logs!$Q$572:'Logs'!$AA$581, "*"&Z$41&"*") -> 3 | AA73: =COUNTIF(Logs!$Q$572:'Logs'!$AA$581, "*"&AA$41&"*") -> 4 | AB73: =COUNTIF(Logs!$Q$572:'Logs'!$AA$581, "*"&AB$41&"*") -> 0 | AC73: =COUNTIF(Logs!$Q$572:'Logs'!$AA$581, "*"&AC$41&"*") -> 1 | AD73: =COUNTIF(Logs!$Q$572:'Logs'!$AA$581, "*"&AD$41&"*") -> 0 | AE73: =COUNTIF(Logs!$Q$572:'Logs'!$AA$581, "*"&AE$41&"*") -> 3
B74: Season 33 | C74: =SUM($D74:$AE74) -> 54 | D74: =COUNTIF(Logs!$Q$591:'Logs'!$AA$598, "*"&D$41&"*") -> 1 | E74: =COUNTIF(Logs!$Q$591:'Logs'!$AA$598, "Attention to Detail") -> 9 | F74: =COUNTIF(Logs!$Q$591:'Logs'!$AA$598, "*"&F$41&"*") -> 0 | G74: =COUNTIF(Logs!$Q$591:'Logs'!$AA$598, "*"&G$41&"*") -> 0 | H74: =COUNTIF(Logs!$Q$591:'Logs'!$AA$598, "*"&H$41&"*") -> 1 | I74: =COUNTIF(Logs!$Q$591:'Logs'!$AA$598, "*"&I$41&"*") -> 3 | J74: =COUNTIF(Logs!$Q$591:'Logs'!$AA$598, "*"&J$41&"*") -> 1 | K74: =COUNTIF(Logs!$Q$591:'Logs'!$AA$598, "*"&K$41&"*") -> 0 | L74: =COUNTIF(Logs!$Q$591:'Logs'!$AA$598, "*"&L$41&"*") -> 8 | M74: =COUNTIF(Logs!$Q$591:'Logs'!$AA$598, "*"&M$41&"*") -> 1 | ... O74: =COUNTIF(Logs!$Q$591:'Logs'!$AA$598, "*"&O$41&"*") -> 0 | P74: =COUNTIF(Logs!$Q$591:'Logs'!$AA$598, "Hand Eye Coordination") -> 1 | Q74: =COUNTIF(Logs!$Q$591:'Logs'!$AA$598, "*"&Q$41&"*") -> 1 | R74: =COUNTIF(Logs!$Q$591:'Logs'!$AA$598, "*"&R$41&"*") -> 0 | S74: =COUNTIF(Logs!$Q$591:'Logs'!$AA$598, "*"&S$41&"*") -> 0 | T74: =COUNTIF(Logs!$Q$591:'Logs'!$AA$598, "Memorization") -> 2 | U74: =COUNTIF(Logs!$Q$591:'Logs'!$AA$598, "*"&U$41&"*") -> 1 | V74: =COUNTIF(Logs!$Q$591:'Logs'!$AA$598, "*"&V$41&"*") -> 0 | W74: =COUNTIF(Logs!$Q$591:'Logs'!$AA$598, W$41) -> 0 | X74: =COUNTIF(Logs!$Q$591:'Logs'!$AA$598, "*"&X$41&"*") -> 0 | Y74: =COUNTIF(Logs!$Q$591:'Logs'!$AA$598, "Physical Strength") -> 8 | Z74: =COUNTIF(Logs!$Q$591:'Logs'!$AA$598, "*"&Z$41&"*") -> 2 | AA74: =COUNTIF(Logs!$Q$591:'Logs'!$AA$598, "*"&AA$41&"*") -> 6 | AB74: =COUNTIF(Logs!$Q$591:'Logs'!$AA$598, "*"&AB$41&"*") -> 0 | AC74: =COUNTIF(Logs!$Q$591:'Logs'!$AA$598, "*"&AC$41&"*") -> 1 | AD74: =COUNTIF(Logs!$Q$591:'Logs'!$AA$598, "*"&AD$41&"*") -> 0 | AE74: =COUNTIF(Logs!$Q$591:'Logs'!$AA$598, "*"&AE$41&"*") -> 6
B75: Season 34 | C75: =SUM($D75:$AE75) -> 51 | D75: =COUNTIF(Logs!$Q$607:'Logs'!$Z$615, "*"&D$41&"*") -> 1 | E75: =COUNTIF(Logs!$Q$607:'Logs'!$Z$615, "Attention to Detail") -> 4 | F75: =COUNTIF(Logs!$Q$607:'Logs'!$Z$615, "*"&F$41&"*") -> 1 | G75: =COUNTIF(Logs!$Q$607:'Logs'!$Z$615, "*"&G$41&"*") -> 1 | H75: =COUNTIF(Logs!$Q$607:'Logs'!$Z$615, "*"&H$41&"*") -> 3 | I75: =COUNTIF(Logs!$Q$607:'Logs'!$Z$615, "*"&I$41&"*") -> 1 | J75: =COUNTIF(Logs!$Q$607:'Logs'!$Z$615, "*"&J$41&"*") -> 0 | K75: =COUNTIF(Logs!$Q$607:'Logs'!$Z$615, "*"&K$41&"*") -> 2 | L75: =COUNTIF(Logs!$Q$607:'Logs'!$Z$615, "*"&L$41&"*") -> 7 | M75: =COUNTIF(Logs!$Q$607:'Logs'!$Z$615, "*"&M$41&"*") -> 0 | ... O75: =COUNTIF(Logs!$Q$607:'Logs'!$Z$615, "*"&O$41&"*") -> 0 | P75: =COUNTIF(Logs!$Q$607:'Logs'!$Z$615, "Hand Eye Coordination") -> 2 | Q75: =COUNTIF(Logs!$Q$607:'Logs'!$Z$615, "*"&Q$41&"*") -> 2 | R75: =COUNTIF(Logs!$Q$607:'Logs'!$Z$615, "*"&R$41&"*") -> 2 | S75: =COUNTIF(Logs!$Q$607:'Logs'!$Z$615, "*"&S$41&"*") -> 0 | T75: =COUNTIF(Logs!$Q$607:'Logs'!$Z$615, "Memorization") -> 6 | U75: =COUNTIF(Logs!$Q$607:'Logs'!$Z$615, "*"&U$41&"*") -> 1 | V75: =COUNTIF(Logs!$Q$607:'Logs'!$Z$615, "*"&V$41&"*") -> 0 | W75: =COUNTIF(Logs!$Q$607:'Logs'!$Z$615, W$41) -> 0 | X75: =COUNTIF(Logs!$Q$607:'Logs'!$Z$615, "*"&X$41&"*") -> 0 | Y75: =COUNTIF(Logs!$Q$607:'Logs'!$Z$615, "Physical Strength") -> 5 | Z75: =COUNTIF(Logs!$Q$607:'Logs'!$Z$615, "*"&Z$41&"*") -> 1 | AA75: =COUNTIF(Logs!$Q$607:'Logs'!$Z$615, "*"&AA$41&"*") -> 1 | AB75: =COUNTIF(Logs!$Q$607:'Logs'!$Z$615, "*"&AB$41&"*") -> 0 | AC75: =COUNTIF(Logs!$Q$607:'Logs'!$Z$615, "*"&AC$41&"*") -> 1 | AD75: =COUNTIF(Logs!$Q$607:'Logs'!$Z$615, "*"&AD$41&"*") -> 1 | AE75: =COUNTIF(Logs!$Q$607:'Logs'!$Z$615, "*"&AE$41&"*") -> 8
B76: Season 35 | C76: =SUM($D76:$AE76) -> 70 | D76: =COUNTIF(Logs!$Q$623:'Logs'!$AB$631, "*"&D$41&"*") -> 0 | E76: =COUNTIF(Logs!$Q$623:'Logs'!$AB$631, "Attention to Detail") -> 9 | F76: =COUNTIF(Logs!$Q$623:'Logs'!$AB$631, "*"&F$41&"*") -> 1 | G76: =COUNTIF(Logs!$Q$623:'Logs'!$AB$631, "*"&G$41&"*") -> 2 | H76: =COUNTIF(Logs!$Q$623:'Logs'!$AB$631, "*"&H$41&"*") -> 3 | I76: =COUNTIF(Logs!$Q$623:'Logs'!$AB$631, "*"&I$41&"*") -> 0 | J76: =COUNTIF(Logs!$Q$623:'Logs'!$AB$631, "*"&J$41&"*") -> 0 | K76: =COUNTIF(Logs!$Q$623:'Logs'!$AB$631, "*"&K$41&"*") -> 3 | L76: =COUNTIF(Logs!$Q$623:'Logs'!$AB$631, "*"&L$41&"*") -> 6 | M76: =COUNTIF(Logs!$Q$623:'Logs'!$AB$631, "*"&M$41&"*") -> 0 | ... O76: =COUNTIF(Logs!$Q$623:'Logs'!$AB$631, "*"&O$41&"*") -> 0 | P76: =COUNTIF(Logs!$Q$623:'Logs'!$AB$631, "Hand Eye Coordination") -> 2 | Q76: =COUNTIF(Logs!$Q$623:'Logs'!$AB$631, "*"&Q$41&"*") -> 5 | R76: =COUNTIF(Logs!$Q$623:'Logs'!$AB$631, "*"&R$41&"*") -> 1 | S76: =COUNTIF(Logs!$Q$623:'Logs'!$AB$631, "*"&S$41&"*") -> 1 | T76: =COUNTIF(Logs!$Q$623:'Logs'!$AB$631, "Memorization") -> 3 | U76: =COUNTIF(Logs!$Q$623:'Logs'!$AB$631, "*"&U$41&"*") -> 0 | V76: =COUNTIF(Logs!$Q$623:'Logs'!$AB$631, "*"&V$41&"*") -> 0 | W76: =COUNTIF(Logs!$Q$623:'Logs'!$AB$631, W$41) -> 2 | X76: =COUNTIF(Logs!$Q$623:'Logs'!$AB$631, "*"&X$41&"*") -> 0 | Y76: =COUNTIF(Logs!$Q$623:'Logs'!$AB$631,"Physical Strength") -> 8 | Z76: =COUNTIF(Logs!$Q$623:'Logs'!$AB$631, "*"&Z$41&"*") -> 3 | AA76: =COUNTIF(Logs!$Q$623:'Logs'!$AB$631, "*"&AA$41&"*") -> 9 | AB76: =COUNTIF(Logs!$Q$623:'Logs'!$AB$631, "*"&AB$41&"*") -> 0 | AC76: =COUNTIF(Logs!$Q$623:'Logs'!$AB$631, "*"&AC$41&"*") -> 0 | AD76: =COUNTIF(Logs!$Q$623:'Logs'!$AB$631, "*"&AD$41&"*") -> 1 | AE76: =COUNTIF(Logs!$Q$623:'Logs'!$AB$631, "*"&AE$41&"*") -> 9
B77: Season 36 | C77: =SUM($D77:$AE77) -> 63 | D77: =COUNTIF(Logs!$Q$640:'Logs'!$AB$648, "*"&D$41&"*") -> 0 | E77: =COUNTIF(Logs!$Q$640:'Logs'!$AB$648, "Attention to Detail") -> 8 | F77: =COUNTIF(Logs!$Q$640:'Logs'!$AB$648, "*"&F$41&"*") -> 2 | G77: =COUNTIF(Logs!$Q$640:'Logs'!$AB$648, "*"&G$41&"*") -> 0 | H77: =COUNTIF(Logs!$Q$640:'Logs'!$AB$648, "*"&H$41&"*") -> 2 | I77: =COUNTIF(Logs!$Q$640:'Logs'!$AB$648, "*"&I$41&"*") -> 2 | J77: =COUNTIF(Logs!$Q$640:'Logs'!$AB$648, "*"&J$41&"*") -> 0 | K77: =COUNTIF(Logs!$Q$640:'Logs'!$AB$648, "*"&K$41&"*") -> 1 | L77: =COUNTIF(Logs!$Q$640:'Logs'!$AB$648, "*"&L$41&"*") -> 7 | M77: =COUNTIF(Logs!$Q$640:'Logs'!$AB$648, "*"&M$41&"*") -> 0 | ... O77: =COUNTIF(Logs!$Q$640:'Logs'!$AB$648, "*"&O$41&"*") -> 0 | P77: =COUNTIF(Logs!$Q$640:'Logs'!$AB$648, "Hand Eye Coordination") -> 5 | Q77: =COUNTIF(Logs!$Q$640:'Logs'!$AB$648, "*"&Q$41&"*") -> 0 | R77: =COUNTIF(Logs!$Q$640:'Logs'!$AB$648, "*"&R$41&"*") -> 0 | S77: =COUNTIF(Logs!$Q$640:'Logs'!$AB$648, "*"&S$41&"*") -> 0 | T77: =COUNTIF(Logs!$Q$640:'Logs'!$AB$648, "Memorization") -> 5 | U77: =COUNTIF(Logs!$Q$640:'Logs'!$AB$648, "*"&U$41&"*") -> 2 | V77: =COUNTIF(Logs!$Q$640:'Logs'!$AB$648, "*"&V$41&"*") -> 0 | W77: =COUNTIF(Logs!$Q$640:'Logs'!$AB$648, W$41) -> 0 | X77: =COUNTIF(Logs!$Q$640:'Logs'!$AB$648, "*"&X$41&"*") -> 1 | Y77: =COUNTIF(Logs!$Q$640:'Logs'!$AB$648,"Physical Strength") -> 10 | Z77: =COUNTIF(Logs!$Q$640:'Logs'!$AB$648, "*"&Z$41&"*") -> 3 | AA77: =COUNTIF(Logs!$Q$640:'Logs'!$AB$648, "*"&AA$41&"*") -> 3 | AB77: =COUNTIF(Logs!$Q$640:'Logs'!$AB$648, "*"&AB$41&"*") -> 1 | AC77: =COUNTIF(Logs!$Q$640:'Logs'!$AB$648, "*"&AC$41&"*") -> 1 | AD77: =COUNTIF(Logs!$Q$640:'Logs'!$AB$648, "*"&AD$41&"*") -> 2 | AE77: =COUNTIF(Logs!$Q$640:'Logs'!$AB$648, "*"&AE$41&"*") -> 8
B78: Season 37 | C78: =SUM($D78:$AE78) -> 68 | D78: =COUNTIF(Logs!$Q$655:'Logs'!$AB$662, "*"&D$41&"*") -> 1 | E78: =COUNTIF(Logs!$Q$655:'Logs'!$AB$662,"*Attention to Detail*") -> 8 | F78: =COUNTIF(Logs!$Q$655:'Logs'!$AB$662, "*"&F$41&"*") -> 3 | G78: =COUNTIF(Logs!$Q$655:'Logs'!$AB$662, "*"&G$41&"*") -> 0 | H78: =COUNTIF(Logs!$Q$655:'Logs'!$AB$662, "*"&H$41&"*") -> 1 | I78: =COUNTIF(Logs!$Q$655:'Logs'!$AB$662, "*"&I$41&"*") -> 1 | J78: =COUNTIF(Logs!$Q$655:'Logs'!$AB$662, "*"&J$41&"*") -> 0 | K78: =COUNTIF(Logs!$Q$655:'Logs'!$AB$662, "*"&K$41&"*") -> 2 | L78: =COUNTIF(Logs!$Q$655:'Logs'!$AB$662, "*"&L$41&"*") -> 7 | M78: =COUNTIF(Logs!$Q$655:'Logs'!$AB$662, "*"&M$41&"*") -> 0 | ... O78: =COUNTIF(Logs!$Q$655:'Logs'!$AB$662, "*"&O$41&"*") -> 0 | P78: =COUNTIF(Logs!$Q$655:'Logs'!$AB$662, "*Hand Eye Coordination*") -> 3 | Q78: =COUNTIF(Logs!$Q$655:'Logs'!$AB$662, "*"&Q$41&"*") -> 2 | R78: =COUNTIF(Logs!$Q$655:'Logs'!$AB$662, "*"&R$41&"*") -> 3 | S78: =COUNTIF(Logs!$Q$655:'Logs'!$AB$662, "*"&S$41&"*") -> 0 | T78: =COUNTIF(Logs!$Q$655:'Logs'!$AB$662, "*Memorization*") -> 4 | U78: =COUNTIF(Logs!$Q$655:'Logs'!$AB$662, "*"&U$41&"*") -> 1 | V78: =COUNTIF(Logs!$Q$655:'Logs'!$AB$662, "*"&V$41&"*") -> 0 | W78: =COUNTIF(Logs!$Q$655:'Logs'!$AB$662, W$41) -> 1 | X78: =COUNTIF(Logs!$Q$655:'Logs'!$AB$662, "*"&X$41&"*") -> 0 | Y78: =COUNTIF(Logs!$Q$655:'Logs'!$AB$662, "*Physical Strength*") -> 9 | Z78: =COUNTIF(Logs!$Q$655:'Logs'!$AB$662, "*"&Z$41&"*") -> 3 | AA78: =COUNTIF(Logs!$Q$655:'Logs'!$AB$662, "*"&AA$41&"*") -> 4 | AB78: =COUNTIF(Logs!$Q$655:'Logs'!$AB$662, "*"&AB$41&"*") -> 0 | AC78: =COUNTIF(Logs!$Q$655:'Logs'!$AB$662, "*"&AC$41&"*") -> 1 | AD78: =COUNTIF(Logs!$Q$655:'Logs'!$AB$662, "*"&AD$41&"*") -> 2 | AE78: =COUNTIF(Logs!$Q$655:'Logs'!$AB$662, "*Travel Issues*") -> 10
B79: Season 38 | C79: =SUM($D79:$AE79) -> 78 | D79: =COUNTIF(Logs!$Q$671:'Logs'!$AB$681, "*"&D$41&"*") -> 2 | E79: =COUNTIF(Logs!$Q$671:'Logs'!$AB$681, "Attention to Detail") -> 7 | F79: =COUNTIF(Logs!$Q$671:'Logs'!$AB$681, "*"&F$41&"*") -> 3 | G79: =COUNTIF(Logs!$Q$671:'Logs'!$AB$681, "*"&G$41&"*") -> 1 | H79: =COUNTIF(Logs!$Q$671:'Logs'!$AB$681, "*"&H$41&"*") -> 4 | I79: =COUNTIF(Logs!$Q$671:'Logs'!$AB$681, "*"&I$41&"*") -> 2 | J79: =COUNTIF(Logs!$Q$671:'Logs'!$AB$681, "*"&J$41&"*") -> 0 | K79: =COUNTIF(Logs!$Q$671:'Logs'!$AB$681, "*"&K$41&"*") -> 3 | L79: =COUNTIF(Logs!$Q$671:'Logs'!$AB$681, "*"&L$41&"*") -> 5 | M79: =COUNTIF(Logs!$Q$671:'Logs'!$AB$681, "*"&M$41&"*") -> 0 | ... O79: =COUNTIF(Logs!$Q$671:'Logs'!$AB$681, "*"&O$41&"*") -> 0 | P79: =COUNTIF(Logs!$Q$671:'Logs'!$AB$681, "Hand Eye Coordination") -> 5 | Q79: =COUNTIF(Logs!$Q$671:'Logs'!$AB$681, "*"&Q$41&"*") -> 3 | R79: =COUNTIF(Logs!$Q$671:'Logs'!$AB$681, "*"&R$41&"*") -> 3 | S79: =COUNTIF(Logs!$Q$671:'Logs'!$AB$681, "*"&S$41&"*") -> 0 | T79: =COUNTIF(Logs!$Q$671:'Logs'!$AB$681, "Memorization") -> 4 | U79: =COUNTIF(Logs!$Q$671:'Logs'!$AB$681, "*"&U$41&"*") -> 1 | V79: =COUNTIF(Logs!$Q$671:'Logs'!$AB$681, "*"&V$41&"*") -> 1 | W79: =COUNTIF(Logs!$Q$671:'Logs'!$AB$681, "*"&W$41&"*") -> 1 | X79: =COUNTIF(Logs!$Q$671:'Logs'!$AB$681, "*"&X$41&"*") -> 0 | Y79: =COUNTIF(Logs!$Q$671:'Logs'!$AB$681, "Physical Strength") -> 7 | Z79: =COUNTIF(Logs!$Q$671:'Logs'!$AB$681, "*"&Z$41&"*") -> 4 | AA79: =COUNTIF(Logs!$Q$671:'Logs'!$AB$681, "*"&AA$41&"*") -> 6 | AB79: =COUNTIF(Logs!$Q$671:'Logs'!$AB$681, "*"&AB$41&"*") -> 1 | AC79: =COUNTIF(Logs!$Q$671:'Logs'!$AB$681, "*"&AC$41&"*") -> 0 | AD79: =COUNTIF(Logs!$Q$671:'Logs'!$AB$681, "*"&AD$41&"*") -> 0 | AE79: =COUNTIF(Logs!$Q$671:'Logs'!$AB$681, "*"&AE$41&"*") -> 12
B80: Total | C80: =SUM($D80:$AE80) -> 2231 | D80: =SUM(D$42:D$79) -> 93 | E80: =SUM(E$42:E$79) -> 186 | F80: =SUM(F$42:F$79) -> 49 | G80: =SUM(G$42:G$79) -> 43 | H80: =SUM(H$42:H$79) -> 86 | I80: =SUM(I$42:I$79) -> 44 | J80: =SUM(J$42:J$79) -> 11 | K80: =SUM(K$42:K$79) -> 44 | ... AE80: =SUM(AE$42:AE$79) -> 290
B81: Average | C81: =AVERAGE(C42:C79) -> 58.710526 | D81: =AVERAGE(D$42:D$79) -> 2.4473684 | E81: =AVERAGE(E$42:E$79) -> 4.8947368 | F81: =AVERAGE(F$42:F$79) -> 1.2894737 | G81: =AVERAGE(G$42:G$79) -> 1.1315789 | H81: =AVERAGE(H$42:H$79) -> 2.2631579 | I81: =AVERAGE(I$42:I$79) -> 1.1578947 | J81: =AVERAGE(J$42:J$79) -> 0.28947368 | K81: =AVERAGE(K$42:K$79) -> 1.1578947 | ... AE81: =AVERAGE(AE$42:AE$79) -> 7.6315789
B82: Max | C82: =MAX(C42:C79) -> 78 | D82: =MAX(D$42:D$79) -> 6 | E82: =MAX(E$42:E$79) -> 10 | F82: =MAX(F$42:F$79) -> 5 | G82: =MAX(G$42:G$79) -> 4 | H82: =MAX(H$42:H$79) -> 7 | I82: =MAX(I$42:I$79) -> 3 | J82: =MAX(J$42:J$79) -> 1 | K82: =MAX(K$42:K$79) -> 3 | ... AE82: =MAX(AE$42:AE$79) -> 12
B83: Mode | C83: =MODE(C42:C79) -> 54 | D83: =MODE(D$42:D$79) -> 2 | E83: =MODE(E$42:E$79) -> 9 | F83: =MODE(F$42:F$79) -> 0 | G83: =MODE(G$42:G$79) -> 1 | H83: =MODE(H$42:H$79) -> 1 | I83: =MODE(I$42:I$79) -> 0 | J83: =MODE(J$42:J$79) -> 0 | K83: =MODE(K$42:K$79) -> 1 | ... AE83: =MODE(AE$42:AE$79) -> 8
B84: Keywords per Season:
AO85: Physical Strength | AQ85: =SUM(Y$42:Y$79) -> 311
AO86: Travel Issues | AQ86: =SUM(AE$42:AE$79) -> 290
AO87: Driving | AQ87: =SUM(L$42:L$79) -> 202
AO88: Searching | AQ88: =SUM(AA$42:AA$79) -> 227
AO89: Attention to Detail | AQ89: =SUM(E$42:E$79) -> 186
AO90: Heights | AQ90: =SUM(Q$42:Q$79) -> 122
AO91: Animals | AQ91: =SUM(D$42:D$79) -> 93
AO92: Puzzle | AQ92: =SUM(Z$42:Z$79) -> 81
AO93: Memory | AQ93: =SUM(T$42:T$79) -> 69
AO94: Food | AQ94: =SUM(N$42:N$79) -> 66
AO95: Building | AQ95: =SUM($H42:$H79) -> 86
AO96: Hand Eye Coordination | AQ96: =SUM(P$42:P$79) -> 78
AO97: Biking | AQ97: =SUM(G$42:G$79) -> 43
AO98: Dancing | AQ98: =SUM(K$42:K$79) -> 44
AO99: Balance | AQ99: =SUM(F$42:F$79) -> 49
AO100: Swimming | AQ100: =SUM(AD$42:AD$79) -> 37
AO101: Language | AQ101: =SUM(R$42:R$79) -> 43
AO102: Pain | AQ102: =SUM(W$42:W$79) -> 29
AO103: Cooking | AQ103: =SUM(I$42:I$79) -> 44
AO104: Music | AQ104: =SUM(U$42:U$79) -> 20
AO105: Math | AQ105: =SUM(S$42:S$79) -> 15
AO106: Navigation | AQ106: =SUM(V$42:V$79) -> 23
AO107: Painting | AQ107: =SUM(X$42:X$79) -> 16
AO108: Selling | AQ108: =SUM(AB$42:AB$79) -> 19
AO109: Singing | AQ109: =SUM(AC$42:AC$79) -> 12
AO110: Flags | AQ110: =SUM(M$42:M$79) -> 8
AO111: Geography | AQ111: =SUM(O$42:O$79) -> 7
AO112: Counting | AQ112: =SUM(J$42:J$79) -> 11
B113: Keyword Bar Graphs:

Sheet Race Locations
B4: Location Information
X5: *NOTE: Colored Legs denote the final leg of that season, Leg 13 is always the final leg
C6: Countries/Areas traveled to in each Leg | AK6: # of Countries traveled to on each Season
C7: Leg # | D7: Leg 1 | F7: Leg 2 | H7: Leg 3 | J7: Leg 4 | L7: Leg 5 | N7: Leg 6 | P7: Leg 7 | R7: Leg 8 | T7: Leg 9 | V7: Leg 10 | X7: Leg 10 | Z7: Leg 11 | AB7: Leg 11 | AD7: Leg 12 | AF7: Leg 12 | AH7: Leg 13 | AK7: Season # | AL7: # | BD7: Countries traveled to in each Leg
C8: Season # | D8: Country/ies | E8: Area of World | F8: Country/ies | G8: Area of World | H8: Country/ies | I8: Area of World | J8: Country/ies | K8: Area of World | L8: Country/ies | M8: Area of World | N8: Country/ies | O8: Area of World | P8: Country/ies | Q8: Area of World | R8: Country/ies | S8: Area of World | T8: Country/ies | U8: Area of World | V8: Country/ies | W8: Area of World | X8: Country/ies | Y8: Area of World | Z8: Country/ies | AA8: Area of World | AB8: Country/ies 2 | AC8: Area of World | AD8: Country/ies 3 | AE8: Area of World | AF8: Country/ies | AG8: Area of World | AH8: Country/ies | AI8: Area of World | AK8: Season 1 | AL8: 8 | BD8: Season # | BE8: Leg 1 | BF8: Leg 2 | BG8: Leg 3 | BH8: Leg 4 | BI8: Leg 5 | BJ8: Leg 6 | BK8: Leg 7 | BL8: Leg 8 | BM8: Leg 9 | BN8: Leg 10 | BO8: Leg 11 | BP8: Leg 12 | BQ8: Leg 13 | BS8: # of Unique Countries
C9: Season 1 | D9: Zambia | E9: Southern Africa | F9: France | G9: Western Europe | H9: France | I9: Western Europe | J9: Tunisia | K9: Northern Africa | L9: Tunisia | M9: Northern Africa | N9: Italy | O9: Southern Europe | P9: India | Q9: South Asia | R9: India | S9: South Asia | T9: Thailand | U9: South East Asia | V9: Thailand | W9: South East Asia | Z9: China | AA9: East Asia | AD9: USA | AE9: North America | AH9: USA | AI9: North America | AK9: Season 2 | AL9: 8 | BD9: Season 1 | BE9: Zambia | BF9: France | BG9: France | BH9: Tunisia | BI9: Tunisia | BJ9: Italy | BK9: India | BL9: India | BM9: Thailand | BN9: Thailand | BO9: China | BP9: USA | BQ9: USA | BS9: {=SUMPRODUCT(1/COUNTIFS(BE9:BQ9,BE9:BQ9))} -> 8
C10: Season 2 | D10: Brazil | E10: South America | F10: Brazil | G10: South America | H10: South Africa | I10: Southern Africa | J10: Namibia | K10: Southern Africa | L10: Thailand | M10: South East Asia | N10: Thailand | O10: South East Asia | P10: China | Q10: East Asia | R10: Australia | S10: Oceania | T10: Australia | U10: Oceania | V10: New Zealand | W10: Oceania | Z10: New Zealand | AA10: Oceania | AD10: USA | AE10: North America | AH10: USA | AI10: North America | AK10: Season 3 | AL10: 12 | BD10: Season 2 | BE10: Brazil | BF10: Brazil | BG10: South Africa | BH10: Namibia | BI10: Thailand | BJ10: Thailand | BK10: China | BL10: Australia | BM10: Australia | BN10: New Zealand | BO10: New Zealand | BP10: USA | BQ10: USA | BS10: {=SUMPRODUCT(1/COUNTIFS(BE10:BQ10,BE10:BQ10))} -> 8
C11: Season 3 | D11: Mexico | E11: North America | F11: Mexico | G11: North America | H11: England Scotland | I11: Western Europe Western Europe | J11: Portugal | K11: Western Europe | L11: Morocco | M11: Northern Africa | N11: Morocco | O11: Northern Africa | P11: Germany Austria | Q11: Central Europe Central Europe | R11: Switzerland | S11: Central Europe | T11: Switzerland | U11: Central Europe | V11: Malaysia Singapore | W11: South East Asia South East Asia | Z11: Vietnam | AA11: South East Asia | AD11: Vietnam | AE11: South East Asia | AH11: USA | AI11: North America | AK11: Season 4 | AL11: 9 | BD11: Season 3 | BE11: Mexico | BF11: Mexico | BG11: England | BH11: Portugal | BI11: Morocco | BJ11: Morocco | BK11: Germany | BL11: Switzerland | BM11: Switzerland | BN11: Malaysia | BO11: Vietnam | BP11: Vietnam | BQ11: USA | BS11: {=SUMPRODUCT(1/COUNTIFS(BE11:BQ11,BE11:BQ11))+COUNTA(BE12:BQ12)} -> 12
C12: Season 4 | D12: Italy | E12: Western Europe | F12: Italy | G12: Southern Europe | H12: Austria | I12: Central Europe | J12: France | K12: Western Europe | L12: Netherlands | M12: Central Europe | N12: India | O12: South Asia | P12: India | Q12: South Asia | R12: Malaysia | S12: South East Asia | T12: Malaysia | U12: South East Asia | V12: South Korea | W12: East Asia | Z12: Australia | AA12: Oceania | AD12: Australia | AE12: Oceania | AH12: USA | AI12: North America | AK12: Season 5 | AL12: 11 | BG12: Scotland | BK12: Austria | BN12: Singapore
C13: Season 5 | D13: Uruguay | E13: South America | F13: Argentina | G13: South America | H13: Argentina | I13: South America | J13: Russia | K13: Eastern Europe | L13: Egypt | M13: Northern Africa | N13: Egypt | O13: Northern Africa | P13: Tanzania | Q13: East Africa | R13: UAE | S13: Middle East | T13: India | U13: South Asia | V13: New Zealand | W13: Oceania | Z13: Philippines | AA13: South East Asia | AD13: Philippines | AE13: South East Asia | AH13: Canada USA | AI13: North America North America | AK13: Season 6 | AL13: 11 | BD13: Season 4 | BE13: Italy | BF13: Italy | BG13: Austria | BH13: France | BI13: Netherlands | BJ13: India | BK13: India | BL13: Malaysia | BM13: Malaysia | BN13: South Korea | BO13: Australia | BP13: Australia | BQ13: USA | BS13: {=SUMPRODUCT(1/COUNTIFS(BE13:BQ13,BE13:BQ13))} -> 9
C14: Season 6 | D14: Iceland | E14: Northern Europe | F14: Norway | G14: Northern Europe | H14: Sweden | I14: Northern Europe | J14: Senegal | K14: West Africa | L14: Germany | M14: Central Europe | N14: Hungary | O14: Central Europe | P14: France | Q14: Western Europe | R14: France Ethiopia | S14: Western Europe East Africa | T14: Sri Lanka | U14: South Asia | V14: China | W14: East Asia | Z14: China | AA14: East Asia | AF14: USA | AG14: North America | AK14: Season 7 | AL14: 11 | BD14: Season 5 | BE14: Uruguay | BF14: Argentina | BG14: Argentina | BH14: Russia | BI14: Egypt | BJ14: Egypt | BK14: Tanzania | BL14: UAE | BM14: India | BN14: New Zealand | BO14: Philippines | BP14: Philippines | BQ14: Canada | BS14: {=SUMPRODUCT(1/COUNTIFS(BE14:BQ14,BE14:BQ14))+COUNTA(BE15:BQ15)} -> 11
C15: Season 7 | D15: Peru | E15: South America | F15: Chile | G15: South America | H15: Argentina | I15: South America | J15: Argentina | K15: South America | L15: South Africa | M15: Southern Africa | N15: Botswana | O15: Southern Africa | P15: Botswana | Q15: Southern Africa | R15: India | S15: South Asia | T15: India | U15: South Asia | V15: Turkey | W15: Middle East | Z15: England | AA15: Western Europe | AD15: Jamaica | AE15: Caribbean | AH15: Puerto Rico USA | AI15: Central America North America | AK15: Season 8 | AL15: 4 | BQ15: USA
C16: Season 8 | D16: USA | E16: North America | F16: USA | G16: North America | H16: USA | I16: North America | J16: USA | K16: North America | L16: Panama | M16: Central America | N16: Costa Rica | O16: Central America | P16: USA | Q16: North America | R16: USA | S16: North America | T16: USA | U16: North America | V16: USA | W16: North America | Z16: USA | AA16: North America | AF16: Canada USA | AG16: North America North America | AK16: Season 9 | AL16: 10 | BD16: Season 6 | BE16: Iceland | BF16: Norway | BG16: Sweden | BH16: Senegal | BI16: Germany | BJ16: Hungary | BK16: France | BL16: France | BM16: Sri Lanka | BN16: China | BO16: China | BP16: USA | BS16: {=SUMPRODUCT(1/COUNTIFS(BE16:BP16,BE16:BP16))+COUNTA(BE17:BQ17)} -> 11
C17: Season 9 | D17: Brazil | E17: South America | F17: Brazil | G17: South America | H17: Russia | I17: Eastern Europe | J17: Germany | K17: Central Europe | L17: Italy | M17: Southern Europe | N17: Italy | O17: Southern Europe | P17: Greece | Q17: Southern Europe | R17: Oman | S17: Middle East | T17: Australia | U17: Oceania | V17: Australia | W17: Oceania | Z17: Thailand | AA17: South East Asia | AD17: Japan | AE17: East Asia | AH17: USA | AI17: North America | AK17: Season 10 | AL17: 13 | BL17: Ethiopia
C18: Season 10 | D18: China | E18: East Asia | F18: Mongolia | G18: East Asia | H18: Vietnam | I18: South East Asia | J18: Vietnam | K18: South East Asia | L18: India | M18: South Asia | N18: Kuwait | O18: Middle East | P18: Mauritius | Q18: Southern Africa | R18: Madagascar | S18: Southern Africa | T18: Finland Ukraine | U18: Northern Europe Eastern Europe | V18: Morocco | W18: Northern Africa | Z18: Spain | AA18: Western Europe | AF18: France USA | AG18: Western Europe North America | AK18: Season 11 | AL18: 10 | BD18: Season 7 | BE18: Peru | BF18: Chile | BG18: Argentina | BH18: Argentina | BI18: South Africa | BJ18: Botswana | BK18: Botswana | BL18: India | BM18: India | BN18: Turkey | BO18: England | BP18: Jamaica | BQ18: Puerto Rico | BS18: {=SUMPRODUCT(1/COUNTIFS(BE18:BQ18,BE18:BQ18))+COUNTA(BE19:BQ19)} -> 11
C19: Season 11 | D19: Ecuador | E19: South America | F19: Chile | G19: South America | H19: Chile | I19: South America | J19: Argentina | K19: South America | L19: Mozambique | M19: East Africa | N19: Tanzania | O19: East Africa | P19: Poland | Q19: Eastern Europe | R19: Poland | S19: Eastern Europe | T19: Malaysia | U19: South East Asia | V19: China | W19: East Asia | Z19: China | AA19: East Asia | AD19: Guam | AE19: Oceania | AH19: USA | AI19: North America | AK19: Season 12 | AL19: 10 | BQ19: USA
C20: Season 12 | D20: Ireland | E20: Western Europe | F20: Netherlands | G20: Central Europe | H20: Burkina Faso | I20: West Africa | J20: Burkina Faso | K20: West Africa | L20: Lithuania | M20: Eastern Europe | N20: Croatia | O20: Southern Europe | P20: Italy | Q20: Southern Europe | R20: India | S20: South Asia | T20: Japan | U20: East Asia | V20: Taiwan | W20: East Asia | AB20: USA | AC20: North America | AK20: Season 13 | AL20: 8 | BD20: Season 8 | BE20: USA | BF20: USA | BG20: USA | BH20: USA | BI20: Panama | BJ20: Costa Rica | BK20: USA | BL20: USA | BM20: USA | BN20: USA | BO20: USA | BP20: Canada | BS20: {=SUMPRODUCT(1/COUNTIFS(BE20:BP20,BE20:BP20))+COUNTA(BE21:BQ21)-1} -> 4
C21: Season 13 | D21: Brazil | E21: South America | F21: Brazil | G21: South America | H21: Bolivia | I21: South America | J21: New Zealand | K21: Oceania | L21: Cambodia | M21: South East Asia | N21: India | O21: South Asia | P21: India | Q21: South Asia | R21: Kazakhstan | S21: Central Asia | T21: Russia | U21: Eastern Europe | V21: Russia | W21: Eastern Europe | AB21: USA | AC21: North America | AK21: Season 14 | AL21: 9 | BP21: USA
C22: Season 14 | D22: Switzerland | E22: Central Europe | F22: Germany Austria | G22: Central Europe Central Europe | H22: Germany Romania | I22: Central Europe Eastern Europe | J22: Russia | K22: Eastern Europe | L22: Russia | M22: Eastern Europe | N22: India | O22: South Asia | P22: Thailand | Q22: South East Asia | R22: Thailand | S22: South East Asia | T22: China | U22: East Asia | V22: China | W22: East Asia | Z22: China | AA22: East Asia | AF22: USA | AG22: North America | AK22: Season 15 | AL22: 9 | BD22: Season 9 | BE22: Brazil | BF22: Brazil | BG22: Russia | BH22: Germany | BI22: Italy | BJ22: Italy | BK22: Greece | BL22: Oman | BM22: Australia | BN22: Australia | BO22: Thailand | BP22: Japan | BQ22: USA | BS22: {=SUMPRODUCT(1/COUNTIFS(BE22:BQ22,BE22:BQ22))} -> 10
C23: Season 15 | D23: Japan | E23: East Asia | F23: Vietnam | G23: South East Asia | H23: Vietnam | I23: South East Asia | J23: Cambodia | K23: South East Asia | L23: UAE | M23: Middle East | N23: UAE | O23: Middle East | P23: Netherlands | Q23: Central Europe | R23: Sweden | S23: Northern Europe | T23: Estonia | U23: Eastern Europe | V23: Czech Republic | W23: Central Europe | Z23: Czech Republic | AA23: Central Europe | AF23: USA | AG23: North America | AK23: Season 16 | AL23: 9 | BD23: Season 10 | BE23: China | BF23: Mongolia | BG23: Vietnam | BH23: Vietnam | BI23: India | BJ23: Kuwait | BK23: Mauritius | BL23: Madagascar | BM23: Finland | BN23: Morocco | BO23: Spain | BP23: France | BS23: {=SUMPRODUCT(1/COUNTIFS(BE23:BP23,BE23:BP23))+COUNTA(BE24:BQ24)} -> 13
C24: Season 16 | D24: Chile | E24: South America | F24: Chile | G24: South America | H24: Argentina | I24: South America | J24: Germany | K24: Central Europe | L24: France | M24: Western Europe | N24: France | O24: Western Europe | P24: Seychelles | Q24: East Africa | R24: Malaysia | S24: South East Asia | T24: Singapore | U24: South East Asia | V24: China | W24: East Asia | Z24: China | AA24: East Asia | AF24: USA | AG24: North America | AK24: Season 17 | AL24: 10 | BM24: Ukraine | BP24: USA
C25: Season 17 | D25: England | E25: Western Europe | F25: Ghana | G25: West Africa | H25: Ghana | I25: West Africa | J25: Sweden | K25: Northern Europe | L25: Norway | M25: Northern Europe | N25: Russia | O25: Eastern Europe | P25: Russia | Q25: Eastern Europe | R25: Oman | S25: Middle East | T25: Bangladesh | U25: South Asia | V25: China | W25: East Asia | Z25: South Korea | AA25: East Asia | AF25: USA | AG25: North America | AK25: Season 18 | AL25: 9 | BD25: Season 11 | BE25: Ecuador | BF25: Chile | BG25: Chile | BH25: Argentina | BI25: Mozambique | BJ25: Tanzania | BK25: Poland | BL25: Poland | BM25: Malaysia | BN25: China | BO25: China | BP25: Guam | BQ25: USA | BS25: {=SUMPRODUCT(1/COUNTIFS(BE25:BQ25,BE25:BQ25))} -> 10
C26: Season 18 | D26: Australia | E26: Oceania | F26: Australia | G26: Oceania | H26: Japan | I26: East Asia | J26: China | K26: East Asia | L26: China | M26: East Asia | N26: India | O26: South Asia | P26: India | Q26: South Asia | R26: Austria | S26: Central Europe | T26: Liechtenstein Switzerland | U26: Central Europe Central Europe | V26: Switzerland | W26: Central Europe | Z26: Brazil | AA26: South America | AF26: USA | AG26: North America | AK26: Season 19 | AL26: 10 | BD26: Season 12 | BE26: Ireland | BF26: Netherlands | BG26: Burkina Faso | BH26: Burkina Faso | BI26: Lithuania | BJ26: Croatia | BK26: Italy | BL26: India | BM26: Japan | BN26: Taiwan | BO26: USA | BS26: {=SUMPRODUCT(1/COUNTIFS(BE26:BO26,BE26:BO26))} -> 10
C27: Season 19 | D27: Taiwan | E27: East Asia | F27: Indonesia | G27: South East Asia | H27: Indonesia | I27: South East Asia | J27: Thailand | K27: South East Asia | L27: Thailand | M27: South East Asia | N27: Malawi | O27: East Africa | P27: Malawi | Q27: East Africa | R27: Denmark | S27: Northern Europe | T27: Germany Belgium | U27: Central Europe Central Europe | V27: Belgium | W27: Central Europe | Z27: Netherlands Panama | AA27: Central Europe Central America | AF27: USA | AG27: North America | AK27: Season 20 | AL27: 10 | BD27: Season 13 | BE27: Brazil | BF27: Brazil | BG27: Bolivia | BH27: New Zealand | BI27: Cambodia | BJ27: India | BK27: India | BL27: Kazakhstan | BM27: Russia | BN27: Russia | BO27: USA | BS27: {=SUMPRODUCT(1/COUNTIFS(BE27:BO27,BE27:BO27))} -> 8
C28: Season 20 | D28: Argentina | E28: South America | F28: Argentina | G28: South America | H28: Paraguay | I28: South America | J28: Italy | K28: Southern Europe | L28: Austria Germany | M28: Central Europe | N28: Azerbaijan | O28: West Asia | P28: Tanzania | Q28: East Africa | R28: Tanzania | S28: East Africa | T28: India | U28: South Asia | V28: India | W28: South Asia | Z28: Japan | AA28: East Asia | AF28: USA | AG28: North America | AK28: Season 21 | AL28: 9 | BD28: Season 14 | BE28: Switzerland | BF28: Germany | BG28: Germany | BH28: Russia | BI28: Russia | BJ28: India | BK28: Thailand | BL28: Thailand | BM28: China | BN28: China | BO28: China | BP28: USA | BS28: {=SUMPRODUCT(1/COUNTIFS(BE28:BP28,BE28:BP28))+COUNTA(BE29:BQ29)} -> 9
C29: Season 21 | D29: China | E29: East Asia | F29: Indonesia | G29: South East Asia | H29: Indonesia | I29: South East Asia | J29: Bangladesh | K29: South Asia | L29: Bangladesh | M29: South Asia | N29: Turkey | O29: Middle East | P29: Russia | Q29: Eastern Europe | R29: Russia | S29: Eastern Europe | T29: Netherlands | U29: Central Europe | V29: Spain | W29: Western Europe | Z29: France | AA29: Western Europe | AF29: USA | AG29: North America | AK29: Season 22 | AL29: 12 | BF29: Austria | BG29: Romania
